Workbook

Sheet Resumen sin TD
A1: - | L1: 100 | M1: 50 | N1: 10
G2: Valores | L2: Costos B2B Según volumen | P2: Margenes B2B Según volumen
A3: Marca | B3: Categoria Padre | C3: Categoria Hijo | D3: Descripcion | E3: Sku | F3: Status MLL | G3: Precio Etiqueta | H3: Costo Oferta | I3: Costo MLL | L3: 0 | M3: 0.07 | N3: 0.14 | P3: 30+ | Q3: 21 y 29 | R3: 10 y 20
A4: Bandú | B4: Accesorios de Bebe | C4: Accesorios de Bebe | D4: Mecedor Electrico Coche Recargable Bebe Baby Chick Bandú | E4: BDBBYCHK | F4: Mix MLL | G4: 54990 | H4: 35288 | I4: 20716 | L4: 20716 | M4: 22196 | N4: 23675 | P4: 0.3 | Q4: 0.25 | R4: 0.2
A5: Bandú | B5: Jueguetes de Rol | C5: Cocina y Accesorios | D5: Casa De Muñecas Clásica Madera Rosada Con Accesorios Bandú | E5: BDCASMUÑEC | F5: Mix MLL | G5: 99990 | H5: 35288 | I5: 23592 | L5: 23592 | M5: 25277 | N5: 26962 | P5: 0.2 | Q5: 0.15 | R5: 0.09
A6: Bandú | B6: Jueguetes de Rol | C6: Cocina y Accesorios | D6: Cocina de Juguete Infantil Niños Madera 11 Accesorios Bandú | E6: BDCOCMEDI | F6: Mix MLL | G6: 119990 | H6: 58818 | I6: 32822 | L6: 32822 | M6: 35166 | N6: 37511 | P6: 0.34 | Q6: 0.29 | R6: 0.24
A7: Bandú | B7: Jueguetes de Rol | C7: Cocina y Accesorios | D7: Cocina de Juguete Infantil Niños Madera Accesorios Bandú | E7: BDCOCGRND | F7: Mix MLL | G7: 139990 | H7: 70582 | I7: 36284 | L7: 36284 | M7: 38876 | N7: 41468 | P7: 0.39 | Q7: 0.34 | R7: 0.3
A8: Bandú | B8: Jueguetes de Rol | C8: Cocina y Accesorios | D8: Cocina de Juguete Infantil Niños Madera Rosada con Acc Bandú | E8: BDCOCPQMD | F8: Mix MLL | G8: 99990 | H8: 47053 | I8: 27042 | L8: 27042 | M8: 28973 | N8: 30905 | P8: 0.32 | Q8: 0.27 | R8: 0.22 | T8: 1656603353038
A9: Bandú | B9: Jueguetes de Rol | C9: Cocina y Accesorios | D9: Juguete Infantil mini Electrodomésticos Cocina Madera Bandú | E9: BDELECTCOC | F9: Mix MLL | G9: 24990 | H9: 11759 | I9: 6246 | L9: 6246 | M9: 6692 | N9: 7138 | P9: 0.37 | Q9: 0.32 | R9: 0.28
A10: Bandú | B10: Jueguetes de Rol | C10: Cocina y Accesorios | D10: Set Juego Mini Cocina de Juguete Alimentos Madera Bandú | E10: BDCOCMIN | F10: Mix MLL | G10: 29990 | H10: 11759 | I10: 7906 | L10: 7906 | M10: 8471 | N10: 9035 | P10: 0.2 | Q10: 0.14 | R10: 0.09
A11: Bandú | B11: Jueguetes de Rol | C11: Cocina y Accesorios | D11: Set Juego Pastelería Corta Postre Infantil Niño Madera Bandú | E11: BDSETPAST | F11: Mix MLL | G11: 24990 | H11: 11759 | I11: 6889 | L11: 6889 | M11: 7381 | N11: 7873 | P11: 0.3 | Q11: 0.25 | R11: 0.2
A12: Bandú | B12: Jueguetes de Rol | C12: Cocina y Accesorios | D12: Set Juego Tazas De Té Juguete Didáctico 16pcs Madera Bandú | E12: BDJUESETTE | F12: Mix MLL | G12: 29990 | H12: 11759 | I12: 6930 | L12: 6930 | M12: 7425 | N12: 7920 | P12: 0.3 | Q12: 0.25 | R12: 0.2
A13: Bandú | B13: Jueguetes de Rol | C13: Juegos de Oficio | D13: Set Juego de Roles Doctor Niños Madera 12 pcs Bandú | E13: BDSETDOC | F13: Mix MLL | G13: 24990 | H13: 8818 | I13: 5410 | L13: 5410 | M13: 5796 | N13: 6183 | P13: 0.27 | Q13: 0.22 | R13: 0.17
A14: Bandú | B14: Jueguetes de Rol | C14: Maquillaje y Belleza | D14: Juego de Maquillaje Set Belleza de Roll Niños Madera Bandú | E14: BDSETMAQ | F14: Mix MLL | G14: 24990 | H14: 11759 | I14: 6056 | L14: 6056 | M14: 6489 | N14: 6921 | P14: 0.39 | Q14: 0.34 | R14: 0.3
A15: Bandú | B15: Jueguetes de Rol | C15: Maquillaje y Belleza | D15: Tocador Infantil Para Niñas Espejo Maquillaje Madera Bandú | E15: BDTOCMD-WH | F15: Mix MLL | G15: 119990 | H15: 58818 | I15: 33401 | L15: 33401 | M15: 35787 | N15: 38173 | P15: 0.32 | Q15: 0.28 | R15: 0.23
A16: Bandú | B16: Juguetes de Armado | C16: Pistas y Vehiculos | D16: Pista de Autos y Tren de Madera Juego Didactico 70pcs Bandú | E16: BDJUETRE | F16: Mix MLL | G16: 64990 | H16: 29406 | I16: 16420 | L16: 16420 | M16: 17593 | N16: 18766 | P16: 0.34 | Q16: 0.29 | R16: 0.24
A17: Bandú | B17: Juguetes de Armado | C17: Pistas y Vehiculos | D17: Set Autos de Juguete Tren Pista y Señaleticas Madera Bandú | E17: BDJUEAUT | F17: Mix MLL | G17: 29990 | H17: 11759 | I17: 7928 | L17: 7928 | M17: 8494 | N17: 9061 | P17: 0.2 | Q17: 0.14 | R17: 0.08
A18: Bandú | B18: Juguetes de Armado | C18: Sets de Construccion | D18: Juego de Construcción Herramientas Madera para Niños Bandú | E18: BDMESHERRA | F18: Mix MLL | G18: 64990 | H18: 29406 | I18: 20332 | L18: 20332 | M18: 21784 | N18: 23237 | P18: 0.18 | Q18: 0.12 | R18: 0.06
A19: Bandú | B19: Juguetes de Motricidad | C19: Andador y Correpasillos | D19: Andador Correpasillos Bebe Didáctico Madera Bandú Rosado | E19: BDANDDIDAC-PK | F19: Mix MLL | G19: 54990 | H19: 29406 | I19: 15240 | L19: 15240 | M19: 16329 | N19: 17417 | P19: 0.38 | Q19: 0.34 | R19: 0.3
A20: Bandú | B20: Juguetes de Motricidad | C20: Andador y Correpasillos | D20: Andador Correpasillos Bebe Didáctico Madera Bandú Verde | E20: BDANDDIDAC-GR | F20: Mix MLL | G20: 54990 | H20: 29406 | I20: 15911 | L20: 15911 | M20: 17047 | N20: 18184 | P20: 0.36 | Q20: 0.31 | R20: 0.26
... A30: Bandú | B30: (en blanco) | C30: (en blanco) | D30: Gimancio Infantil Juego Pikler Parque 8 en 1 Bandu | E30: BDGIMPIK | F30: Mix MLL | G30: 349990 | H30: 170582 | I30: 86480 | L30: 86480 | M30: 92657 | N30: 98835 | P30: 0.4 | Q30: 0.35 | R30: 0.31
A31: Total Bandú | G31: 1938730 | H31: 923371 | I31: 511878
A32: Dynamo Tools | B32: Herramientas Eléctricas | C32: Otras | D32: Hidrolavadora eléctrica Dynamo WP 1800w 130bar 220/240V 60Hz | E32: DYNHYDLA | F32: Mix MLL | G32: 99990 | H32: 47053 | I32: 32555 | L32: 32555 | M32: 34880 | N32: 37206 | P32: 0.18 | Q32: 0.12 | R32: 0.06
A33: Dynamo Tools | B33: Herramientas Eléctricas | C33: Taladro y Atornilladores | D33: Kit Taladro Destornillador Inalámbrico Dynamo 21v 2 Baterías | E33: DYNTALSPER | F33: Mix MLL | G33: 59990 | H33: 17641 | I33: 10941 | L33: 10941 | M33: 11722 | N33: 12504 | P33: 0.26 | Q33: 0.21 | R33: 0.16
A34: Dynamo Tools | B34: Herramientas Eléctricas | C34: Taladro y Atornilladores | D34: Llave de Impacto Inalámbrica Dynamo 21V + 2 Baterias y Acss | E34: DYNLLAIMP | F34: Mix MLL | G34: 99990 | H34: 35288 | I34: 25907 | L34: 25907 | M34: 27757 | N34: 29608 | P34: 0.13 | Q34: 0.06 | R34: 0
A35: Dynamo Tools | B35: Herramientas Eléctricas | C35: Taladro y Atornilladores | D35: Pack Taladro Percutor + Atornillador de Impacto 21V Dynamo | E35: DYNTALIMPA | F35: Mix MLL | G35: 149990 | H35: 52935 | I35: 39607 | L35: 39607 | M35: 42436 | N35: 45265 | P35: 0.11 | Q35: 0.05 | R35: -0.02
A36: Dynamo Tools | B36: Herramientas Eléctricas | C36: Taladro y Atornilladores | D36: Taladro Desatornillador Inalámbrico Dynamo YM 21V 2 baterías | E36: DYNTALSCA | F36: Mix MLL | G36: 39990 | H36: 11759 | I36: 8630 | L36: 8630 | M36: 9246 | N36: 9863 | P36: 0.13 | Q36: 0.06 | R36: 0
A37: Dynamo Tools | B37: Herramientas Eléctricas | C37: Taladro y Atornilladores | D37: Taladro Inalámbrico Dynamo Rotomartillo Percutor 2 Baterías | E37: DYNTALPOW | F37: Mix MLL | G37: 89990 | H37: 35288 | I37: 25079 | L37: 25079 | M37: 26870 | N37: 28662 | P37: 0.15 | Q37: 0.09 | R37: 0.03
A38: Dynamo Tools | B38: Herramientas Eléctricas | C38: Taladro y Atornilladores | D38: Taladro Percutor Inalámbrico Dynamo 21v 2 Baterías + Accs | E38: DYNTALCPER | F38: Mix MLL | G38: 69990 | H38: 17641 | I38: 11893 | L38: 11893 | M38: 12742 | N38: 13592 | P38: 0.2 | Q38: 0.14 | R38: 0.08
A39: Total Dynamo Tools | G39: 609930 | H39: 217606 | I39: 154612
A40: Innovate-K | B40: Gasfiteria | C40: Baroscopios | D40: Cámara de inspección alcantarillado con pantalla LCD de 7 pulgadas H6 endoscopio boroscopio | E40: 1661880000000 | F40: Mix MLL | G40: 699990 | H40: 382347 | I40: 275044 | L40: 275044 | M40: 294689 | N40: 314337 | P40: 0.14 | Q40: 0.08 | R40: 0.02
A41: Innovate-K | B41: Gasfiteria | C41: Baroscopios | D41: Cámara de Inspección Baroscopio 512 Hz con Sonda 20 Mts H5 | E41: INNCAMINSH5512-20 | F41: Mix MLL | G41: 1699990 | H41: 823524 | I41: 423998 | L41: 423998 | M41: 454282 | N41: 484570 | P41: 0.39 | Q41: 0.34 | R41: 0.3
A42: Innovate-K | B42: Gasfiteria | C42: Baroscopios | D42: Cámara de Inspección Baroscopio con Sonda 20 Mts H5 | E42: INNCAMINSH5-20 | F42: Mix MLL | G42: 1149990 | H42: 558818 | I42: 282666 | L42: 282666 | M42: 302855 | N42: 323048 | P42: 0.4 | Q42: 0.36 | R42: 0.31
A43: Innovate-K | B43: Gasfiteria | C43: Baroscopios | D43: Cámara de Inspección Baroscopio con Sonda 40 Mts H6 | E43: INNCAMINSH6-40 | F43: Mix MLL | G43: 1999990 | H43: 588229 | I43: 302856 | L43: 302856 | M43: 324487 | N43: 346122 | P43: 0.39 | Q43: 0.34 | R43: 0.3
A44: Innovate-K | B44: Gasfiteria | C44: Baroscopios | D44: Cámara de Inspección Baroscopio con Sonda 40 Mts TP9200 | E44: INCAMINS92-40 | F44: Mix MLL | G44: 899990 | H44: 470582 | I44: 293682 | L44: 293682 | M44: 314658 | N44: 335637 | P44: 0.26 | Q44: 0.2 | R44: 0.15
A45: Innovate-K | B45: Gasfiteria | C45: Baroscopios | D45: Cámara de Inspección de Tuberías Endoscopio Industrial TP9600 | E45: INNCAMINS-96 | F45: Mix MLL | G45: 1499990 | H45: 764700 | I45: 432031 | L45: 432031 | M45: 462889 | N45: 493751 | P45: 0.33 | Q45: 0.28 | R45: 0.23
A46: Innovate-K | B46: Gasfiteria | C46: Baroscopios | D46: Cámara de Inspección de Tuberías Endoscopio Industrial TP9607F | E46: INNCAMINS-7F | F46: Mix MLL | G46: 1699990 | H46: 941171 | I46: 553437 | L46: 553437 | M46: 592966 | N46: 632501 | P46: 0.3 | Q46: 0.25 | R46: 0.2
A47: Innovate-K | B47: Gasfiteria | C47: Baroscopios | D47: Cámara de Inspección de Tuberías Endoscopio Industrial U9 | E47: INNCAMINS-U9 | F47: Mix MLL | G47: 159990 | H47: 88229 | I47: 50149 | L47: 50149 | M47: 53731 | N47: 57313 | P47: 0.32 | Q47: 0.28 | R47: 0.23
A48: Innovate-K | B48: Gasfiteria | C48: Baroscopios | D48: Cámara de Inspección Baroscopio con Sonda 70 Mts H3 | E48: INNCAMINSH3-70 | F48: Mix MLL | G48: 7199990 | H48: 3529406 | I48: 29251 | L48: 29251 | M48: 31340 | N48: 33430 | P48: 0.99 | Q48: 0.99 | R48: 0.99
A49: Innovate-K | B49: Gasfiteria | C49: Baroscopios | D49: Cámara de Inspección Baroscopio con Sonda 20 Mts TP9200 | E49: 1661880000000 | F49: Mix MLL | G49: 599990 | H49: 323524 | I49: 237256 | L49: 237256 | M49: 254202 | N49: 271150 | P49: 0.13 | Q49: 0.06 | R49: 0
A50: Innovate-K | B50: Hogar | C50: Accesorios para Baño | D50: Secador De Toallas Pedestal 6 Niveles | E50: 1571060000000 | F50: Mix MLL | G50: 89990 | H50: 29406 | I50: 19690 | L50: 19690 | M50: 21096 | N50: 22503 | P50: 0.2 | Q50: 0.15 | R50: 0.09
A51: Total Innovate-K | G51: 17699890 | H51: 8499935 | I51: 2900060
A52: Klip Klap | B52: Instrumentos Musicales | C52: Metalofonos | D52: Metalofono Cromatico 25 infantil Amarillo | E52: 67114500000000 | F52: Descontinuado | G52: 29990 | H52: 14700 | I52: 6081 | L52: 6081 | M52: 6515 | N52: 6950 | P52: 0.51 | Q52: 0.47 | R52: 0.44
A53: Klip Klap | B53: Instrumentos Musicales | C53: Metalofonos | D53: Metalofono Cromatico 25 infantil Azul | E53: 67114500000000 | F53: Descontinuado | G53: 29990 | H53: 14700 | I53: 6071 | L53: 6071 | M53: 6505 | N53: 6938 | P53: 0.51 | Q53: 0.47 | R53: 0.44
A54: Klip Klap | B54: Instrumentos Musicales | C54: Metalofonos | D54: Metalofono Cromatico 25 infantil Rojo | E54: 67114500000000 | F54: Descontinuado | G54: 29990 | H54: 14700 | I54: 5982 | L54: 5982 | M54: 6409 | N54: 6837 | P54: 0.52 | Q54: 0.48 | R54: 0.45
A55: Klip Klap | B55: Instrumentos Musicales | C55: Metalofonos | D55: Metalofono Cromatico 25 infantil Rosado | E55: 67114500000000 | F55: Descontinuado | G55: 29990 | H55: 14700 | I55: 5894 | L55: 5894 | M55: 6315 | N55: 6736 | P55: 0.52 | Q55: 0.49 | R55: 0.45
A56: Total Klip Klap | G56: 119960 | H56: 58800 | I56: 24028
A57: LEVO | B57: Accesorios | C57: Cable Cargador | D57: Cable USB Tipo-C a Lightning blanco | E57: LVCABTCLIGH-WH | F57: Mix MLL | G57: 10990 | H57: 4112 | I57: 840 | L57: 840 | M57: 900 | N57: 960 | P57: 0.76 | Q57: 0.74 | R57: 0.72
A58: LEVO | B58: Accesorios | C58: Cable Cargador | D58: Cable USB Tipo-C a Tipo-C (5A) blanco | E58: LVCABTC-WH | F58: Mix MLL | G58: 10990 | H58: 4112 | I58: 1815 | L58: 1815 | M58: 1945 | N58: 2074 | P58: 0.47 | Q58: 0.44 | R58: 0.4
A59: LEVO | B59: Accesorios | C59: Cable Cargador | D59: Cable USB Tipo-C a Tipo-C (5A) negro | E59: LVCABTC-BK | F59: Mix MLL | G59: 10990 | H59: 4112 | I59: 1815 | L59: 1815 | M59: 1945 | N59: 2074 | P59: 0.47 | Q59: 0.44 | R59: 0.4
A60: LEVO | B60: Accesorios | C60: Cargador Automovil | D60: Soporte Cargador Magnético V+ | E60: 1650300000000 | F60: Mix MLL | G60: 24990 | H60: 8818 | I60: 5881 | L60: 5881 | M60: 6301 | N60: 6721 | P60: 0.21 | Q60: 0.15 | R60: 0.09
A61: LEVO | B61: Accesorios | C61: Cargador Automovil | D61: Soporte Cargador Magnético VO1 | E61: 1652830000000 | F61: Mix MLL | G61: 24990 | H61: 8818 | I61: 6398 | L61: 6398 | M61: 6855 | N61: 7312 | P61: 0.14 | Q61: 0.07 | R61: 0.01
A62: LEVO | B62: Accesorios | C62: Cargador de Celular | D62: Cargador Rapido 25W Blanco | E62: LVCAR25W-WH | F62: Mix MLL | G62: 14990 | H62: 4700 | I62: 2126 | L62: 2126 | M62: 2278 | N62: 2430 | P62: 0.46 | Q62: 0.42 | R62: 0.38
A63: LEVO | B63: Accesorios | C63: Cargador de Celular | D63: Cargador Rapido 25W Negro | E63: LVCAR25W-BK | F63: Mix MLL | G63: 14990 | H63: 4700 | I63: 2126 | L63: 2126 | M63: 2278 | N63: 2430 | P63: 0.46 | Q63: 0.42 | R63: 0.38
A64: LEVO | B64: Accesorios | C64: Cargador de Celular | D64: Cargador Ultra Rapido 45 W Blanco | E64: LVCAR45W-WH | F64: Mix MLL | G64: 19990 | H64: 5876 | I64: 3112 | L64: 3112 | M64: 3334 | N64: 3557 | P64: 0.37 | Q64: 0.32 | R64: 0.28
A65: LEVO | B65: Accesorios | C65: Cargador de Celular | D65: Cargador Ultra Rapido 45 W Negro | E65: LVCAR45W-BK | F65: Mix MLL | G65: 19990 | H65: 5876 | I65: 3112 | L65: 3112 | M65: 3334 | N65: 3557 | P65: 0.37 | Q65: 0.32 | R65: 0.28
A66: LEVO | B66: Accesorios | C66: Dispositivo Multipuerto | D66: Hub multipuerto Tipo-C 5 puertos con entrada Ethernet | E66: LVHUBMP-5 | F66: Mix MLL | G66: 14990 | H66: 6465 | I66: 3786 | L66: 3786 | M66: 4056 | N66: 4327 | P66: 0.3 | Q66: 0.25 | R66: 0.2
A67: LEVO | B67: Accesorios | C67: Dispositivo Multipuerto | D67: Hub multipuerto Tipo-C 6 puertos con entrada TF y SD | E67: LVHUBMP-6 | F67: Mix MLL | G67: 14990 | H67: 7641 | I67: 3506 | L67: 3506 | M67: 3756 | N67: 4007 | P67: 0.45 | Q67: 0.41 | R67: 0.38
A68: LEVO | B68: Mochilas y Fundas | C68: Fundas | D68: Funda Maletin Notebook EXECUTIVE Gris 15,6" LEVO | E68: LVFUEX-GR | F68: Descontinuado | G68: 19990 | H68: 11759 | I68: 7961 | L68: 7961 | M68: 8530 | N68: 9098 | P68: 0.19 | Q68: 0.14 | R68: 0.08
A69: LEVO | B69: Mochilas y Fundas | C69: Fundas | D69: Funda Maletin Notebook EXECUTIVE Negro 15,6" LEVO | E69: LVFUEX-BK | F69: Descontinuado | G69: 19990 | H69: 9994 | I69: 11441 | L69: 11441 | M69: 12259 | N69: 13076 | P69: -0.36 | Q69: -0.46 | R69: -0.56
A70: LEVO | B70: Mochilas y Fundas | C70: Fundas | D70: Funda Notebook Hardshell 13,3 | E70: LVFNOTHS13-BK | F70: Mix MLL | G70: 39990 | H70: 14700 | I70: 9002 | L70: 9002 | M70: 9645 | N70: 10288 | P70: 0.27 | Q70: 0.22 | R70: 0.17
A71: LEVO | B71: Mochilas y Fundas | C71: Fundas | D71: Funda Notebook Hardshell 15,6 | E71: LVFNOTHS15-BK | F71: Mix MLL | G71: 44990 | H71: 15876 | I71: 10253 | L71: 10253 | M71: 10985 | N71: 11718 | P71: 0.23 | Q71: 0.18 | R71: 0.12
A72: LEVO | B72: Mochilas y Fundas | C72: Mochilas | D72: Mochila de Viaje AeroSuite 30 L Negra LEVO | E72: LVMOVITR-BK | F72: Mix MLL | G72: 79990 | H72: 29406 | I72: 19694 | L72: 19694 | M72: 21101 | N72: 22507 | P72: 0.2 | Q72: 0.15 | R72: 0.09
A73: LEVO | B73: Mochilas y Fundas | C73: Mochilas | D73: Mochila LEVO Computador Gris | E73: 1660000000000 | F73: Mix B2B | G73: 19990 | H73: 7641 | I73: 3637 | L73: 3637 | M73: 3897 | N73: 4157 | P73: 0.43 | Q73: 0.39 | R73: 0.35
A74: LEVO | B74: Mochilas y Fundas | C74: Mochilas | D74: Mochila LEVO Computador Negro | E74: 1660000000000 | F74: Mix B2B | G74: 19990 | H74: 7641 | I74: 3577 | L74: 3577 | M74: 3832 | N74: 4088 | P74: 0.44 | Q74: 0.4 | R74: 0.36
A75: LEVO | B75: Mochilas y Fundas | C75: Mochilas | D75: Mochila Notebook MANAGER Gris LEVO | E75: LVMOMA-GR | F75: Mix MLL | G75: 32990 | H75: 14700 | I75: 8609 | L75: 8609 | M75: 9224 | N75: 9839 | P75: 0.3 | Q75: 0.25 | R75: 0.2
A76: LEVO | B76: Mochilas y Fundas | C76: Mochilas | D76: Mochila Notebook MANAGER Negra LEVO | E76: LVMOMA-BK | F76: Mix MLL | G76: 32990 | H76: 14700 | I76: 8666 | L76: 8666 | M76: 9285 | N76: 9904 | P76: 0.3 | Q76: 0.25 | R76: 0.2
A77: LEVO | B77: Mochilas y Fundas | C77: Mochilas | D77: Mochila Notebook WOLF Negra LEVO | E77: LVMOWO-BK | F77: Mix MLL | G77: 32990 | H77: 14700 | I77: 8775 | L77: 8775 | M77: 9402 | N77: 10029 | P77: 0.29 | Q77: 0.24 | R77: 0.19
A78: LEVO | B78: Pantallas | C78: Monitores | D78: Monitor Portatil ViewGo LEVO | E78: LVMONPOR-15 | F78: Mix B2B | G78: 169990 | H78: 67220 | I78: 48174 | L78: 48174 | M78: 51615 | N78: 55056 | P78: 0.15 | Q78: 0.09 | R78: 0.03
A79: LEVO | B79: Pantallas | C79: Monitores | D79: Pantalla Monitor Portátil 15.6 LED NexView Full HD LEVO | E79: LVMONEXV-15 | F79: Transito | G79: 169990 | H79: 58818 | I79: 37835 | L79: 37835 | M79: 40537 | N79: 43240 | P79: 0.23 | Q79: 0.18 | R79: 0.13
A80: LEVO | B80: Pantallas | C80: Pantallas Publicitarias | D80: Pantalla Totem Publicitario 43" Touch Android Wifi Usb LEVO | E80: LVPANTOTPUB-43 | F80: Mix MLL | G80: 999990 | H80: 529406 | I80: 345276 | L80: 345276 | M80: 369937 | N80: 394602 | P80: 0.22 | Q80: 0.17 | R80: 0.11
A81: LEVO | B81: Pantallas | C81: Pantallas Publicitarias | D81: Pantalla Totem Publicitario 50" Touch Android Wifi Usb LEVO | E81: LVPANTOTPUB-50 | F81: Mix MLL | G81: 1099990 | H81: 588229 | I81: 415412 | L81: 415412 | M81: 445083 | N81: 474758 | P81: 0.16 | Q81: 0.1 | R81: 0.04
A82: LEVO | B82: Perifericos de Computacion | C82: Gaming | D82: Audífono Gamer RGB Thunder | E82: 1659990000000 | F82: Descontinuado | G82: 59990 | H82: 20582 | I82: 16625 | L82: 16625 | M82: 17812 | N82: 19000 | P82: 0.04 | Q82: -0.03 | R82: -0.1
A83: LEVO | B83: Perifericos de Computacion | C83: Gaming | D83: Audifono Gamer Zenit Elite Wireless 7.1 LEVO | E83: LVAUDGM-BK | F83: Mix MLL | G83: 59990 | H83: 26465 | I83: 17160 | L83: 17160 | M83: 18386 | N83: 19611 | P83: 0.23 | Q83: 0.17 | R83: 0.12
A84: LEVO | B84: Perifericos de Computacion | C84: Gaming | D84: Mouse Gamer LED | E84: 1659970000000 | F84: Descontinuado | G84: 19990 | H84: 4112 | I84: 2638 | L84: 2638 | M84: 2826 | N84: 3015 | P84: 0.24 | Q84: 0.18 | R84: 0.13
A85: LEVO | B85: Perifericos de Computacion | C85: Gaming | D85: Mousepad LEVO BattleMat XXL Negro | E85: LVMPADXXL-BK | F85: Mix MLL | G85: 19990 | H85: 7641 | I85: 3474 | L85: 3474 | M85: 3722 | N85: 3970 | P85: 0.46 | Q85: 0.42 | R85: 0.38
A86: LEVO | B86: Perifericos de Computacion | C86: Gaming | D86: Teclado Gamer NovaBlade Red Switch Mecanico LEVO | E86: LVTECMCC-BK | F86: Mix MLL | G86: 39990 | H86: 15876 | I86: 9424 | L86: 9424 | M86: 10097 | N86: 10770 | P86: 0.29 | Q86: 0.24 | R86: 0.19
A87: LEVO | B87: Perifericos de Computacion | C87: Gaming | D87: Teclado Gamer RGB Storm | E87: 1659990000000 | F87: Descontinuado | G87: 39990 | H87: 11759 | I87: 10725 | L87: 10725 | M87: 11491 | N87: 12257 | P87: -0.09 | Q87: -0.16 | R87: -0.24
A88: LEVO | B88: Perifericos de Computacion | C88: Gaming | D88: Vr Box | E88: 1479750000000 | F88: Mix MLL | G88: 14990 | H88: 5288 | I88: 2887 | L88: 2887 | M88: 3093 | N88: 3299 | P88: 0.35 | Q88: 0.3 | R88: 0.26
A89: LEVO | B89: Perifericos de Computacion | C89: Gaming | D89: Vr Box Ultra + audifonos | E89: 1658330000000 | F89: Mix MLL | G89: 24990 | H89: 11759 | I89: 6761 | L89: 6761 | M89: 7244 | N89: 7727 | P89: 0.32 | Q89: 0.27 | R89: 0.22
A90: LEVO | B90: Perifericos de Computacion | C90: Gaming | D90: Control Gamer Inalámbrico PC | E90: 1659990000000 | F90: Mix MLL | G90: 29990 | H90: 11759 | I90: 8843 | L90: 8843 | M90: 9475 | N90: 10106 | P90: 0.11 | Q90: 0.04 | R90: -0.02
A91: LEVO | B91: Perifericos de Computacion | C91: Gaming | D91: Joystick Inalámbrico Dualshock 4 | E91: 1659990000000 | F91: Mix MLL | G91: 29990 | H91: 11759 | I91: 8888 | L91: 8888 | M91: 9523 | N91: 10158 | P91: 0.1 | Q91: 0.04 | R91: -0.03
A92: LEVO | B92: Perifericos de Computacion | C92: Gaming | D92: Joystick Inalámbrico Dualshock 4 ROJO | E92: 66436800000000 | F92: Mix MLL | G92: 29990 | H92: 11759 | I92: 8608 | L92: 8608 | M92: 9223 | N92: 9838 | P92: 0.13 | Q92: 0.07 | R92: 0
A93: LEVO | B93: Perifericos de Computacion | C93: Gaming | D93: Pro Control Nintendo Switch NEGRO | E93: LVCONSW-BK | F93: Mix MLL | G93: 32990 | H93: 14700 | I93: 12273 | L93: 12273 | M93: 13150 | N93: 14026 | P93: 0.01 | Q93: -0.06 | R93: -0.14
A94: LEVO | B94: Perifericos de Computacion | C94: Gaming | D94: Pro Controller Inalámbrico Nintendo S | E94: 1659990000000 | F94: Mix MLL | G94: 32990 | H94: 11759 | I94: 6964 | L94: 6964 | M94: 7461 | N94: 7959 | P94: 0.3 | Q94: 0.24 | R94: 0.19
A95: LEVO | B95: Perifericos de Computacion | C95: Gaming | D95: Mouse Inalámbrico Gamer NovaStrike Negro LEVO | E95: LVMSGMNS-BK | F95: Mix MLL | G95: 69990 | H95: 20582 | I95: 15204 | L95: 15204 | M95: 16290 | N95: 17376 | P95: 0.12 | Q95: 0.06 | R95: 0
A96: LEVO | B96: Perifericos de Computacion | C96: Gaming | D96: Audifono Gamer Zenit Elite Wireless 7.1 Blanco LEVO | E96: LVAUDGM-WH | F96: Mix MLL | G96: 59990 | H96: 26465 | I96: 17185 | L96: 17185 | M96: 18412 | N96: 19640 | P96: 0.23 | Q96: 0.17 | R96: 0.12
A97: LEVO | B97: Perifericos de Computacion | C97: Gaming | D97: Mousepad BattleMat L Negro LEVO | E97: LVMPADL-BK | F97: Transito | G97: 19990 | H97: 5876 | I97: 2378 | L97: 2378 | M97: 2548 | N97: 2718 | P97: 0.52 | Q97: 0.48 | R97: 0.45
A98: LEVO | B98: Perifericos de Computacion | C98: Oficina | D98: Kit Teclado y Mouse Inalámbrico Blanco | E98: 1627420000000 | F98: Descontinuado | G98: 24990 | H98: 8818 | I98: 6549 | L98: 6549 | M98: 7017 | N98: 7485 | P98: 0.12 | Q98: 0.05 | R98: -0.01
A99: LEVO | B99: Perifericos de Computacion | C99: Oficina | D99: Silla Ejecutiva Negra | E99: 67898100000000 | F99: Mix B2B | G99: 149990 | H99: 64700 | I99: 41118 | L99: 41118 | M99: 44055 | N99: 46992 | P99: 0.24 | Q99: 0.19 | R99: 0.14
A100: LEVO | B100: Perifericos de Computacion | C100: Oficina | D100: Silla Escritorio Ergonomica | E100: LVSILLERGO-BL | F100: Mix MLL | G100: 129990 | H100: 58818 | I100: 36777 | L100: 36777 | M100: 39404 | N100: 42031 | P100: 0.26 | Q100: 0.2 | R100: 0.15
A101: LEVO | B101: Perifericos de Computacion | C101: Oficina | D101: Silla Gamer Negro-Roja | E101: 1630370000000 | F101: Descontinuado | G101: 319990 | H101: 117641 | I101: 48846 | L101: 48846 | M101: 52335 | N101: 55824 | P101: 0.51 | Q101: 0.47 | R101: 0.44
A102: LEVO | B102: Perifericos de Computacion | C102: Oficina | D102: Teclado Inalambrico Slim LEVO Cygna Grafito | E102: LVTECOFSL-GR | F102: Mix MLL | G102: 49990 | H102: 23524 | I102: 14045 | L102: 14045 | M102: 15048 | N102: 16051 | P102: 0.29 | Q102: 0.24 | R102: 0.19
A103: LEVO | B103: Perifericos de Computacion | C103: Oficina | D103: Mouse Inalámbrico Slim Velar Grafito LEVO | E103: LVMSVEL-GR | F103: Mix MLL | G103: 19990 | H103: 5876 | I103: 3342 | L103: 3342 | M103: 3581 | N103: 3819 | P103: 0.32 | Q103: 0.27 | R103: 0.23
A104: LEVO | B104: Perifericos de Computacion | C104: Oficina | D104: KIT Transmisiones Sonidos | E104: LVMICPORT | F104: Mix MLL | G104: 49990 | H104: 17641 | I104: 13499 | L104: 13499 | M104: 14464 | N104: 15428 | P104: 0.09 | Q104: 0.02 | R104: -0.04
A105: LEVO | B105: Perifericos de Computacion | C105: Oficina | D105: Mousepad OfficePad S Negro LEVO | E105: LVMPADS-BK | F105: Transito | G105: 14990 | H105: 4700 | I105: 1297 | L105: 1297 | M105: 1390 | N105: 1483 | P105: 0.67 | Q105: 0.65 | R105: 0.62
A106: LEVO | B106: Perifericos de Computacion | C106: Oficina | D106: Silla de Escritorio Lite Ergonómica LEVO | E106: LVSILLLIT-BL | F106: Transito | G106: 69990 | H106: 29406 | I106: 10481 | L106: 10481 | M106: 11230 | N106: 11978 | P106: 0.58 | Q106: 0.55 | R106: 0.52
A107: LEVO | B107: Smart Home | C107: Aspiradoras | D107: Aspiradora Inalámbrica XPIRA | E107: 1652830000000 | F107: Mix MLL | G107: 29990 | H107: 13524 | I107: 7262 | L107: 7262 | M107: 7781 | N107: 8299 | P107: 0.36 | Q107: 0.32 | R107: 0.27
A108: LEVO | B108: Smart Home | C108: Cámaras de automovil | D108: Cámara de Auto Dual D3 | E108: 67327600000000 | F108: Mix MLL | G108: 69990 | H108: 23524 | I108: 12919 | L108: 12919 | M108: 13842 | N108: 14765 | P108: 0.35 | Q108: 0.3 | R108: 0.25
A109: LEVO | B109: Smart Home | C109: Cámaras de automovil | D109: Dual Camara con GPS R300 | E109: 1748320000000 | F109: Descontinuado | G109: 89990 | H109: 35288 | I109: 30370 | L109: 30370 | M109: 32539 | N109: 34709 | P109: -0.02 | Q109: -0.1 | R109: -0.17
...

Sheet Maestra
E2: INFORMACION CLIENTE | G2: INFORMACION UNIONX | J2: INFORMACION CLIENTE | R2: 0.3
E3: UnionX | F3: Cliente | G3: UnionX | J3: Precios Ciente | L3: Costo Cliente | N3: Margen | P3: Status
A4: Marca | B4: Sku | C4: Seccion | D4: Familia | E4: Grupo | F4: Descripcion | G4: Costo MLL | H4: ROI | I4: Utilidad UnionX | J4: P Etiqueta | K4: PVP Oferta | L4: Costo | M4: Costo Oferta | N4: Margen Master | O4: Margen Oferta | P4: Status MLL | Q4: MG FRONT | R4: MG COMISION
A5: Bandú | B5: BDBBYCHK | C5: Accesorios de Bebe | D5: Accesorios de Bebe | E5: Baby Chick Bandú - Mecedor eléctrico de bebé | F5: Mecedor Eléctrico Coche Recargable Bebé Baby Chick Bandú | G5: 20716 | H5: 0.41 | I5: 14572 | J5: $64.990 | K5: $59.990 | L5: 38229 | M5: 35288 | N5: 0.3 | O5: 0.3 | P5: Mix UnionX | Q5: 0.59 | R5: 0.36
A6: Bandú | B6: BDCASMUÑEC | C6: Jueguetes de Rol | D6: Cocina y Accesorios | E6: Casa De Muñecas Clásica Madera Rosada Con Accesorios Bandú | F6: Casa De Muñecas Clásica Madera Rosada Con Accesorios Bandú | G6: 23592 | H6: 0.33 | I6: 11696 | J6: $99.990 | K6: $59.990 | L6: 58818 | M6: 35288 | N6: 0.3 | O6: 0.3 | P6: Mix UnionX | Q6: 0.53 | R6: 0.3
A7: Bandú | B7: BDCOCMEDI | C7: Jueguetes de Rol | D7: Cocina y Accesorios | E7: Cocina de Juguete Infantil Niños Madera 11 Accesorios Bandú | F7: Cocina de Juguete Infantil Niños Madera 11 Accesorios Bandú | G7: 28393 | H7: 0.52 | I7: 30424 | J7: $119.990 | K7: $99.990 | L7: 70582 | M7: 58818 | N7: 0.3 | O7: 0.3 | P7: Mix UnionX | Q7: 0.66 | R7: 0.43
A8: Bandú | B8: BDCOCGRND | C8: Jueguetes de Rol | D8: Cocina y Accesorios | E8: Cocina de Juguete Infantil Niños Madera Accesorios Bandú | F8: Cocina de Juguete Infantil Niños Madera Accesorios Bandú | G8: 31896 | H8: 0.55 | I8: 38687 | J8: $139.990 | K8: $119.990 | L8: 82347 | M8: 70582 | N8: 0.3 | O8: 0.3 | P8: Mix UnionX | Q8: 0.68 | R8: 0.45
A9: Bandú | B9: BDCOCPQMD | C9: Jueguetes de Rol | D9: Cocina y Accesorios | E9: Cocina de Juguete Infantil Niños Madera Rosada con Acc Bandú | F9: Cocina de Juguete Infantil Niños Madera Rosada con Acc Bandú | G9: 26348 | H9: 0.36 | I9: 14822 | J9: $99.990 | K9: $69.990 | L9: 58818 | M9: 41171 | N9: 0.3 | O9: 0.3 | P9: Mix UnionX | Q9: 0.55 | R9: 0.32
A10: Bandú | B10: BDELECTCOC | C10: Jueguetes de Rol | D10: Cocina y Accesorios | E10: Juguete Infantil mini Electrodomésticos Cocina Madera Bandú | F10: Juguete Infantil Mini Electrodomésticos Cocina Madera Bandú | G10: 5823 | H10: 0.42 | I10: 4171 | J10: $24.990 | K10: $16.990 | L10: 14700 | M10: 9994 | N10: 0.3 | O10: 0.3 | P10: Mix UnionX | Q10: 0.59 | R10: 0.36
A11: Bandú | B11: BDCOCMIN | C11: Jueguetes de Rol | D11: Cocina y Accesorios | E11: Set Juego Mini Cocina de Juguete Alimentos Madera Bandú | F11: Set Juego Mini Cocina de Juguete Alimentos Madera Bandú | G11: 7906 | H11: 0.33 | I11: 3853 | J11: $29.990 | K11: $19.990 | L11: 17641 | M11: 11759 | N11: 0.3 | O11: 0.3 | P11: Mix UnionX | Q11: 0.53 | R11: 0.3
A12: Bandú | B12: BDSETPAST | C12: Jueguetes de Rol | D12: Cocina y Accesorios | E12: Set Juego Pastelería Corta Postre Infantil Niño Madera Bandú | F12: Set Juego Pastelería Corta Postre Infantil Niño Madera Bandú | G12: 6889 | H12: 0.31 | I12: 3105 | J12: $24.990 | K12: $16.990 | L12: 14700 | M12: 9994 | N12: 0.3 | O12: 0.3 | P12: Mix UnionX | Q12: 0.52 | R12: 0.29
A13: Bandú | B13: BDJUESETTE | C13: Jueguetes de Rol | D13: Cocina y Accesorios | E13: Set Juego Tazas De Té Juguete Didáctico 16pcs Madera Bandú | F13: Set Juego Tazas De Té Juguete Didáctico 16pcs Madera Bandú | G13: 6930 | H13: 0.41 | I13: 4829 | J13: $29.990 | K13: $19.990 | L13: 17641 | M13: 11759 | N13: 0.3 | O13: 0.3 | P13: Mix UnionX | Q13: 0.59 | R13: 0.36
A14: Bandú | B14: BDSETDOC | C14: Jueguetes de Rol | D14: Juegos de Oficio | E14: Set Juego de Roles Doctor Niños Madera 12 pcs Bandú | F14: Set Juego de Roles Doctor Niños Madera 12 pcs Bandú | G14: 4770 | H14: 0.46 | I14: 4048 | J14: $24.990 | K14: $14.990 | L14: 14700 | M14: 8818 | N14: 0.3 | O14: 0.3 | P14: Mix UnionX | Q14: 0.62 | R14: 0.39
A15: Bandú | B15: BDSETMAQ | C15: Jueguetes de Rol | D15: Maquillaje y Belleza | E15: Juego de Maquillaje Set Belleza de Roll Niños Madera Bandú | F15: Juego de Maquillaje Set Belleza de Roll Niños Madera Bandú | G15: 4770 | H15: 0.59 | I15: 6989 | J15: $24.990 | K15: $19.990 | L15: 14700 | M15: 11759 | N15: 0.3 | O15: 0.3 | P15: Mix UnionX | Q15: 0.72 | R15: 0.49
A16: Bandú | B16: BDTOCMD-WH | C16: Jueguetes de Rol | D16: Maquillaje y Belleza | E16: Tocador Infantil Para Niñas Espejo Maquillaje Madera Bandú | F16: Tocador Infantil Para Niñas Espejo Maquillaje Madera Bandú | G16: 33401 | H16: 0.43 | I16: 25417 | J16: $119.990 | K16: $99.990 | L16: 70582 | M16: 58818 | N16: 0.3 | O16: 0.3 | P16: Mix UnionX | Q16: 0.6 | R16: 0.37
... A46: GOYA | B46: GOYAHOSP-CV | C46: Aromatización | D46: Home Spray | E46: Home Spray 500ml Aroma Citron Verveine GOYA | F46: Home Spray 500ml Aroma Citron Verveine GOYA | G46: 7500 | H46: 0.25 | I46: 2494 | J46: $17.990 | K46: $16.990 | L46: 10582 | M46: 9994 | N46: 0.3 | O46: 0.3 | P46: Mix UnionX | Q46: 0.47 | R46: 0.24
A47: Innovate-K | B47: 1661877072053 | C47: Gasfiteria | D47: Baroscopios | E47: Cámara de inspección alcantarillado con pantalla LCD de 7 pulgadas H6 endoscopio boroscopio | F47: Cámara de inspección alcantarillado con pantalla LCD de 7 pulgadas H6 endoscopio boroscopio | G47: 275044 | H47: 0.28 | I47: 107303 | J47: $699.990 | K47: $649.990 | L47: 411759 | M47: 382347 | N47: 0.3 | O47: 0.3 | P47: Mix UnionX | Q47: 0.5 | R47: 0.27
A48: Innovate-K | B48: INNCAMINSH5512-20 | C48: Gasfiteria | D48: Baroscopios | E48: Cámara de Inspección Baroscopio 512 Hz con Sonda 20 Mts H5 | F48: Cámara de Inspección Baroscopio 512 Hz con Sonda 20 Mts H5 | G48: 423998 | H48: 0.49 | I48: 399526 | J48: $1.699.990 | K48: $1.399.990 | L48: 999994 | M48: 823524 | N48: 0.3 | O48: 0.3 | P48: Mix UnionX | Q48: 0.64 | R48: 0.41
A49: Innovate-K | B49: INNCAMINSH3-70 | C49: Gasfiteria | D49: Baroscopios | E49: Cámara de Inspección Baroscopio con Sonda 20 Mts H3 | F49: Cámara de Inspección Baroscopio con Sonda 70 Mts H3 | G49: 1867612 | H49: 0.47 | I49: 1661794 | J49: $7.199.990 | K49: $5.999.990 | L49: 4235288 | M49: 3529406 | N49: 0.3 | O49: 0.3 | P49: Mix UnionX | Q49: 0.63 | R49: 0.4
A50: Innovate-K | B50: INNCAMINSH5-20 | C50: Gasfiteria | D50: Baroscopios | E50: Cámara de Inspección Baroscopio con Sonda 20 Mts H5 | F50: Cámara de Inspección Baroscopio con Sonda 20 Mts H5 | G50: 282666 | H50: 0.49 | I50: 276152 | J50: $1.149.990 | K50: $949.990 | L50: 676465 | M50: 558818 | N50: 0.3 | O50: 0.3 | P50: Mix UnionX | Q50: 0.65 | R50: 0.42
A51: Innovate-K | B51: INNCAMINSH6-40 | C51: Gasfiteria | D51: Baroscopios | E51: Cámara de Inspección Baroscopio con Sonda 40 Mts H6 | F51: Cámara de Inspección Baroscopio con Sonda 40 Mts H6 | G51: 302856 | H51: 0.49 | I51: 285373 | J51: $1.999.990 | K51: $999.990 | L51: 1176465 | M51: 588229 | N51: 0.3 | O51: 0.3 | P51: Mix UnionX | Q51: 0.64 | R51: 0.41
A52: Innovate-K | B52: INCAMINS92-40 | C52: Gasfiteria | D52: Baroscopios | E52: Cámara de Inspección Baroscopio con Sonda 40 Mts TP9200 | F52: Cámara de Inspección Baroscopio con Sonda 40 Mts TP9200 | G52: 293682 | H52: 0.38 | I52: 176900 | J52: $899.990 | K52: $799.990 | L52: 529406 | M52: 470582 | N52: 0.3 | O52: 0.3 | P52: Mix UnionX | Q52: 0.56 | R52: 0.33
A53: Innovate-K | B53: 1661877043628 | C53: Gasfiteria | D53: Baroscopios | E53: Cámara de inspección de tuberías de alcantarillado TP9200 endoscopio boroscopio | F53: Cámara de Inspección Baroscopio con Sonda 20 Mts TP9200 | G53: 237256 | H53: 0.27 | I53: 86268 | J53: $599.990 | K53: $549.990 | L53: 352935 | M53: 323524 | N53: 0.3 | O53: 0.3 | P53: Mix UnionX | Q53: 0.49 | R53: 0.26
A54: Innovate-K | B54: INNCAMINS-96 | C54: Gasfiteria | D54: Baroscopios | E54: Camara de Inspeccion TP9600 | F54: Cámara de Inspección de Tuberías Endoscopio Industrial TP9600 | G54: 432031 | H54: 0.44 | I54: 332669 | J54: $1.499.990 | K54: $1.299.990 | L54: 882347 | M54: 764700 | N54: 0.3 | O54: 0.3 | P54: Mix UnionX | Q54: 0.6 | R54: 0.37
A55: Innovate-K | B55: INNCAMINS-7F | C55: Gasfiteria | D55: Baroscopios | E55: Camara de Inspeccion TP9607F | F55: Cámara de Inspección de Tuberías Endoscopio Industrial TP9607F | G55: 553437 | H55: 0.41 | I55: 387734 | J55: $1.699.990 | K55: $1.599.990 | L55: 999994 | M55: 941171 | N55: 0.3 | O55: 0.3 | P55: Mix UnionX | Q55: 0.59 | R55: 0.36
A56: Innovate-K | B56: INNCAMINS-U9 | C56: Gasfiteria | D56: Baroscopios | E56: Camara de Inspeccion U9 | F56: Cámara de Inspección de Tuberías Endoscopio Industrial U9 | G56: 50149 | H56: 0.43 | I56: 38080 | J56: $159.990 | K56: $149.990 | L56: 94112 | M56: 88229 | N56: 0.3 | O56: 0.3 | P56: Mix UnionX | Q56: 0.6 | R56: 0.37
A57: Innovate-K | B57: INCAMINS92-40 | C57: Gasfiteria | D57: Baroscopios | E57: Cámaras de Inspeccion | F57: Cámara de Inspección Baroscopio con Sonda 40 Mts TP9200 | G57: 293682 | H57: 0.38 | I57: 176900 | J57: $899.990 | K57: $799.990 | L57: 529406 | M57: 470582 | N57: 0.3 | O57: 0.3 | P57: Mix UnionX | Q57: 0.56 | R57: 0.33
A58: Innovate-K | B58: 1571055493973 | C58: Hogar | D58: Accesorios para Baño | E58: Secador De Toallas Pedestal 6 Niveles | F58: Secador De Toallas Pedestal 6 Niveles | G58: 19691 | H58: 0.33 | I58: 9715 | J58: $74.990 | K58: $49.990 | L58: 44112 | M58: 29406 | N58: 0.3 | O58: 0.3 | P58: Mix UnionX | Q58: 0.53 | R58: 0.3
A59: Klip Klap | B59: 67114508251225 | C59: Instrumentos Musicales | D59: Metalofonos | E59: Metalofono Cromatico | F59: Metalofono Cromatico 25 infantil Amarillo | G59: 6081 | H59: 0.42 | I59: 8619 | J59: $29.990 | K59: $24.990 | L59: 17641 | M59: 14700 | N59: 0.3 | O59: 0.3 | P59: Descontinuado | Q59: 0.71 | R59: 0.48
A60: Klip Klap | B60: 67114505814137 | C60: Instrumentos Musicales | D60: Metalofonos | E60: Metalofono Cromatico | F60: Metalofono Cromatico 25 infantil Rosado | G60: 5894 | H60: 0.49 | I60: 8806 | J60: $29.990 | K60: $24.990 | L60: 17641 | M60: 14700 | N60: 0.3 | O60: 0.3 | P60: Descontinuado | Q60: 0.72 | R60: 0.49
A61: Levo | B61: LVCABTCLIGH-WH | C61: Accesorios | D61: Cable Cargador | E61: Cable USB Tipo-C a Lightning blanco | F61: Cable de Carga USB-C a Lightning 1 Mt Blanco LEVO | G61: 840 | H61: 0.76 | I61: 2684 | J61: $9.990 | K61: $5.990 | L61: 5876 | M61: 3524 | N61: 0.3 | O61: 0.3 | P61: Mix UnionX | Q61: 0.83 | R61: 0.6
A62: Levo | B62: LVCABTC-WH | C62: Accesorios | D62: Cable Cargador | E62: Cable USB Tipo-C a Tipo-C (5A) blanco | F62: Cable de Carga Rápida USB-C 100W 5A 1Mt Blanco LEVO | G62: 1815 | H62: 0.56 | I62: 2297 | J62: $9.990 | K62: $6.990 | L62: 5876 | M62: 4112 | N62: 0.3 | O62: 0.3 | P62: Mix UnionX | Q62: 0.69 | R62: 0.46
A63: Levo | B63: LVCABTC-BK | C63: Accesorios | D63: Cable Cargador | E63: Cable USB Tipo-C a Tipo-C (5A) negro | F63: Cable de Carga Rápida USB-C 100W 5A 1Mt Negro LEVO | G63: 1815 | H63: 0.56 | I63: 2297 | J63: $9.990 | K63: $6.990 | L63: 5876 | M63: 4112 | N63: 0.3 | O63: 0.3 | P63: Mix UnionX | Q63: 0.69 | R63: 0.46
A64: Levo | B64: 1650299083874 | C64: Accesorios | D64: Cargador Automovil | E64: Soporte Cargador Magnetico V+ | F64: Cargador Inalámbrico Carga Rapida iPhone 12/13 Auto V+ LEVO | G64: 5881 | H64: 0.33 | I64: 2937 | J64: $24.990 | K64: $14.990 | L64: 14700 | M64: 8818 | N64: 0.3 | O64: 0.3 | P64: Mix UnionX | Q64: 0.53 | R64: 0.3
A65: Levo | B65: 1652825203439 | C65: Accesorios | D65: Cargador Automovil | E65: Soporte Cargador Magnetico V01 | F65: Cargador Inalámbrico Carga Rápida Magnético Auto VO1 LEVO | G65: 6398 | H65: 0.27 | I65: 2420 | J65: $24.990 | K65: $14.990 | L65: 14700 | M65: 8818 | N65: 0.3 | O65: 0.3 | P65: Mix UnionX | Q65: 0.49 | R65: 0.26
A66: Levo | B66: LVCAR25W-WH | C66: Accesorios | D66: Cargador de Celular | E66: Cargador 25W Blanco | F66: Cargador Super Rapido De Pared 25W USB-C Blanco LEVO | G66: 2126 | H66: 0.48 | I66: 1986 | J66: $14.990 | K66: $6.990 | L66: 8818 | M66: 4112 | N66: 0.3 | O66: 0.3 | P66: Mix UnionX | Q66: 0.64 | R66: 0.41
A67: Levo | B67: LVCAR25W-BK | C67: Accesorios | D67: Cargador de Celular | E67: Cargador 25W Negro | F67: Cargador Super Rapido De Pared 25W USB-C Negro LEVO | G67: 2126 | H67: 0.48 | I67: 1986 | J67: $14.990 | K67: $6.990 | L67: 8818 | M67: 4112 | N67: 0.3 | O67: 0.3 | P67: Mix UnionX | Q67: 0.64 | R67: 0.41
A68: Levo | B68: LVCAR45W-WH | C68: Accesorios | D68: Cargador de Celular | E68: Cargador 45 W Blanco | F68: Cargador Ultra Rapido De Pared 45W USB-C Blanco LEVO | G68: 3112 | H68: 0.41 | I68: 2176 | J68: $19.990 | K68: $8.990 | L68: 11759 | M68: 5288 | N68: 0.3 | O68: 0.3 | P68: Mix UnionX | Q68: 0.59 | R68: 0.36
A69: Levo | B69: LVCAR45W-BK | C69: Accesorios | D69: Cargador de Celular | E69: Cargador 45 W Negro | F69: Cargador Ultra Rapido De Pared 45W USB-C Negro LEVO | G69: 3112 | H69: 0.41 | I69: 2176 | J69: $19.990 | K69: $8.990 | L69: 11759 | M69: 5288 | N69: 0.3 | O69: 0.3 | P69: Mix UnionX | Q69: 0.59 | R69: 0.36
A70: Levo | B70: LVHUBMP-5 | C70: Accesorios | D70: Dispositivo Multipuerto | E70: Hub multipuerto Tipo-C 5 puertos con entrada Ethernet | F70: Hub USB-C Adaptador Multipuerto 5 en 1 Macbook Windows LEVO | G70: 3786 | H70: 0.5 | I70: 3855 | J70: $14.990 | K70: $12.990 | L70: 8818 | M70: 7641 | N70: 0.3 | O70: 0.3 | P70: Mix UnionX | Q70: 0.65 | R70: 0.42
A71: Levo | B71: LVHUBMP-6 | C71: Accesorios | D71: Dispositivo Multipuerto | E71: Hub multipuerto Tipo-C 6 puertos con entrada TF y SD | F71: Hub USB-C Adaptador Multipuerto 6 en 1 Macbook Windows LEVO | G71: 3470 | H71: 0.51 | I71: 3583 | J71: $14.990 | K71: $11.990 | L71: 8818 | M71: 7053 | N71: 0.3 | O71: 0.3 | P71: Mix UnionX | Q71: 0.66 | R71: 0.43
A72: Levo | B72: LVFNOTHS13-BK | C72: Mochilas y Fundas | D72: Fundas | E72: Funda LEVO HardShell para Notebook 13-14" Negro | F72: Funda HardShell Notebook 13-14" Negra LEVO | G72: 8004 | H72: 0.41 | I72: 5520 | J72: $39.990 | K72: $22.990 | L72: 23524 | M72: 13524 | N72: 0.3 | O72: 0.3 | P72: Mix UnionX | Q72: 0.59 | R72: 0.36
A73: Levo | B73: LVFNOTHS15-BK | C73: Mochilas y Fundas | D73: Fundas | E73: Funda LEVO HardShell para Notebook 15-16" Negro | F73: Funda HardShell Notebook 15-16" Negra LEVO | G73: 9561 | H73: 0.35 | I73: 5139 | J73: $44.990 | K73: $24.990 | L73: 26465 | M73: 14700 | N73: 0.3 | O73: 0.3 | P73: Mix UnionX | Q73: 0.54 | R73: 0.31
A74: Levo | B74: LVFUEX-GR | C74: Mochilas y Fundas | D74: Fundas | E74: Funda Notebook EXECUTIVE | F74: Funda Maletin Notebook EXECUTIVE 15,6" Negra LEVO | G74: 7961 | H74: 0.1 | I74: 857 | J74: $19.990 | K74: $14.990 | L74: 11759 | M74: 8818 | N74: 0.3 | O74: 0.3 | P74: Descontinuado | Q74: 0.37 | R74: 0.14
A75: Levo | B75: LVFUEX-BK | C75: Mochilas y Fundas | D75: Fundas | E75: Funda Notebook EXECUTIVE | F75: Funda Maletin Notebook EXECUTIVE 15,6" Negra LEVO | G75: 11441 | H75: -0.3 | I75: -2623 | J75: $19.990 | K75: $14.990 | L75: 11759 | M75: 8818 | N75: 0.3 | O75: 0.3 | P75: Descontinuado | Q75: 0.09 | R75: -0.14
A76: Levo | B76: LVMOVITR-BK | C76: Mochilas y Fundas | D76: Mochilas | E76: Mochila de Viaje AeroSuite 30 L Negra Levo | F76: Mochila Viaje Impermeable Notebook 30L Aerosuite Negra LEVO | G76: 18056 | H76: 0.39 | I76: 11349 | J76: $79.990 | K76: $49.990 | L76: 47053 | M76: 29406 | N76: 0.3 | O76: 0.3 | P76: Mix UnionX | Q76: 0.57 | R76: 0.34
A77: Levo | B77: 1659999392257 | C77: Mochilas y Fundas | D77: Mochilas | E77: Mochila Levo Computador | F77: Mochila Notebook Puerto USB 15,6" Gris LEVO | G77: 3637 | H77: 0.52 | I77: 4004 | J77: $19.990 | K77: $12.990 | L77: 11759 | M77: 7641 | N77: 0.3 | O77: 0.3 | P77: Mix UnionX | Q77: 0.67 | R77: 0.44
A78: Levo | B78: 1659999410637 | C78: Mochilas y Fundas | D78: Mochilas | E78: Mochila Levo Computador | F78: Mochila Notebook Puerto USB 15,6" Negra LEVO | G78: 3527 | H78: 0.54 | I78: 4115 | J78: $19.990 | K78: $12.990 | L78: 11759 | M78: 7641 | N78: 0.3 | O78: 0.3 | P78: Mix UnionX | Q78: 0.68 | R78: 0.45
A79: Levo | B79: LVMOMA-GR | C79: Mochilas y Fundas | D79: Mochilas | E79: Mochila Notebook MANAGER | F79: Mochila Notebook MANAGER 15,6" Gris LEVO | G79: 8609 | H79: 0.41 | I79: 6091 | J79: $32.990 | K79: $24.990 | L79: 19406 | M79: 14700 | N79: 0.3 | O79: 0.3 | P79: Descontinuado | Q79: 0.59 | R79: 0.36
A80: Levo | B80: LVMOMA-BK | C80: Mochilas y Fundas | D80: Mochilas | E80: Mochila Notebook MANAGER | F80: Mochila Notebook MANAGER 15,6" Negra LEVO | G80: 8666 | H80: 0.41 | I80: 6034 | J80: $32.990 | K80: $24.990 | L80: 19406 | M80: 14700 | N80: 0.3 | O80: 0.3 | P80: Descontinuado | Q80: 0.59 | R80: 0.36
A81: Levo | B81: LVMOWO-BK | C81: Mochilas y Fundas | D81: Mochilas | E81: Mochila Notebook WOLF | F81: Mochila Notebook WOLF Negra 15,6" LEVO | G81: 8775 | H81: 0.4 | I81: 5925 | J81: $32.990 | K81: $24.990 | L81: 19406 | M81: 14700 | N81: 0.3 | O81: 0.3 | P81: Descontinuado | Q81: 0.58 | R81: 0.35
A82: Levo | B82: LVMONPOR-15 | C82: Pantallas | D82: Monitores | E82: Pantalla Monitor | F82: Monitor Portátil Gamer ViewGo 15,6" Full HD 1080P LEVO | G82: 48287 | H82: 0.28 | I82: 18933 | J82: $169.990 | K82: $99.990 | L82: 99994 | M82: 67220 | N82: 0.3 | O82: 0.2 | P82: Mix UnionX | Q82: 0.43 | R82: 0.2
A83: Levo | B83: LVMONEXV-15 | C83: Pantallas | D83: Monitores | E83: Pantalla Monitor Portátil 15.6 LED NexView Full HD LEVO | F83: Monitor Portátil Gamer NexView 15.6" Full HD 1080P LEVO | G83: 37116 | H83: 0.37 | I83: 21702 | J83: $129.990 | K83: $99.990 | L83: 76465 | M83: 58818 | N83: 0.3 | O83: 0.3 | P83: Mix UnionX | Q83: 0.56 | R83: 0.33
A84: Levo | B84: LVPANTOTPUB-43 | C84: Pantallas | D84: Pantallas Publicitarias | E84: Pantalla Totem Publicitario 43" Touch Android Wifi Usb Levo | F84: Pantalla Totem Publicitario 43" Touch Android Wifi Usb LEVO | G84: 289710 | H84: 0.45 | I84: 239696 | J84: $999.990 | K84: $899.990 | L84: 588229 | M84: 529406 | N84: 0.3 | O84: 0.3 | P84: Mix UnionX | Q84: 0.62 | R84: 0.39
A85: Levo | B85: LVPANTOTPUB-50 | C85: Pantallas | D85: Pantallas Publicitarias | E85: Pantalla Totem Publicitario 50" Touch Android Wifi Usb Levo | F85: Pantalla Totem Publicitario 50" Touch Android Wifi Usb LEVO | G85: 340911 | H85: 0.42 | I85: 247318 | J85: $1.099.990 | K85: $999.990 | L85: 647053 | M85: 588229 | N85: 0.3 | O85: 0.3 | P85: Mix UnionX | Q85: 0.59 | R85: 0.36
A86: Levo | B86: 1659989621591 | C86: Perifericos de Computacion | D86: Gaming | E86: Audifono Gamer RGB Thunder | F86: Audífono Gamer RGB Thunder | G86: 16625 | H86: 0.19 | I86: 3957 | J86: $59.990 | K86: $34.990 | L86: 35288 | M86: 20582 | N86: 0.3 | O86: 0.3 | P86: Descontinuado | Q86: 0.43 | R86: 0.2
A87: Levo | B87: LVAUDGM-BK | C87: Perifericos de Computacion | D87: Gaming | E87: Audifono Gamer Zenit Elite Wireless 7.1 Levo | F87: Audífono Gamer Inalámbrico Zenit Elite Bluetooth RGB Negro LEVO | G87: 17160 | H87: 0.35 | I87: 9305 | J87: $59.990 | K87: $44.990 | L87: 35288 | M87: 26465 | N87: 0.3 | O87: 0.3 | P87: Mix UnionX | Q87: 0.55 | R87: 0.32
A88: Levo | B88: 1659990828178 | C88: Perifericos de Computacion | D88: Gaming | E88: Joystick Inalambrico Dualshock 4 | F88: Control Joystick Inalámbrico doble Shock P4 Negro LEVO | G88: 7275 | H88: 0.38 | I88: 4484 | J88: $29.990 | K88: $19.990 | L88: 17641 | M88: 11759 | N88: 0.3 | O88: 0.3 | P88: Mix UnionX | Q88: 0.57 | R88: 0.34
A89: Levo | B89: 66436804863605 | C89: Perifericos de Computacion | D89: Gaming | E89: Joystick Inalambrico Dualshock 4 | F89: Control Joystick Inalámbrico doble Shock P4 Rojo LEVO | G89: 7298 | H89: 0.38 | I89: 4461 | J89: $29.990 | K89: $19.990 | L89: 17641 | M89: 11759 | N89: 0.3 | O89: 0.3 | P89: Mix UnionX | Q89: 0.57 | R89: 0.34
A90: Levo | B90: LVMPADXXL-BK | C90: Perifericos de Computacion | D90: Gaming | E90: Mousepad Levo BattleMat XXL Negro | F90: Mousepad Battlemat XXL 90x40 cm Antideslizante Negro LEVO | G90: 3238 | H90: 0.58 | I90: 4403 | J90: $14.990 | K90: $12.990 | L90: 8818 | M90: 7641 | N90: 0.3 | O90: 0.3 | P90: Mix UnionX | Q90: 0.7 | R90: 0.47
A91: Levo | B91: 1659990788079 | C91: Perifericos de Computacion | D91: Gaming | E91: Pro Control Nintengo Switch | F91: Control Joystick Controller Compatible Nintendo Switch LEVO | G91: 5989 | H91: 0.49 | I91: 5770 | J91: $32.990 | K91: $19.990 | L91: 19406 | M91: 11759 | N91: 0.3 | O91: 0.3 | P91: Mix UnionX | Q91: 0.64 | R91: 0.41
A92: Levo | B92: LVTECMCC-BK | C92: Perifericos de Computacion | D92: Gaming | E92: Teclado Gamer NovaBlade Red Switch Mecanico Levo | F92: Teclado Gamer NovaBlade TKL Red Switch Mecánico Español RGB LEVO | G92: 9424 | H92: 0.41 | I92: 6452 | J92: $39.990 | K92: $26.990 | L92: 23524 | M92: 15876 | N92: 0.3 | O92: 0.3 | P92: Mix UnionX | Q92: 0.58 | R92: 0.35
A93: Levo | B93: LVMSVEL-GR | C93: Perifericos de Computacion | D93: Gaming | E93: Mouse Inalámbrico Ultra Slim Silencioso Velar Grafito LEVO | F93: Mouse Inalámbrico Ultra Slim Silencioso Velar Grafito LEVO | G93: 3137 | H93: 0.47 | I93: 2740 | J93: $19.990 | K93: $9.990 | L93: 11759 | M93: 5876 | N93: 0.3 | O93: 0.3 | P93: Mix UnionX | Q93: 0.63 | R93: 0.4
A94: Levo | B94: 1479750635184 | C94: Perifericos de Computacion | D94: Gaming | E94: Vr Box | F94: Vr Box + Control Lentes de Realidad Virtual LEVO | G94: 2651 | H94: 0.5 | I94: 2637 | J94: $14.990 | K94: $8.990 | L94: 8818 | M94: 5288 | N94: 0.3 | O94: 0.3 | P94: Mix UnionX | Q94: 0.65 | R94: 0.42
A95: Levo | B95: 1658329968514 | C95: Perifericos de Computacion | D95: Gaming | E95: Vr Box Ultra + Audifono | F95: Vr Box Ultra + Audífonos Lentes de Realidad Virtual LEVO | G95: 6324 | H95: 0.46 | I95: 5435 | J95: $24.990 | K95: $19.990 | L95: 14700 | M95: 11759 | N95: 0.3 | O95: 0.3 | P95: Mix UnionX | Q95: 0.62 | R95: 0.39
A96: Levo | B96: LVAUDGM-WH | C96: Perifericos de Computacion | D96: Gaming | E96: Audifono Gamer Zenit Elite Wireless 7.1 Blanco Levo | F96: Audífono Gamer Inalámbrico Zenit Elite Bluetooth RGB Blanco LEVO | G96: 17185 | H96: 0.42 | I96: 12221 | J96: $69.990 | K96: $49.990 | L96: 41171 | M96: 29406 | N96: 0.3 | O96: 0.3 | P96: Mix UnionX | Q96: 0.59 | R96: 0.36
A97: Levo | B97: LVMPADS-BK | C97: Perifericos de Computacion | D97: Gaming | E97: Mousepad Levo OfficePad S Negro | F97: Mousepad Levo OfficePad S Negro | G97: 1201 | H97: 0.74 | I97: 3499 | J97: $9.990 | K97: $7.990 | L97: 5876 | M97: 4700 | N97: 0.3 | O97: 0.3 | P97: Mix UnionX | Q97: 0.82 | R97: 0.59
A98: Levo | B98: LVMPADL-BK | C98: Perifericos de Computacion | D98: Gaming | E98: Mousepad Levo GamerPad L Negro | F98: Mousepad Levo GamerPad L Negro | G98: 2201 | H98: 0.63 | I98: 3675 | J98: $14.990 | K98: $9.990 | L98: 8818 | M98: 5876 | N98: 0.3 | O98: 0.3 | P98: Mix UnionX | Q98: 0.74 | R98: 0.51
A99: Levo | B99: LVMSGMNS-BK | C99: Perifericos de Computacion | D99: Oficina | E99: Mouse Gamer Inalambrico RGB NovaStrike Negro LEVO | F99: Mouse Gamer Inalambrico RGB NovaStrike Negro LEVO | G99: 14265 | H99: 0.19 | I99: 3376 | J99: $69.990 | K99: $29.990 | L99: 41171 | M99: 17641 | N99: 0.3 | O99: 0.3 | P99: Mix UnionX | Q99: 0.43 | R99: 0.2
A100: Levo | B100: LVTECOFSL-GR | C100: Perifericos de Computacion | D100: Oficina | E100: Teclado Inalambrico Slim Levo Cygna Grafito | F100: Teclado Inalámbrico Cygna Slim Grafito LEVO | G100: 11991 | H100: 0.38 | I100: 7415 | J100: $49.990 | K100: $32.990 | L100: 29406 | M100: 19406 | N100: 0.3 | O100: 0.3 | P100: Mix UnionX | Q100: 0.57 | R100: 0.34
A101: Levo | B101: LVMICPORT | C101: Perifericos de Computacion | D101: Oficina | E101: KIT Micrófono de Solapa Inalámbrico Lavalier EchoPro | F101: KIT Micrófono de Solapa Inalámbrico Lavalier EchoPro LEVO | G101: 13499 | H101: 0.23 | I101: 4142 | J101: $49.990 | K101: $29.990 | L101: 29406 | M101: 17641 | N101: 0.3 | O101: 0.3 | P101: Descontinuado | Q101: 0.46 | R101: 0.23
A102: Levo | B102: 67898087132855 | C102: Perifericos de Computacion | D102: Oficina | E102: Silla Ejecutiva | F102: Silla Escritorio Oficina Ejecutiva Reclinable Comfort LEVO | G102: 40886 | H102: 0.3 | I102: 17932 | J102: $149.990 | K102: $99.990 | L102: 88229 | M102: 58818 | N102: 0.3 | O102: 0.3 | P102: Mix UnionX | Q102: 0.51 | R102: 0.28
A103: Levo | B103: LVSILLERGO-BL | C103: Perifericos de Computacion | D103: Oficina | E103: Silla Escritorio Ergonomica | F103: Silla Escritorio Oficina Ergonómica Reclinable Ergotech LEVO | G103: 36631 | H103: 0.31 | I103: 16304 | J103: $129.990 | K103: $89.990 | L103: 76465 | M103: 52935 | N103: 0.3 | O103: 0.3 | P103: Mix UnionX | Q103: 0.52 | R103: 0.29
A104: Levo | B104: LVSILLLIT-BL | C104: Perifericos de Computacion | D104: Oficina | E104: Silla de Escritorio Lite Ergonómica LEVO | F104: Silla de Escritorio Oficina Ergonomica Reclinable Lite LEVO | G104: 9205 | H104: 0.61 | I104: 14319 | J104: $59.990 | K104: $39.990 | L104: 35288 | M104: 23524 | N104: 0.3 | O104: 0.3 | P104: Mix UnionX | Q104: 0.73 | R104: 0.5
A105: Levo | B105: 1652825027456 | C105: Smart Home | D105: Aspiradoras | E105: Aspiradora Inalambrica XPIRA | F105: Aspiradora Inalámbrica Portátil Xpira Negra LEVO | G105: 6467 | H105: 0.45 | I105: 5292 | J105: $29.990 | K105: $19.990 | L105: 17641 | M105: 11759 | N105: 0.3 | O105: 0.3 | P105: Mix UnionX | Q105: 0.62 | R105: 0.39
A106: Levo | B106: 67327559384453 | C106: Smart Home | D106: Cámaras de automovil | E106: Camara de Auto Dual D3 | F106: Cámara HD Auto D3 Frontal, Interior y Trasera LEVO | G106: 11466 | H106: 0.35 | I106: 6176 | J106: $69.990 | K106: $29.990 | L106: 41171 | M106: 17641 | N106: 0.3 | O106: 0.3 | P106: Mix UnionX | Q106: 0.55 | R106: 0.32
A107: Levo | B107: 1748316345017 | C107: Smart Home | D107: Cámaras de automovil | E107: Dual Camara con GPS R300 | F107: Dual Camara con GPS R300 | G107: 30370 | H107: 0.14 | I107: 4918 | J107: $89.990 | K107: $59.990 | L107: 52935 | M107: 35288 | N107: 0.3 | O107: 0.3 | P107: Descontinuado | Q107: 0.4 | R107: 0.17
A108: Levo | B108: LVCAMSEGEX-BK | C108: Smart Home | D108: Cámaras de seguridad | E108: Cámara de Seguridad Exterior 5G Wifi Negra Levo | F108: Cámara de Seguridad Impermeable Wifi 5G 2MP GuardPro X5 LEVO | G108: 7602 | H108: 0.35 | I108: 4157 | J108: $34.990 | K108: $19.990 | L108: 20582 | M108: 11759 | N108: 0.3 | O108: 0.3 | P108: Mix UnionX | Q108: 0.55 | R108: 0.32
A109: Levo | B109: LVCITMONWF | C109: Smart Home | D109: Citofonia | E109: Citofono Monitor WIFI | F109: Timbre Video Portero Citofono Monitor WIFI LEVO | G109: 65373 | H109: 0.26 | I109: 22856 | J109: $249.990 | K109: $149.990 | L109: 147053 | M109: 88229 | N109: 0.3 | O109: 0.3 | P109: Descontinuado | Q109: 0.48 | R109: 0.25
A110: Levo | B110: 1543406075297 | C110: Smart Home | D110: Pesas Digitales | E110: Pesa Digital Inteligente | F110: Pesa Digital Balanza Baño Bluetooth Inteligente Blanca LEVO | G110: 3664 | H110: 0.38 | I110: 2212 | J110: $24.990 | K110: $9.990 | L110: 14700 | M110: 5876 | N110: 0.3 | O110: 0.3 | P110: Mix UnionX | Q110: 0.56 | R110: 0.33
A111: Levo | B111: 1538141129434 | C111: Smart Home | D111: Pesas Digitales | E111: Pesa Digital Inteligente | F111: Pesa Digital Balanza Baño Bluetooth Inteligente Negra LEVO | G111: 3250 | H111: 0.45 | I111: 2627 | J111: $24.990 | K111: $9.990 | L111: 14700 | M111: 5876 | N111: 0.3 | O111: 0.3 | P111: Mix UnionX | Q111: 0.61 | R111: 0.38
A112: Levo | B112: LVSPBRX2MN | C112: Soportes | D112: Soporte Computacion | E112: Soporte Brazo Doble Monitor Notebook Escritorio Negro LEVO | F112: Soporte Brazo Doble Monitor Notebook Escritorio Negro LEVO | G112: 9256 | H112: 0.37 | I112: 5444 | J112: $34.990 | K112: $24.990 | L112: 20582 | M112: 14700 | N112: 0.3 | O112: 0.3 | P112: Mix UnionX | Q112: 0.56 | R112: 0.33
A113: Levo | B113: LVSPALZNPLE | C113: Soportes | D113: Soporte Computacion | E113: Soporte Base Alzador Notebook Plegable Ajustable Gris LEVO | F113: Soporte Base Alzador Notebook Plegable Ajustable Gris LEVO | G113: 4517 | H113: 0.49 | I113: 4301 | J113: $29.990 | K113: $14.990 | L113: 17641 | M113: 8818 | N113: 0.3 | O113: 0.3 | P113: Mix UnionX | Q113: 0.64 | R113: 0.41
A114: Levo | B114: LVSPTVUN | C114: Soportes | D114: Soportes de Television | E114: Soportes de TV | F114: Soporte de Television Ajustable 32" a 72" LEVO | G114: 2955 | H114: 0.28 | I114: 1157 | J114: $9.990 | K114: $6.990 | L114: 5876 | M114: 4112 | N114: 0.3 | O114: 0.3 | P114: Mix UnionX | Q114: 0.5 | R114: 0.27
A115: Levo | B115: LVPROLUM | C115: Telones y Proyectores | D115: Proyectores | E115: Proyector Led inalambrico portatil FullHD max lumix | F115: Proyector Portatil Smart Lumix 9000lm Inalambrico BT LEVO | G115: 88385 | H115: 0.34 | I115: 46062 | J115: $319.990 | K115: $199.990 | L115: 188229 | M115: 134447 | N115: 0.3 | O115: 0.2 | P115: Mix UnionX | Q115: 0.47 | R115: 0.24
A116: Levo | B116: LVPROHAL | C116: Telones y Proyectores | D116: Proyectores | E116: Proyector Led portatil Halo FullHD | F116: Proyector Led portatil Halo HD | G116: 46527 | H116: 0.13 | I116: 7248 | J116: $169.990 | K116: $79.990 | L116: 99994 | M116: 53775 | N116: 0.3 | O116: 0.2 | P116: Descontinuado | Q116: 0.31 | R116: 0.08
A117: Levo | B117: LVPRONOV | C117: Telones y Proyectores | D117: Proyectores | E117: Proyector Led portatil Nova FullHD | F117: Proyector Portatil Smart Nova 9000lm WiFi BT Android LEVO | G117: 56843 | H117: 0.4 | I117: 37268 | J117: $219.990 | K117: $139.990 | L117: 129406 | M117: 94111 | N117: 0.3 | O117: 0.2 | P117: Mix UnionX | Q117: 0.52 | R117: 0.29
A118: Levo | B118: LVPROORI | C118: Telones y Proyectores | D118: Proyectores | E118: Proyector Led portatil Orion FullHD | F118: Proyector Portatil Smart Orion 12000lm WiFi BT Android LEVO | G118: 76078 | H118: 0.33 | I118: 38201 | J118: $269.990 | K118: $169.990 | L118: 158818 | M118: 114279 | N118: 0.3 | O118: 0.2 | P118: Mix UnionX | Q118: 0.47 | R118: 0.24
A119: Levo | B119: LVPROHEX | C119: Telones y Proyectores | D119: Proyectores | E119: Proyector Led portatil Hexa FullHD | F119: Proyector Portatil Smart Hexa 8000lm WiFi BT Android LEVO | G119: 36795 | H119: 0.45 | I119: 30425 | J119: $149.990 | K119: $99.990 | L119: 88229 | M119: 67220 | N119: 0.3 | O119: 0.2 | P119: Mix UnionX | Q119: 0.56 | R119: 0.33
A120: Levo | B120: 1659991971809 | C120: Telones y Proyectores | D120: Telones Proyector | E120: Telon Proyector 100 | F120: Telón Proyector 100 pulgadas 200 x 150 cm LEVO | G120: 20217 | H120: 0.47 | I120: 18012 | J120: $99.990 | K120: $64.990 | L120: 58818 | M120: 38229 | N120: 0.3 | O120: 0.3 | P120: Mix UnionX | Q120: 0.63 | R120: 0.4
A121: Levo | B121: LVTELELE-100 | C121: Telones y Proyectores | D121: Telones Proyector | E121: Telon Proyector 100 Electrico | F121: Telón Proyector 100 pulgadas Eléctrico 200 x 150 cm LEVO | G121: 22862 | H121: 0.48 | I121: 21250 | J121: $129.990 | K121: $74.990 | L121: 76465 | M121: 44112 | N121: 0.3 | O121: 0.3 | P121: Mix UnionX | Q121: 0.64 | R121: 0.41
A122: Levo | B122: 1659991999728 | C122: Telones y Proyectores | D122: Telones Proyector | E122: Telon Proyector 60 | F122: Telón Proyector 60 pulgadas 120 x 90 cm LEVO | G122: 9617 | H122: 0.59 | I122: 13906 | J122: $69.990 | K122: $39.990 | L122: 41171 | M122: 23524 | N122: 0.3 | O122: 0.3 | P122: Mix UnionX | Q122: 0.71 | R122: 0.48
A123: Levo | B123: LVTELELE-60 | C123: Telones y Proyectores | D123: Telones Proyector | E123: Telon Proyector 60 Electrico | F123: Telón Proyector 60 pulgadas Eléctrico 120 x 90 cm LEVO | G123: 18020 | H123: 0.39 | I123: 11386 | J123: $89.990 | K123: $49.990 | L123: 52935 | M123: 29406 | N123: 0.3 | O123: 0.3 | P123: Mix UnionX | Q123: 0.57 | R123: 0.34
A124: Levo | B124: LVTEL-80 | C124: Telones y Proyectores | D124: Telones Proyector | E124: Telon Proyector 80 | F124: Telón Proyector 80 pulgadas 165 x 125 cm LEVO | G124: 17801 | H124: 0.45 | I124: 14546 | J124: $89.990 | K124: $54.990 | L124: 52935 | M124: 32347 | N124: 0.3 | O124: 0.3 | P124: Mix UnionX | Q124: 0.61 | R124: 0.38
A125: Levo | B125: LVTELELE-80 | C125: Telones y Proyectores | D125: Telones Proyector | E125: Telon Proyector 80 Electrico | F125: Telón Proyector 80 pulgadas Eléctrico 165 x 125 cm LEVO | G125: 20893 | H125: 0.45 | I125: 17336 | J125: $99.990 | K125: $64.990 | L125: 58818 | M125: 38229 | N125: 0.3 | O125: 0.3 | P125: Mix UnionX | Q125: 0.62 | R125: 0.39
A126: Levo | B126: LVTELRETR-100 | C126: Telones y Proyectores | D126: Telones Proyector | E126: Telón Proyector 100" Sistema de Elevación 200 x 150cm LEVO | F126: Telón Proyector 100 pulgadas Elevación 200 x 150cm LEVO | G126: 90498 | H126: 0.38 | I126: 56555 | J126: $349.990 | K126: $249.990 | L126: 205876 | M126: 147053 | N126: 0.3 | O126: 0.3 | P126: Mix UnionX | Q126: 0.57 | R126: 0.34
A127: Levo | B127: LVTELBK-100 | C127: Telones y Proyectores | D127: Telones Proyector | E127: Telon Proyector 100 pulgadas Negro | F127: Telón Proyector 100 pulgadas 200 x 150 cm Negro LEVO | G127: 20134 | H127: 0.51 | I127: 21036 | J127: $99.990 | K127: $69.990 | L127: 58818 | M127: 41171 | N127: 0.3 | O127: 0.3 | P127: Mix UnionX | Q127: 0.66 | R127: 0.43
A128: Levo | B128: LVTELBK-80 | C128: Telones y Proyectores | D128: Telones Proyector | E128: Telon Proyector 80 pulgadas Negro | F128: Telón Proyector 80 pulgadas 165 x 125 cm Negro LEVO | G128: 17734 | H128: 0.5 | I128: 17555 | J128: $89.990 | K128: $59.990 | L128: 52935 | M128: 35288 | N128: 0.3 | O128: 0.3 | P128: Mix UnionX | Q128: 0.65 | R128: 0.42
A129: Levo | B129: LVTELBK-60 | C129: Telones y Proyectores | D129: Telones Proyector | E129: Telon Proyector 60 pulgadas Negro | F129: Telón Proyector 60 pulgadas 120 x 90 cm Negro LEVO | G129: 9493 | H129: 0.6 | I129: 14030 | J129: $69.990 | K129: $39.990 | L129: 41171 | M129: 23524 | N129: 0.3 | O129: 0.3 | P129: Mix UnionX | Q129: 0.72 | R129: 0.49
A130: Lhotse | B130: LHCALTOBGRS-M | C130: Accesorio Vestuario | D130: Calcetines | E130: Calcetin Corte Tobillo Numa Gray S-M | F130: Calcetin Corte Tobillo Numa Gray S-M | G130: 2303 | H130: 0.56 | I130: 2985 | J130: $9.990 | K130: $8.990 | L130: 5876 | M130: 5288 | N130: 0.3 | O130: 0.3 | P130: Mix UnionX | Q130: 0.7 | R130: 0.47
...

Sheet Stock Empresa por Bodega
A1: BDT/Stock | B1: SKU | C1: Cantidad
A2: [1000190502] Collar Triángulo Azul Talla Xs Perro Mascan | B2: 1000190502 | C2: 1.00
A3: [1513614057219] Lámpara Solar Linterna Inflable Camping Pesca Outdoor | B3: 1513614057219 | C3: 6.00
A4: [1523536647880] Hamaca Camping Pesca Outdoor Lhotse Verde Claro 270 Cm | B4: 1523536647880 | C4: 2.00
A5: [1564150627423] Audífonos Lhotse Bluetooth Inalámbrico Rm12 Blanco | B5: 1564150627423 | C5: 100.00
A6: [1564150661249] Audífonos Lhotse Bluetooth Inalámbrico Rm12 Negro | B6: 1564150661249 | C6: 100.00
A7: [1566335721736] Audífonos Lhotse Bluetooth Inalámbrico Rm12 Celeste | B7: 1566335721736 | C7: 99.00
A8: [1566849947902] Mochila Antirrobo Lhotse Gris Oscuro MA147 | B8: 1566849947902 | C8: 26.00
A9: [1571423280815] Pick-up Pad Lhotse Porta 5 Bicicletas | B9: 1571423280815 | C9: 15.00
A10: [1592492799236] Audífonos Lhotse Bluetooth Inalámbrico Rm12 Rosado | B10: 1592492799236 | C10: 100.00
A11: [1597086499840] Audífonos Lhotse RM7 Pro Inalámbrico Blanco | B11: 1597086499840 | C11: 100.00
A12: [1597098592591] Audífonos Lhotse RM7 Pro Inalámbrico Negro | B12: 1597098592591 | C12: 108.00
A13: [1615383366170] Pick-up Pad Lhotse Porta 6 Bicicletas | B13: 1615383366170 | C13: 11.00
... A61: [1909000061510] Bolsas Sanitarias Biodegradables Para Perro Mascan | B61: 1909000061510 | C61: 1.00
A62: [20-40015] Loción De Protección Solar Hidratante SPF 15 Sun Bum | B62: 20-40015 | C62: 1.00
A63: [20-45085] After Sun Cool Down Lotion Sun Bum | B63: 20-45085 | C63: 1.00
A64: [6182252] Balancio Juego De Ingenio Scratch Europe | B64: 6182252 | C64: 1.00
A65: [66800469437952] Termo de Comida Insulado Acero Inox 750 ml Rosado Simplit | B65: 66800469437952 | C65: 2.00
A66: [66800472805184] Termo de Comida Insulado Acero Inox 750 ml Gris Simplit | B66: 66800472805184 | C66: 10.00
A67: [66800506435054] Cubeta de Hielo Silicona 160 Mini Hielos Simplit | B67: 66800506435054 | C67: 8.00
A68: [66800509015029] Cubeta de Hielo Silicona 6 Hielos Redondos Simplit | B68: 66800509015029 | C68: 10.00
A69: [67327712330533] Set de 7 Contenedores Herméticos Plástico Negro Simplit | B69: 67327712330533 | C69: 74.00
A70: [67933831843970] Parlante Portatil Bluetooth Lhotse Tune Up Negro | B70: 67933831843970 | C70: 100.00
A71: [67933833934278] Parlante Portatil Bluetooth Lhotse Tune Up Rojo | B71: 67933833934278 | C71: 100.00
A72: [67933835121467] Parlante Portatil Bluetooth Lhotse Tune Up Azul | B72: 67933835121467 | C72: 10.00
A73: [67933854599885] Set 2 Vasos Cobre Moscow Mule Mojito Bar + Bombilla Simplit | B73: 67933854599885 | C73: 7.00
A74: [67933857637909] Set 6 Vasos Largo Vintage Charlotte 350ml Simplit | B74: 67933857637909 | C74: 14.00
A75: [67933859111971] Set 6 Vasos redondos Virginia 340ml Simplit | B75: 67933859111971 | C75: 12.00
... A86: [757450528058] Serum Crecimiento Pestañas Y Cejas Sheet | B86: 757450528058 | C86: 1.00
A87: [BAR-SP24] Imabars 24 piezas | B87: BAR-SP24 | C87: 7.00
A88: [BAR-SP60] Imabars 60 Piezas | B88: BAR-SP60 | C88: 1.00
A89: [CNS10150] Espuma Mousse de Limpieza Facial Caracol Natural 150 ml | B89: CNS10150 | C89: 4.00
A90: [CNS250] Crema Hidratante Antiedad Antiarrugas Caracol Natural 50 ml | B90: CNS250 | C90: 1.00
A91: [CNS550] Crema Reafirmante Restauradora Facial Caracol Natural 50 ml | B91: CNS550 | C91: 1.00
A92: [CNS630] Serum Rellenador Regenerador Facial Caracol Natural 30 ml | B92: CNS630 | C92: 3.00
A93: [CNS720] Crema Contorno de Ojos Caracol Natural 20 ml | B93: CNS720 | C93: 3.00
A94: [CNS8200] Tónico Hidratante Facial Caracol Natural 150 ml | B94: CNS8200 | C94: 1.00
A95: [DOT-020] Imadots Mini Juego Magnético | B95: DOT-020 | C95: 1.00
A96: [DOT-030] Imadots Juego Magnético | B96: DOT-030 | C96: 1.00
A97: [DYNHYDLA] Hidrolavadora eléctrica Dynamo WP 1800w 130bar 220/240V 60Hz | B97: DYNHYDLA | C97: 6.00
A98: [DYNLLAIMP] Llave de Impacto Inalámbrica Dynamo 21V + 2 Baterias y Acss | B98: DYNLLAIMP | C98: 22.00
... A286: BFE/Stock | B286: #ERROR | C286: 35.00
A287: [1652825295706] Cafetera Italiana Negra Granito 12 Tazas Simplit | B287: 1652825295706 | C287: 2.00
A288: [1660858118518] Mantequillero Cerámica Tapa Bamboo + Cuchillo 600 ml Simplit | B288: 1660858118518 | C288: 2.00
A289: [1660858416606] Panera Metálica con Tapa Bamboo Blanca Simplit | B289: 1660858416606 | C289: 2.00
A290: [1660859171584] Espumador de Leche 4 en 1 Negro Simplit | B290: 1660859171584 | C290: 2.00
A291: [67933857637909] Set 6 Vasos Largo Vintage Charlotte 350ml Simplit | B291: 67933857637909 | C291: 2.00
A292: [SIMBATOTOUL] Batería de Cocina Toulouse 7 pcs + Accesorios Simplit | B292: SIMBATOTOUL | C292: 2.00
A293: [SIMCUPGL-30] Set de Cuchillería 30 pcs Cubiertos Acero Inoxidable Puglia | B293: SIMCUPGL-30 | C293: 2.00
A294: [SIMCUPRO-4] Set Cuchillos para Queso 4 pcs Provenza Simplit | B294: SIMCUPRO-4 | C294: 2.00
A295: [SIMCUSTA-5] Set Cuchillos Stahl 5 pcs Acero Inoxidable + Taco Simplit | B295: SIMCUSTA-5 | C295: 2.00
A296: [SIMCUVER-CR] Set de Cuchillería 24 pcs Cubiertos Versalle Simplit | B296: SIMCUVER-CR | C296: 4.00
A297: [SIMCUVER-WO] Set de Cuchillería 24 pcs Cubiertos Le Mans Simplit | B297: SIMCUVER-WO | C297: 2.00
A298: [SIMFUESIE] Fuente Ovalada Aperitivo Cerámica 36 cm Siena Simplit | B298: SIMFUESIE | C298: 2.00
A299: [SIMHIECHAR] Hielera Vidrio Charlotte Tapa Madera 3,8lts Simplit | B299: SIMHIECHAR | C299: 2.00
A300: [SIMJULZAMA-16] Juego de Loza 16 pcs Cerámica Amalfi Simplit | B300: SIMJULZAMA-16 | C300: 2.00
A301: [SIMJULZSIE-30] Juego de Loza 30 pcs Cerámica Siena Simplit | B301: SIMJULZSIE-30 | C301: 1.00
A302: [SIMJULZTOS-12] Juego de Loza 12 pcs Cerámica Toscana Simplit | B302: SIMJULZTOS-12 | C302: 2.00
A303: [SIMPLAMA-4] Set 4 Platos Fondo Cerámica 27,4 cm Amalfi Simplit | B303: SIMPLAMA-4 | C303: 2.00
A304: BFFa/Stock | B304: #ERROR | C304: 1,722.00
A305: [1535543463599] Parrilla Portátil Carbón Kettle Roja 17 | B305: 1535543463599 | C305: 7.00
A306: [1538141129434] Pesa Digital Balanza Baño Bluetooth Negra Inteligente | B306: 1538141129434 | C306: 6.00
A307: [1543406075297] Pesa Digital Balanza Baño Bluetooth Blanca Inteligente | B307: 1543406075297 | C307: 3.00
A308: [1548358566329] Mochila Maternal Pañalera Bebé Freaky Mommy Azul Marino | B308: 1548358566329 | C308: 1.00
A309: [1564150627423] Audífonos Lhotse Bluetooth Inalámbrico Rm12 Blanco | B309: 1564150627423 | C309: 129.00
A310: [1564150661249] Audífonos Lhotse Bluetooth Inalámbrico Rm12 Negro | B310: 1564150661249 | C310: 90.00
A311: [1566335721736] Audífonos Lhotse Bluetooth Inalámbrico Rm12 Celeste | B311: 1566335721736 | C311: 57.00
A312: [1566849947902] Mochila Antirrobo Lhotse Gris Oscuro MA147 | B312: 1566849947902 | C312: 10.00
A313: [1571423280815] Pick-up Pad Lhotse Porta 5 Bicicletas | B313: 1571423280815 | C313: 6.00
A314: [1589209076056] Lentes Antiparras Transparentes Protección | B314: 1589209076056 | C314: 10.00
A315: [1592492799236] Audífonos Lhotse Bluetooth Inalámbrico Rm12 Rosado | B315: 1592492799236 | C315: 24.00
A316: [1597086499840] Audífonos Lhotse RM7 Pro Inalámbrico Blanco | B316: 1597086499840 | C316: 1.00
... A371: [1659992478281] Botella Térmica Coihue Negra 800 ml Lhotse | B371: 1659992478281 | C371: 1.00
A372: [1660-SET] Set 6 Vasos Vidrio Super Sham Rock 311 Ml Libbey | B372: 1660-SET | C372: 8.00
A373: [1660857800718] Especiero Condimentos de Madera 8 Frascos Vidrio Simplit | B373: 1660857800718 | C373: 3.00
A374: [1660858101318] Mantequillero de Cerámica Tapa Bamboo 300 ml Simplit | B374: 1660858101318 | C374: 1.00
A375: [1660858118518] Mantequillero Cerámica Tapa Bamboo + Cuchillo 600 ml Simplit | B375: 1660858118518 | C375: 3.00
A376: [1660858235219] Termo Jarra Insulado 1 Lt Gris Simplit | B376: 1660858235219 | C376: 3.00
A377: [1660858356962] Secaplatos Escurridor 2 Niveles Acero Inox Blanco Simplit | B377: 1660858356962 | C377: 11.00
A378: [1660858416606] Panera Metálica con Tapa Bamboo Blanca Simplit | B378: 1660858416606 | C378: 2.00
A379: [1660858702400] Set 2 Molinillos de Sal y Pimienta Vidrio Simplit | B379: 1660858702400 | C379: 45.00
A380: [1660858756233] Contenedor de Cerámica Hermético Tapa Madera S Negro Simplit | B380: 1660858756233 | C380: 3.00
A381: [1660858793429] Contenedor de Cerámica Hermético Tapa Madera L Negro Simplit | B381: 1660858793429 | C381: 1.00
A382: [1660858844449] Contenedor Cerámica Hermético Tapa Madera L Blanco Simplit | B382: 1660858844449 | C382: 1.00
A383: [1660859287583] Set 4 Contenedores de Vidrio Herméticos Tapa Bamboo Simplit | B383: 1660859287583 | C383: 2.00
A384: [1661-SET] Set 6 Vasos Super Sham Vidrio 355 Ml Libbey | B384: 1661-SET | C384: 21.00
A385: [1661872956577] Set 3 Fuentes de Cerámica para Horno Celeste Simplit | B385: 1661872956577 | C385: 4.00
A386: [1661873779510] Mochila Street Lhotse 20 Lt Verde | B386: 1661873779510 | C386: 15.00
A387: [1662389376894] Set 3 Contenedores Cerámica Hermético Blanco Simplit | B387: 1662389376894 | C387: 1.00
A388: [1700887] Juego 5 Pzas De Vidrio Tempo Libbey | B388: 1700887 | C388: 1.00
A389: [1709226] Jarra Pitcher 2,2Lt Brisa Libbey | B389: 1709226 | C389: 2.00
A390: [1720434] Set 6 Vasos Heavy Sham HB 483ml Libbey | B390: 1720434 | C390: 3.00
A391: [1720662] Set 6 Vasos Koba 472 ml Libbey | B391: 1720662 | C391: 3.00
A392: [184957] Termo Sifón Vidrio 2,5 Lt Thermos | B392: 184957 | C392: 2.00
A393: [186296] Termo Multiuso Acero 1 Lt Thermos | B393: 186296 | C393: 5.00
A394: [20-65032] Signature Face Stick Tinted SPF 50 Sun Bum | B394: 20-65032 | C394: 1.00
A395: [25533] Alcancia Oink Cerámica Balvi | B395: 25533 | C395: 3.00
A396: [25782] Marco Fotos Madisson Magneticos X6 Balvi | B396: 25782 | C396: 2.00
A397: [26667] Perchero Shiitake Acero Blanco Balvi | B397: 26667 | C397: 1.00
A398: [26668] Perchero Shiitake Madera Blanco Balvi | B398: 26668 | C398: 2.00
...

Sheet Resumen Maestra
K2: 100 | L2: 50 | M2: 10
F3: P Etiqueta | G3: PVP | H3: Costo Oferta | I3: Costo MLL | K3: Costos B2B Según volumen | O3: Margenes B2B Según volumen
F4: 0 | G4: 0 | H4: 0 | I4: 0 | K4: 0 | L4: 0.071425 | M4: 0.14286 | O4: 100+ | P4: 50 y 99 | Q4: 10 y 49
B5: Total | F5: 0 | G5: 0 | H5: 0 | I5: 0 | K5: =$H5*(1+K$4) -> 0 | L5: =$H5*(1+L$4) -> 0 | M5: =$H5*(1+M$4) -> 0 | O5: =1-K5/(G5/1.19) -> #DIV/0! | P5: =1-L5/(G5/1.19) -> #DIV/0! | Q5: =1-M5/(G5/1.19) -> #DIV/0!
B6: Bandú | C6: Accesorios de Bebe | D6: Accesorios de Bebe | E6: BDBBYCHK | F6: 0.41 | G6: 14572 | H6: 0 | I6: 0 | K6: =$H6*(1+K$4) -> 0 | L6: =$H6*(1+L$4) -> 0 | M6: =$H6*(1+M$4) -> 0 | O6: =1-K6/(G6/1.19) -> 1 | P6: =1-L6/(G6/1.19) -> 1 | Q6: =1-M6/(G6/1.19) -> 1
C7: Jueguetes de Rol | D7: Cocina y Accesorios | E7: BDCASMUÑEC | F7: 0.33 | G7: 11696 | H7: 0 | I7: 0 | K7: =$H7*(1+K$4) -> 0 | L7: =$H7*(1+L$4) -> 0 | M7: =$H7*(1+M$4) -> 0 | O7: =1-K7/(G7/1.19) -> 1 | P7: =1-L7/(G7/1.19) -> 1 | Q7: =1-M7/(G7/1.19) -> 1
E8: BDCOCGRND | F8: 0.55 | G8: 38687 | H8: 0 | I8: 0 | K8: =$H8*(1+K$4) -> 0 | L8: =$H8*(1+L$4) -> 0 | M8: =$H8*(1+M$4) -> 0 | O8: =1-K8/(G8/1.19) -> 1 | P8: =1-L8/(G8/1.19) -> 1 | Q8: =1-M8/(G8/1.19) -> 1
E9: BDCOCMEDI | F9: 0.52 | G9: 30424 | H9: 0 | I9: 0 | K9: =$H9*(1+K$4) -> 0 | L9: =$H9*(1+L$4) -> 0 | M9: =$H9*(1+M$4) -> 0 | O9: =1-K9/(G9/1.19) -> 1 | P9: =1-L9/(G9/1.19) -> 1 | Q9: =1-M9/(G9/1.19) -> 1
E10: BDCOCMIN | F10: 0.33 | G10: 3853 | H10: 0 | I10: 0 | K10: =$H10*(1+K$4) -> 0 | L10: =$H10*(1+L$4) -> 0 | M10: =$H10*(1+M$4) -> 0 | O10: =1-K10/(G10/1.19) -> 1 | P10: =1-L10/(G10/1.19) -> 1 | Q10: =1-M10/(G10/1.19) -> 1
E11: BDCOCPQMD | F11: 0.36 | G11: 14822 | H11: 0 | I11: 0 | K11: =$H11*(1+K$4) -> 0 | L11: =$H11*(1+L$4) -> 0 | M11: =$H11*(1+M$4) -> 0 | O11: =1-K11/(G11/1.19) -> 1 | P11: =1-L11/(G11/1.19) -> 1 | Q11: =1-M11/(G11/1.19) -> 1
E12: BDELECTCOC | F12: 0.42 | G12: 4171 | H12: 0 | I12: 0 | K12: =$H12*(1+K$4) -> 0 | L12: =$H12*(1+L$4) -> 0 | M12: =$H12*(1+M$4) -> 0 | O12: =1-K12/(G12/1.19) -> 1 | P12: =1-L12/(G12/1.19) -> 1 | Q12: =1-M12/(G12/1.19) -> 1
E13: BDJUESETTE | F13: 0.41 | G13: 4829 | H13: 0 | I13: 0 | K13: =$H13*(1+K$4) -> 0 | L13: =$H13*(1+L$4) -> 0 | M13: =$H13*(1+M$4) -> 0 | O13: =1-K13/(G13/1.19) -> 1 | P13: =1-L13/(G13/1.19) -> 1 | Q13: =1-M13/(G13/1.19) -> 1
E14: BDSETPAST | F14: 0.31 | G14: 3105 | H14: 0 | I14: 0 | K14: =$H14*(1+K$4) -> 0 | L14: =$H14*(1+L$4) -> 0 | M14: =$H14*(1+M$4) -> 0 | O14: =1-K14/(G14/1.19) -> 1 | P14: =1-L14/(G14/1.19) -> 1 | Q14: =1-M14/(G14/1.19) -> 1
D15: Juegos de Oficio | E15: BDSETDOC | F15: 0.46 | G15: 4048 | H15: 0 | I15: 0 | K15: =$H15*(1+K$4) -> 0 | L15: =$H15*(1+L$4) -> 0 | M15: =$H15*(1+M$4) -> 0 | O15: =1-K15/(G15/1.19) -> 1 | P15: =1-L15/(G15/1.19) -> 1 | Q15: =1-M15/(G15/1.19) -> 1
D16: Maquillaje y Belleza | E16: BDSETMAQ | F16: 0.59 | G16: 6989 | H16: 0 | I16: 0 | K16: =$H16*(1+K$4) -> 0 | L16: =$H16*(1+L$4) -> 0 | M16: =$H16*(1+M$4) -> 0 | O16: =1-K16/(G16/1.19) -> 1 | P16: =1-L16/(G16/1.19) -> 1 | Q16: =1-M16/(G16/1.19) -> 1
E17: BDTOCMD-WH | F17: 0.43 | G17: 25417 | H17: 0 | I17: 0 | K17: =$H17*(1+K$4) -> 0 | L17: =$H17*(1+L$4) -> 0 | M17: =$H17*(1+M$4) -> 0 | O17: =1-K17/(G17/1.19) -> 1 | P17: =1-L17/(G17/1.19) -> 1 | Q17: =1-M17/(G17/1.19) -> 1
C18: Juguetes de Armado | D18: Pistas y Vehiculos | E18: BDHELMAD | F18: 0.38 | G18: 8898 | H18: 0 | I18: 0 | K18: =$H18*(1+K$4) -> 0 | L18: =$H18*(1+L$4) -> 0 | M18: =$H18*(1+M$4) -> 0 | O18: =1-K18/(G18/1.19) -> 1 | P18: =1-L18/(G18/1.19) -> 1 | Q18: =1-M18/(G18/1.19) -> 1
E19: BDJUEAUT | F19: 0.44 | G19: 5118 | H19: 0 | I19: 0 | K19: =$H19*(1+K$4) -> 0 | L19: =$H19*(1+L$4) -> 0 | M19: =$H19*(1+M$4) -> 0 | O19: =1-K19/(G19/1.19) -> 1 | P19: =1-L19/(G19/1.19) -> 1 | Q19: =1-M19/(G19/1.19) -> 1
E20: BDJUETRE | F20: 0.44 | G20: 12986 | H20: 0 | I20: 0 | K20: =$H20*(1+K$4) -> 0 | L20: =$H20*(1+L$4) -> 0 | M20: =$H20*(1+M$4) -> 0 | O20: =1-K20/(G20/1.19) -> 1 | P20: =1-L20/(G20/1.19) -> 1 | Q20: =1-M20/(G20/1.19) -> 1
D21: Sets de Construccion | E21: BDMESHERRA | F21: 0.31 | G21: 9074 | H21: 0 | I21: 0 | K21: =$H21*(1+K$4) -> 0 | L21: =$H21*(1+L$4) -> 0 | M21: =$H21*(1+M$4) -> 0 | O21: =1-K21/(G21/1.19) -> 1 | P21: =1-L21/(G21/1.19) -> 1 | Q21: =1-M21/(G21/1.19) -> 1
C22: Juguetes de Motricidad | D22: Andador y Correpasillos | E22: BDANDDIDAC-GR | F22: 0.52 | G22: 15192 | H22: 0 | I22: 0 | K22: =$H22*(1+K$4) -> 0 | L22: =$H22*(1+L$4) -> 0 | M22: =$H22*(1+M$4) -> 0 | O22: =1-K22/(G22/1.19) -> 1 | P22: =1-L22/(G22/1.19) -> 1 | Q22: =1-M22/(G22/1.19) -> 1
E23: BDANDDIDAC-PK | F23: 0.5 | G23: 14751 | H23: 0 | I23: 0 | K23: =$H23*(1+K$4) -> 0 | L23: =$H23*(1+L$4) -> 0 | M23: =$H23*(1+M$4) -> 0 | O23: =1-K23/(G23/1.19) -> 1 | P23: =1-L23/(G23/1.19) -> 1 | Q23: =1-M23/(G23/1.19) -> 1
E24: BNANDCONTRU | F24: 0.43 | G24: 12706 | H24: 0 | I24: 0 | K24: =$H24*(1+K$4) -> 0 | L24: =$H24*(1+L$4) -> 0 | M24: =$H24*(1+M$4) -> 0 | O24: =1-K24/(G24/1.19) -> 1 | P24: =1-L24/(G24/1.19) -> 1 | Q24: =1-M24/(G24/1.19) -> 1
D25: Didacticos | E25: BDMBAVTHIE | F25: 0.18 | G25: 2453 | H25: 0 | I25: 0 | K25: =$H25*(1+K$4) -> 0 | L25: =$H25*(1+L$4) -> 0 | M25: =$H25*(1+M$4) -> 0 | O25: =1-K25/(G25/1.19) -> 1 | P25: =1-L25/(G25/1.19) -> 1 | Q25: =1-M25/(G25/1.19) -> 1
E26: BDMBBOESP | F26: 0.23 | G26: 1338 | H26: 0 | I26: 0 | K26: =$H26*(1+K$4) -> 0 | L26: =$H26*(1+L$4) -> 0 | M26: =$H26*(1+M$4) -> 0 | O26: =1-K26/(G26/1.19) -> 1 | P26: =1-L26/(G26/1.19) -> 1 | Q26: =1-M26/(G26/1.19) -> 1
E27: BDMBCIUMG | F27: 0.2 | G27: 2247 | H27: 0 | I27: 0 | K27: =$H27*(1+K$4) -> 0 | L27: =$H27*(1+L$4) -> 0 | M27: =$H27*(1+M$4) -> 0 | O27: =1-K27/(G27/1.19) -> 1 | P27: =1-L27/(G27/1.19) -> 1 | Q27: =1-M27/(G27/1.19) -> 1
E28: BDMBMNMRIO | F28: 0.27 | G28: 2343 | H28: 0 | I28: 0 | K28: =$H28*(1+K$4) -> 0 | L28: =$H28*(1+L$4) -> 0 | M28: =$H28*(1+M$4) -> 0 | O28: =1-K28/(G28/1.19) -> 1 | P28: =1-L28/(G28/1.19) -> 1 | Q28: =1-M28/(G28/1.19) -> 1
E29: BDMBSPAVMRIO | F29: 0.17 | G29: 2541 | H29: 0 | I29: 0 | K29: =$H29*(1+K$4) -> 0 | L29: =$H29*(1+L$4) -> 0 | M29: =$H29*(1+M$4) -> 0 | O29: =1-K29/(G29/1.19) -> 1 | P29: =1-L29/(G29/1.19) -> 1 | Q29: =1-M29/(G29/1.19) -> 1
E30: BDMESDIDAC | F30: 0.48 | G30: 14110 | H30: 0 | I30: 0 | K30: =$H30*(1+K$4) -> 0 | L30: =$H30*(1+L$4) -> 0 | M30: =$H30*(1+M$4) -> 0 | O30: =1-K30/(G30/1.19) -> 1 | P30: =1-L30/(G30/1.19) -> 1 | Q30: =1-M30/(G30/1.19) -> 1
D31: Escalada y Equilibrio | E31: BDGIMPIK | F31: 0.51 | G31: 86833 | H31: 0 | I31: 0 | K31: =$H31*(1+K$4) -> 0 | L31: =$H31*(1+L$4) -> 0 | M31: =$H31*(1+M$4) -> 0 | O31: =1-K31/(G31/1.19) -> 1 | P31: =1-L31/(G31/1.19) -> 1 | Q31: =1-M31/(G31/1.19) -> 1
E32: BDMROBLDESC | F32: 0.49 | G32: 37573 | H32: 0 | I32: 0 | K32: =$H32*(1+K$4) -> 0 | L32: =$H32*(1+L$4) -> 0 | M32: =$H32*(1+M$4) -> 0 | O32: =1-K32/(G32/1.19) -> 1 | P32: =1-L32/(G32/1.19) -> 1 | Q32: =1-M32/(G32/1.19) -> 1
B33: Total Bandú | F33: 10.67 | G33: 390776 | H33: 0 | I33: 0 | K33: =$H33*(1+K$4) -> 0 | L33: =$H33*(1+L$4) -> 0 | M33: =$H33*(1+M$4) -> 0 | O33: =1-K33/(G33/1.19) -> 1 | P33: =1-L33/(G33/1.19) -> 1 | Q33: =1-M33/(G33/1.19) -> 1
B34: Dynamo Tools | C34: Herramientas Eléctricas | D34: Otras | E34: DYNHYDLA | F34: 0.21 | G34: 8616 | H34: 0 | I34: 0 | K34: =$H34*(1+K$4) -> 0 | L34: =$H34*(1+L$4) -> 0 | M34: =$H34*(1+M$4) -> 0 | O34: =1-K34/(G34/1.19) -> 1 | P34: =1-L34/(G34/1.19) -> 1 | Q34: =1-M34/(G34/1.19) -> 1
D35: Taladro y Atornilladores | E35: DYNLLAIMP | F35: 0.27 | G35: 9381 | H35: 0 | I35: 0 | K35: =$H35*(1+K$4) -> 0 | L35: =$H35*(1+L$4) -> 0 | M35: =$H35*(1+M$4) -> 0 | O35: =1-K35/(G35/1.19) -> 1 | P35: =1-L35/(G35/1.19) -> 1 | Q35: =1-M35/(G35/1.19) -> 1
E36: DYNTALCPER | F36: 0.42 | G36: 7323 | H36: 0 | I36: 0 | K36: =$H36*(1+K$4) -> 0 | L36: =$H36*(1+L$4) -> 0 | M36: =$H36*(1+M$4) -> 0 | O36: =1-K36/(G36/1.19) -> 1 | P36: =1-L36/(G36/1.19) -> 1 | Q36: =1-M36/(G36/1.19) -> 1
E37: DYNTALIMPA | F37: 0.37 | G37: 19336 | H37: 0 | I37: 0 | K37: =$H37*(1+K$4) -> 0 | L37: =$H37*(1+L$4) -> 0 | M37: =$H37*(1+M$4) -> 0 | O37: =1-K37/(G37/1.19) -> 1 | P37: =1-L37/(G37/1.19) -> 1 | Q37: =1-M37/(G37/1.19) -> 1
E38: DYNTALPOW | F38: 0.29 | G38: 10209 | H38: 0 | I38: 0 | K38: =$H38*(1+K$4) -> 0 | L38: =$H38*(1+L$4) -> 0 | M38: =$H38*(1+M$4) -> 0 | O38: =1-K38/(G38/1.19) -> 1 | P38: =1-L38/(G38/1.19) -> 1 | Q38: =1-M38/(G38/1.19) -> 1
E39: DYNTALSCA | F39: 0.27 | G39: 3129 | H39: 0 | I39: 0 | K39: =$H39*(1+K$4) -> 0 | L39: =$H39*(1+L$4) -> 0 | M39: =$H39*(1+M$4) -> 0 | O39: =1-K39/(G39/1.19) -> 1 | P39: =1-L39/(G39/1.19) -> 1 | Q39: =1-M39/(G39/1.19) -> 1
E40: DYNTALSPER | F40: 0.44 | G40: 7766 | H40: 0 | I40: 0 | K40: =$H40*(1+K$4) -> 0 | L40: =$H40*(1+L$4) -> 0 | M40: =$H40*(1+M$4) -> 0 | O40: =1-K40/(G40/1.19) -> 1 | P40: =1-L40/(G40/1.19) -> 1 | Q40: =1-M40/(G40/1.19) -> 1
B41: Total Dynamo Tools | F41: 2.27 | G41: 65760 | H41: 0 | I41: 0 | K41: =$H41*(1+K$4) -> 0 | L41: =$H41*(1+L$4) -> 0 | M41: =$H41*(1+M$4) -> 0 | O41: =1-K41/(G41/1.19) -> 1 | P41: =1-L41/(G41/1.19) -> 1 | Q41: =1-M41/(G41/1.19) -> 1
B42: GOYA | C42: Aromatización | D42: Difusor | E42: GOYADIVA-FM | F42: 0.33 | G42: 3671 | H42: 0 | I42: 0 | K42: =$H42*(1+K$4) -> 0 | L42: =$H42*(1+L$4) -> 0 | M42: =$H42*(1+M$4) -> 0 | O42: =1-K42/(G42/1.19) -> 1 | P42: =1-L42/(G42/1.19) -> 1 | Q42: =1-M42/(G42/1.19) -> 1
E43: GOYADIVA-SW | F43: 0.33 | G43: 3671 | H43: 0 | I43: 0 | K43: =$H43*(1+K$4) -> 0 | L43: =$H43*(1+L$4) -> 0 | M43: =$H43*(1+M$4) -> 0 | O43: =1-K43/(G43/1.19) -> 1 | P43: =1-L43/(G43/1.19) -> 1 | Q43: =1-M43/(G43/1.19) -> 1
E44: GOYADVTR-CV | F44: 0.33 | G44: 3671 | H44: 0 | I44: 0 | K44: =$H44*(1+K$4) -> 0 | L44: =$H44*(1+L$4) -> 0 | M44: =$H44*(1+M$4) -> 0 | O44: =1-K44/(G44/1.19) -> 1 | P44: =1-L44/(G44/1.19) -> 1 | Q44: =1-M44/(G44/1.19) -> 1
E45: GOYADVTR-VS | F45: 0.33 | G45: 3671 | H45: 0 | I45: 0 | K45: =$H45*(1+K$4) -> 0 | L45: =$H45*(1+L$4) -> 0 | M45: =$H45*(1+M$4) -> 0 | O45: =1-K45/(G45/1.19) -> 1 | P45: =1-L45/(G45/1.19) -> 1 | Q45: =1-M45/(G45/1.19) -> 1
D46: Home Spray | E46: GOYAHOSP-CV | F46: 0.25 | G46: 2494 | H46: 0 | I46: 0 | K46: =$H46*(1+K$4) -> 0 | L46: =$H46*(1+L$4) -> 0 | M46: =$H46*(1+M$4) -> 0 | O46: =1-K46/(G46/1.19) -> 1 | P46: =1-L46/(G46/1.19) -> 1 | Q46: =1-M46/(G46/1.19) -> 1
E47: GOYAHOSP-FM | F47: 0.25 | G47: 2494 | H47: 0 | I47: 0 | K47: =$H47*(1+K$4) -> 0 | L47: =$H47*(1+L$4) -> 0 | M47: =$H47*(1+M$4) -> 0 | O47: =1-K47/(G47/1.19) -> 1 | P47: =1-L47/(G47/1.19) -> 1 | Q47: =1-M47/(G47/1.19) -> 1
E48: GOYAHOSP-SW | F48: 0.25 | G48: 2494 | H48: 0 | I48: 0 | K48: =$H48*(1+K$4) -> 0 | L48: =$H48*(1+L$4) -> 0 | M48: =$H48*(1+M$4) -> 0 | O48: =1-K48/(G48/1.19) -> 1 | P48: =1-L48/(G48/1.19) -> 1 | Q48: =1-M48/(G48/1.19) -> 1
E49: GOYAHOSP-VS | F49: 0.25 | G49: 2494 | H49: 0 | I49: 0 | K49: =$H49*(1+K$4) -> 0 | L49: =$H49*(1+L$4) -> 0 | M49: =$H49*(1+M$4) -> 0 | O49: =1-K49/(G49/1.19) -> 1 | P49: =1-L49/(G49/1.19) -> 1 | Q49: =1-M49/(G49/1.19) -> 1
B50: Total GOYA | F50: 2.32 | G50: 24660 | H50: 0 | I50: 0 | K50: =$H50*(1+K$4) -> 0 | L50: =$H50*(1+L$4) -> 0 | M50: =$H50*(1+M$4) -> 0 | O50: =1-K50/(G50/1.19) -> 1 | P50: =1-L50/(G50/1.19) -> 1 | Q50: =1-M50/(G50/1.19) -> 1
B51: Innovate-K | C51: Gasfiteria | D51: Baroscopios | E51: 1661877043628 | F51: 0.27 | G51: 86268 | H51: 0 | I51: 0 | K51: =$H51*(1+K$4) -> 0 | L51: =$H51*(1+L$4) -> 0 | M51: =$H51*(1+M$4) -> 0 | O51: =1-K51/(G51/1.19) -> 1 | P51: =1-L51/(G51/1.19) -> 1 | Q51: =1-M51/(G51/1.19) -> 1
E52: 1661877072053 | F52: 0.28 | G52: 107303 | H52: 0 | I52: 0 | K52: =$H52*(1+K$4) -> 0 | L52: =$H52*(1+L$4) -> 0 | M52: =$H52*(1+M$4) -> 0 | O52: =1-K52/(G52/1.19) -> 1 | P52: =1-L52/(G52/1.19) -> 1 | Q52: =1-M52/(G52/1.19) -> 1
E53: INCAMINS92-40 | F53: 0.76 | G53: 353800 | H53: 0 | I53: 0 | K53: =$H53*(1+K$4) -> 0 | L53: =$H53*(1+L$4) -> 0 | M53: =$H53*(1+M$4) -> 0 | O53: =1-K53/(G53/1.19) -> 1 | P53: =1-L53/(G53/1.19) -> 1 | Q53: =1-M53/(G53/1.19) -> 1
E54: INNCAMINS-7F | F54: 0.41 | G54: 387734 | H54: 0 | I54: 0 | K54: =$H54*(1+K$4) -> 0 | L54: =$H54*(1+L$4) -> 0 | M54: =$H54*(1+M$4) -> 0 | O54: =1-K54/(G54/1.19) -> 1 | P54: =1-L54/(G54/1.19) -> 1 | Q54: =1-M54/(G54/1.19) -> 1
E55: INNCAMINS-96 | F55: 0.44 | G55: 332669 | H55: 0 | I55: 0 | K55: =$H55*(1+K$4) -> 0 | L55: =$H55*(1+L$4) -> 0 | M55: =$H55*(1+M$4) -> 0 | O55: =1-K55/(G55/1.19) -> 1 | P55: =1-L55/(G55/1.19) -> 1 | Q55: =1-M55/(G55/1.19) -> 1
E56: INNCAMINS-U9 | F56: 0.43 | G56: 38080 | H56: 0 | I56: 0 | K56: =$H56*(1+K$4) -> 0 | L56: =$H56*(1+L$4) -> 0 | M56: =$H56*(1+M$4) -> 0 | O56: =1-K56/(G56/1.19) -> 1 | P56: =1-L56/(G56/1.19) -> 1 | Q56: =1-M56/(G56/1.19) -> 1
E57: INNCAMINSH3-70 | F57: 0.47 | G57: 1661794 | H57: 0 | I57: 0 | K57: =$H57*(1+K$4) -> 0 | L57: =$H57*(1+L$4) -> 0 | M57: =$H57*(1+M$4) -> 0 | O57: =1-K57/(G57/1.19) -> 1 | P57: =1-L57/(G57/1.19) -> 1 | Q57: =1-M57/(G57/1.19) -> 1
E58: INNCAMINSH5-20 | F58: 0.49 | G58: 276152 | H58: 0 | I58: 0 | K58: =$H58*(1+K$4) -> 0 | L58: =$H58*(1+L$4) -> 0 | M58: =$H58*(1+M$4) -> 0 | O58: =1-K58/(G58/1.19) -> 1 | P58: =1-L58/(G58/1.19) -> 1 | Q58: =1-M58/(G58/1.19) -> 1
E59: INNCAMINSH5512-20 | F59: 0.49 | G59: 399526 | H59: 0 | I59: 0 | K59: =$H59*(1+K$4) -> 0 | L59: =$H59*(1+L$4) -> 0 | M59: =$H59*(1+M$4) -> 0 | O59: =1-K59/(G59/1.19) -> 1 | P59: =1-L59/(G59/1.19) -> 1 | Q59: =1-M59/(G59/1.19) -> 1
E60: INNCAMINSH6-40 | F60: 0.49 | G60: 285373 | H60: 0 | I60: 0 | K60: =$H60*(1+K$4) -> 0 | L60: =$H60*(1+L$4) -> 0 | M60: =$H60*(1+M$4) -> 0 | O60: =1-K60/(G60/1.19) -> 1 | P60: =1-L60/(G60/1.19) -> 1 | Q60: =1-M60/(G60/1.19) -> 1
C61: Hogar | D61: Accesorios para Baño | E61: 1571055493973 | F61: 0.33 | G61: 9715 | H61: 0 | I61: 0 | K61: =$H61*(1+K$4) -> 0 | L61: =$H61*(1+L$4) -> 0 | M61: =$H61*(1+M$4) -> 0 | O61: =1-K61/(G61/1.19) -> 1 | P61: =1-L61/(G61/1.19) -> 1 | Q61: =1-M61/(G61/1.19) -> 1
B62: Total Innovate-K | F62: 4.86 | G62: 3938414 | H62: 0 | I62: 0 | K62: =$H62*(1+K$4) -> 0 | L62: =$H62*(1+L$4) -> 0 | M62: =$H62*(1+M$4) -> 0 | O62: =1-K62/(G62/1.19) -> 1 | P62: =1-L62/(G62/1.19) -> 1 | Q62: =1-M62/(G62/1.19) -> 1
B63: Klip Klap | C63: Instrumentos Musicales | D63: Metalofonos | E63: 67114505814137 | F63: 0.49 | G63: 8806 | H63: 0 | I63: 0 | K63: =$H63*(1+K$4) -> 0 | L63: =$H63*(1+L$4) -> 0 | M63: =$H63*(1+M$4) -> 0 | O63: =1-K63/(G63/1.19) -> 1 | P63: =1-L63/(G63/1.19) -> 1 | Q63: =1-M63/(G63/1.19) -> 1
E64: 67114508251225 | F64: 0.42 | G64: 8619 | H64: 0 | I64: 0 | K64: =$H64*(1+K$4) -> 0 | L64: =$H64*(1+L$4) -> 0 | M64: =$H64*(1+M$4) -> 0 | O64: =1-K64/(G64/1.19) -> 1 | P64: =1-L64/(G64/1.19) -> 1 | Q64: =1-M64/(G64/1.19) -> 1
B65: Total Klip Klap | F65: 0.91 | G65: 17425 | H65: 0 | I65: 0 | K65: =$H65*(1+K$4) -> 0 | L65: =$H65*(1+L$4) -> 0 | M65: =$H65*(1+M$4) -> 0 | O65: =1-K65/(G65/1.19) -> 1 | P65: =1-L65/(G65/1.19) -> 1 | Q65: =1-M65/(G65/1.19) -> 1
B66: Levo | C66: Accesorios | D66: Cable Cargador | E66: LVCABTC-BK | F66: 0.56 | G66: 2297 | H66: 0 | I66: 0 | K66: =$H66*(1+K$4) -> 0 | L66: =$H66*(1+L$4) -> 0 | M66: =$H66*(1+M$4) -> 0 | O66: =1-K66/(G66/1.19) -> 1 | P66: =1-L66/(G66/1.19) -> 1 | Q66: =1-M66/(G66/1.19) -> 1
E67: LVCABTC-WH | F67: 0.56 | G67: 2297 | H67: 0 | I67: 0 | K67: =$H67*(1+K$4) -> 0 | L67: =$H67*(1+L$4) -> 0 | M67: =$H67*(1+M$4) -> 0 | O67: =1-K67/(G67/1.19) -> 1 | P67: =1-L67/(G67/1.19) -> 1 | Q67: =1-M67/(G67/1.19) -> 1
E68: LVCABTCLIGH-WH | F68: 0.76 | G68: 2684 | H68: 0 | I68: 0 | K68: =$H68*(1+K$4) -> 0 | L68: =$H68*(1+L$4) -> 0 | M68: =$H68*(1+M$4) -> 0 | O68: =1-K68/(G68/1.19) -> 1 | P68: =1-L68/(G68/1.19) -> 1 | Q68: =1-M68/(G68/1.19) -> 1
D69: Cargador Automovil | E69: 1650299083874 | F69: 0.33 | G69: 2937 | H69: 0 | I69: 0 | K69: =$H69*(1+K$4) -> 0 | L69: =$H69*(1+L$4) -> 0 | M69: =$H69*(1+M$4) -> 0 | O69: =1-K69/(G69/1.19) -> 1 | P69: =1-L69/(G69/1.19) -> 1 | Q69: =1-M69/(G69/1.19) -> 1
E70: 1652825203439 | F70: 0.27 | G70: 2420 | H70: 0 | I70: 0 | K70: =$H70*(1+K$4) -> 0 | L70: =$H70*(1+L$4) -> 0 | M70: =$H70*(1+M$4) -> 0 | O70: =1-K70/(G70/1.19) -> 1 | P70: =1-L70/(G70/1.19) -> 1 | Q70: =1-M70/(G70/1.19) -> 1
D71: Cargador de Celular | E71: LVCAR25W-BK | F71: 0.48 | G71: 1986 | H71: 0 | I71: 0 | K71: =$H71*(1+K$4) -> 0 | L71: =$H71*(1+L$4) -> 0 | M71: =$H71*(1+M$4) -> 0 | O71: =1-K71/(G71/1.19) -> 1 | P71: =1-L71/(G71/1.19) -> 1 | Q71: =1-M71/(G71/1.19) -> 1
E72: LVCAR25W-WH | F72: 0.48 | G72: 1986 | H72: 0 | I72: 0 | K72: =$H72*(1+K$4) -> 0 | L72: =$H72*(1+L$4) -> 0 | M72: =$H72*(1+M$4) -> 0 | O72: =1-K72/(G72/1.19) -> 1 | P72: =1-L72/(G72/1.19) -> 1 | Q72: =1-M72/(G72/1.19) -> 1
E73: LVCAR45W-BK | F73: 0.41 | G73: 2176 | H73: 0 | I73: 0 | K73: =$H73*(1+K$4) -> 0 | L73: =$H73*(1+L$4) -> 0 | M73: =$H73*(1+M$4) -> 0 | O73: =1-K73/(G73/1.19) -> 1 | P73: =1-L73/(G73/1.19) -> 1 | Q73: =1-M73/(G73/1.19) -> 1
E74: LVCAR45W-WH | F74: 0.41 | G74: 2176 | H74: 0 | I74: 0 | K74: =$H74*(1+K$4) -> 0 | L74: =$H74*(1+L$4) -> 0 | M74: =$H74*(1+M$4) -> 0 | O74: =1-K74/(G74/1.19) -> 1 | P74: =1-L74/(G74/1.19) -> 1 | Q74: =1-M74/(G74/1.19) -> 1
D75: Dispositivo Multipuerto | E75: LVHUBMP-5 | F75: 0.5 | G75: 3855 | H75: 0 | I75: 0 | K75: =$H75*(1+K$4) -> 0 | L75: =$H75*(1+L$4) -> 0 | M75: =$H75*(1+M$4) -> 0 | O75: =1-K75/(G75/1.19) -> 1 | P75: =1-L75/(G75/1.19) -> 1 | Q75: =1-M75/(G75/1.19) -> 1
E76: LVHUBMP-6 | F76: 0.51 | G76: 3583 | H76: 0 | I76: 0 | K76: =$H76*(1+K$4) -> 0 | L76: =$H76*(1+L$4) -> 0 | M76: =$H76*(1+M$4) -> 0 | O76: =1-K76/(G76/1.19) -> 1 | P76: =1-L76/(G76/1.19) -> 1 | Q76: =1-M76/(G76/1.19) -> 1
C77: Mochilas y Fundas | D77: Fundas | E77: LVFNOTHS13-BK | F77: 0.41 | G77: 5520 | H77: 0 | I77: 0 | K77: =$H77*(1+K$4) -> 0 | L77: =$H77*(1+L$4) -> 0 | M77: =$H77*(1+M$4) -> 0 | O77: =1-K77/(G77/1.19) -> 1 | P77: =1-L77/(G77/1.19) -> 1 | Q77: =1-M77/(G77/1.19) -> 1
E78: LVFNOTHS15-BK | F78: 0.35 | G78: 5139 | H78: 0 | I78: 0 | K78: =$H78*(1+K$4) -> 0 | L78: =$H78*(1+L$4) -> 0 | M78: =$H78*(1+M$4) -> 0 | O78: =1-K78/(G78/1.19) -> 1 | P78: =1-L78/(G78/1.19) -> 1 | Q78: =1-M78/(G78/1.19) -> 1
E79: LVFUEX-BK | F79: -0.3 | G79: -2623 | H79: 0 | I79: 0 | K79: =$H79*(1+K$4) -> 0 | L79: =$H79*(1+L$4) -> 0 | M79: =$H79*(1+M$4) -> 0 | O79: =1-K79/(G79/1.19) -> 1 | P79: =1-L79/(G79/1.19) -> 1 | Q79: =1-M79/(G79/1.19) -> 1
E80: LVFUEX-GR | F80: 0.1 | G80: 857 | H80: 0 | I80: 0 | K80: =$H80*(1+K$4) -> 0 | L80: =$H80*(1+L$4) -> 0 | M80: =$H80*(1+M$4) -> 0 | O80: =1-K80/(G80/1.19) -> 1 | P80: =1-L80/(G80/1.19) -> 1 | Q80: =1-M80/(G80/1.19) -> 1
D81: Mochilas | E81: 1659999392257 | F81: 0.52 | G81: 4004 | H81: 0 | I81: 0 | K81: =$H81*(1+K$4) -> 0 | L81: =$H81*(1+L$4) -> 0 | M81: =$H81*(1+M$4) -> 0 | O81: =1-K81/(G81/1.19) -> 1 | P81: =1-L81/(G81/1.19) -> 1 | Q81: =1-M81/(G81/1.19) -> 1
E82: 1659999410637 | F82: 0.54 | G82: 4115 | H82: 0 | I82: 0 | K82: =$H82*(1+K$4) -> 0 | L82: =$H82*(1+L$4) -> 0 | M82: =$H82*(1+M$4) -> 0 | O82: =1-K82/(G82/1.19) -> 1 | P82: =1-L82/(G82/1.19) -> 1 | Q82: =1-M82/(G82/1.19) -> 1
E83: LVMOMA-BK | F83: 0.41 | G83: 6034 | H83: 0 | I83: 0 | K83: =$H83*(1+K$4) -> 0 | L83: =$H83*(1+L$4) -> 0 | M83: =$H83*(1+M$4) -> 0 | O83: =1-K83/(G83/1.19) -> 1 | P83: =1-L83/(G83/1.19) -> 1 | Q83: =1-M83/(G83/1.19) -> 1
E84: LVMOMA-GR | F84: 0.41 | G84: 6091 | H84: 0 | I84: 0 | K84: =$H84*(1+K$4) -> 0 | L84: =$H84*(1+L$4) -> 0 | M84: =$H84*(1+M$4) -> 0 | O84: =1-K84/(G84/1.19) -> 1 | P84: =1-L84/(G84/1.19) -> 1 | Q84: =1-M84/(G84/1.19) -> 1
E85: LVMOVITR-BK | F85: 0.39 | G85: 11349 | H85: 0 | I85: 0 | K85: =$H85*(1+K$4) -> 0 | L85: =$H85*(1+L$4) -> 0 | M85: =$H85*(1+M$4) -> 0 | O85: =1-K85/(G85/1.19) -> 1 | P85: =1-L85/(G85/1.19) -> 1 | Q85: =1-M85/(G85/1.19) -> 1
E86: LVMOWO-BK | F86: 0.4 | G86: 5925 | H86: 0 | I86: 0 | K86: =$H86*(1+K$4) -> 0 | L86: =$H86*(1+L$4) -> 0 | M86: =$H86*(1+M$4) -> 0 | O86: =1-K86/(G86/1.19) -> 1 | P86: =1-L86/(G86/1.19) -> 1 | Q86: =1-M86/(G86/1.19) -> 1
C87: Pantallas | D87: Monitores | E87: LVMONEXV-15 | F87: 0.37 | G87: 21702 | H87: 0 | I87: 0 | K87: =$H87*(1+K$4) -> 0 | L87: =$H87*(1+L$4) -> 0 | M87: =$H87*(1+M$4) -> 0 | O87: =1-K87/(G87/1.19) -> 1 | P87: =1-L87/(G87/1.19) -> 1 | Q87: =1-M87/(G87/1.19) -> 1
E88: LVMONPOR-15 | F88: 0.28 | G88: 18933 | H88: 0 | I88: 0 | K88: =$H88*(1+K$4) -> 0 | L88: =$H88*(1+L$4) -> 0 | M88: =$H88*(1+M$4) -> 0 | O88: =1-K88/(G88/1.19) -> 1 | P88: =1-L88/(G88/1.19) -> 1 | Q88: =1-M88/(G88/1.19) -> 1
D89: Pantallas Publicitarias | E89: LVPANTOTPUB-43 | F89: 0.45 | G89: 239696 | H89: 0 | I89: 0 | K89: =$H89*(1+K$4) -> 0 | L89: =$H89*(1+L$4) -> 0 | M89: =$H89*(1+M$4) -> 0 | O89: =1-K89/(G89/1.19) -> 1 | P89: =1-L89/(G89/1.19) -> 1 | Q89: =1-M89/(G89/1.19) -> 1
E90: LVPANTOTPUB-50 | F90: 0.42 | G90: 247318 | H90: 0 | I90: 0 | K90: =$H90*(1+K$4) -> 0 | L90: =$H90*(1+L$4) -> 0 | M90: =$H90*(1+M$4) -> 0 | O90: =1-K90/(G90/1.19) -> 1 | P90: =1-L90/(G90/1.19) -> 1 | Q90: =1-M90/(G90/1.19) -> 1
C91: Perifericos de Computacion | D91: Gaming | E91: 1479750635184 | F91: 0.5 | G91: 2637 | H91: 0 | I91: 0 | K91: =$H91*(1+K$4) -> 0 | L91: =$H91*(1+L$4) -> 0 | M91: =$H91*(1+M$4) -> 0 | O91: =1-K91/(G91/1.19) -> 1 | P91: =1-L91/(G91/1.19) -> 1 | Q91: =1-M91/(G91/1.19) -> 1
E92: 1658329968514 | F92: 0.46 | G92: 5435 | H92: 0 | I92: 0 | K92: =$H92*(1+K$4) -> 0 | L92: =$H92*(1+L$4) -> 0 | M92: =$H92*(1+M$4) -> 0 | O92: =1-K92/(G92/1.19) -> 1 | P92: =1-L92/(G92/1.19) -> 1 | Q92: =1-M92/(G92/1.19) -> 1
E93: 1659989621591 | F93: 0.19 | G93: 3957 | H93: 0 | I93: 0 | K93: =$H93*(1+K$4) -> 0 | L93: =$H93*(1+L$4) -> 0 | M93: =$H93*(1+M$4) -> 0 | O93: =1-K93/(G93/1.19) -> 1 | P93: =1-L93/(G93/1.19) -> 1 | Q93: =1-M93/(G93/1.19) -> 1
E94: 1659990788079 | F94: 0.49 | G94: 5770 | H94: 0 | I94: 0 | K94: =$H94*(1+K$4) -> 0 | L94: =$H94*(1+L$4) -> 0 | M94: =$H94*(1+M$4) -> 0 | O94: =1-K94/(G94/1.19) -> 1 | P94: =1-L94/(G94/1.19) -> 1 | Q94: =1-M94/(G94/1.19) -> 1
E95: 1659990828178 | F95: 0.38 | G95: 4484 | H95: 0 | I95: 0 | K95: =$H95*(1+K$4) -> 0 | L95: =$H95*(1+L$4) -> 0 | M95: =$H95*(1+M$4) -> 0 | O95: =1-K95/(G95/1.19) -> 1 | P95: =1-L95/(G95/1.19) -> 1 | Q95: =1-M95/(G95/1.19) -> 1
E96: 66436804863605 | F96: 0.38 | G96: 4461 | H96: 0 | I96: 0 | K96: =$H96*(1+K$4) -> 0 | L96: =$H96*(1+L$4) -> 0 | M96: =$H96*(1+M$4) -> 0 | O96: =1-K96/(G96/1.19) -> 1 | P96: =1-L96/(G96/1.19) -> 1 | Q96: =1-M96/(G96/1.19) -> 1
E97: LVAUDGM-BK | F97: 0.35 | G97: 9305 | H97: 0 | I97: 0 | K97: =$H97*(1+K$4) -> 0 | L97: =$H97*(1+L$4) -> 0 | M97: =$H97*(1+M$4) -> 0 | O97: =1-K97/(G97/1.19) -> 1 | P97: =1-L97/(G97/1.19) -> 1 | Q97: =1-M97/(G97/1.19) -> 1
E98: LVAUDGM-WH | F98: 0.42 | G98: 12221 | H98: 0 | I98: 0 | K98: =$H98*(1+K$4) -> 0 | L98: =$H98*(1+L$4) -> 0 | M98: =$H98*(1+M$4) -> 0 | O98: =1-K98/(G98/1.19) -> 1 | P98: =1-L98/(G98/1.19) -> 1 | Q98: =1-M98/(G98/1.19) -> 1
E99: LVMPADL-BK | F99: 0.63 | G99: 3675 | H99: 0 | I99: 0 | K99: =$H99*(1+K$4) -> 0 | L99: =$H99*(1+L$4) -> 0 | M99: =$H99*(1+M$4) -> 0 | O99: =1-K99/(G99/1.19) -> 1 | P99: =1-L99/(G99/1.19) -> 1 | Q99: =1-M99/(G99/1.19) -> 1
E100: LVMPADS-BK | F100: 0.74 | G100: 3499 | H100: 0 | I100: 0 | K100: =$H100*(1+K$4) -> 0 | L100: =$H100*(1+L$4) -> 0 | M100: =$H100*(1+M$4) -> 0 | O100: =1-K100/(G100/1.19) -> 1 | P100: =1-L100/(G100/1.19) -> 1 | Q100: =1-M100/(G100/1.19) -> 1
E101: LVMPADXXL-BK | F101: 0.58 | G101: 4403 | H101: 0 | I101: 0 | K101: =$H101*(1+K$4) -> 0 | L101: =$H101*(1+L$4) -> 0 | M101: =$H101*(1+M$4) -> 0 | O101: =1-K101/(G101/1.19) -> 1 | P101: =1-L101/(G101/1.19) -> 1 | Q101: =1-M101/(G101/1.19) -> 1
...

Sheet Urban Maestra
F2: INFORMACION CLIENTE | H2: INFORMACION UNIONX | K2: INFORMACION CLIENTE
F3: UnionX | G3: Cliente | H3: UnionX | K3: Precios Ciente | M3: Costo Cliente | O3: Margen | Q3: Status
A4: CLUSTER | B4: Marca | C4: Sku | D4: Seccion | E4: Familia | F4: Grupo | G4: Descripcion | H4: Costo MLL | I4: ROI | J4: Utilidad UnionX | K4: P Etiqueta | L4: PVP Oferta | M4: Costo | N4: Costo Oferta | O4: Margen Master | P4: Margen Oferta | Q4: Status MLL | R4: MG FRONT | S4: MG COMISION | T4: PVP Oferta Competitivo | U4: Caja Master
A5: A | B5: Atmosphera | C5: 209063 | D5: Alfombras | E5: Alfombras | F5: Alfombra Yute redonda impresa malakite 118 cm | G5: Alfombra Yute redonda impresa malakite 118 cm | H5: 18761 | I5: 0.36 | J5: 10644 | K5: 69990 | L5: 49990 | M5: 41171 | N5: 29406 | O5: 0.3 | P5: 0.3 | Q5: Mix MLL | R5: 0.55 | S5: 0.32
A6: A | B6: Atmosphera | C6: 168857Z | D6: Alfombras | E6: Alfombras | F6: Alfombra Yute Borde Blanco 120 x 170 cm | G6: Alfombra Yute Borde Blanco 120 x 170 cm | H6: 27796 | I6: 0.37 | J6: 16316 | K6: 89990 | L6: 74990 | M6: 52935 | N6: 44112 | O6: 0.3 | P6: 0.3 | Q6: Mix MLL | R6: 0.56 | S6: 0.33
A7: A | B7: Atmosphera | C7: 201982 | D7: Alfombras | E7: Alfombras | F7: Alfombra Yute de pasillo 80 cm x 200 cm | G7: Alfombra Yute de pasillo 80 cm x 200 cm | H7: 20840 | I7: 0.36 | J7: 11507 | K7: 69990 | L7: 54990 | M7: 41171 | N7: 32347 | O7: 0.3 | P7: 0.3 | Q7: Mix MLL | R7: 0.55 | S7: 0.32
A8: A | B8: Atmosphera | C8: 202016 | D8: Alfombras | E8: Alfombras | F8: Alfombra de exterior/interior Luka 120 cm x 170 cm | G8: Alfombra de exterior/interior Luka 120 cm x 170 cm | H8: 27796 | I8: 0.37 | J8: 16316 | K8: 99990 | L8: 74990 | M8: 58818 | N8: 44112 | O8: 0.3 | P8: 0.3 | Q8: Mix MLL | R8: 0.56 | S8: 0.33
A9: A | B9: Atmosphera | C9: 202017 | D9: Alfombras | E9: Alfombras | F9: Alfombra de exterior/interior Luka 160 cm x 230 cm | G9: Alfombra de exterior/interior Luka 160 cm x 230 cm | H9: 48623 | I9: 0.36 | J9: 27841 | K9: 149990 | L9: 129990 | M9: 88229 | N9: 76465 | O9: 0.3 | P9: 0.3 | Q9: Mix MLL | R9: 0.55 | S9: 0.32
A10: A | B10: Atmosphera | C10: 184924 | D10: Muebles deco | E10: Muebles deco | F10: Rack Tv 2 puertas Colva | G10: Rack Tv 2 puertas Colva | H10: 126000 | I10: 0.33 | J10: 62229 | K10: 349990 | L10: 319990 | M10: 205876 | N10: 188229 | O10: 0.3 | P10: 0.3 | Q10: Mix MLL | R10: 0.53 | S10: 0.3
A11: A | B11: Atmosphera | C11: 179010 | D11: Muebles deco | E11: Muebles deco | F11: Respaldo Aoni Ratan 160 cm x 140 cm | G11: Respaldo Aoni Ratan 160 cm x 140 cm | H11: 103950 | I11: 0.35 | J11: 54868 | K11: 299990 | L11: 269990 | M11: 176465 | N11: 158818 | O11: 0.3 | P11: 0.3 | Q11: Mix MLL | R11: 0.54 | S11: 0.31
A12: A | B12: Atmosphera | C12: 192954 | D12: Muebles deco | E12: Muebles deco | F12: Respaldo Ronnie Ratan 160 cm x 100 cm | G12: Respaldo Ronnie Ratan 160 cm x 100 cm | H12: 103950 | I12: 0.35 | J12: 54868 | K12: 299990 | L12: 269990 | M12: 176465 | N12: 158818 | O12: 0.3 | P12: 0.3 | Q12: Mix MLL | R12: 0.54 | S12: 0.31
A13: A | B13: Atmosphera | C13: 197700 | D13: Muebles deco | E13: Muebles deco | F13: Velador Yute 1 cajon Rayo | G13: Velador Yute 1 cajon Rayo | H13: 55440 | I13: 0.37 | J13: 32789 | K13: 149990 | L13: 149990 | M13: 88229 | N13: 88229 | O13: 0.3 | P13: 0.3 | Q13: Mix MLL | R13: 0.56 | S13: 0.33
A14: A | B14: Atmosphera | C14: 179012 | D14: Muebles deco | E14: Muebles deco | F14: Velador Ratan 1 cajon Aoni | G14: Velador Ratan 1 cajon Aoni | H14: 63000 | I14: 0.33 | J14: 31112 | K14: 149990 | L14: 159990 | M14: 88229 | N14: 94112 | O14: 0.3 | P14: 0.3 | Q14: Mix MLL | R14: 0.53 | S14: 0.3
A15: A | B15: Atmosphera | C15: 114516A | D15: Muebles deco | E15: Muebles deco | F15: Velador 1 cajon blanco Chrysa | G15: Velador 1 cajon blanco Chrysa | H15: 63000 | I15: 0.33 | J15: 31112 | K15: 149990 | L15: 159990 | M15: 88229 | N15: 94112 | O15: 0.3 | P15: 0.3 | Q15: Mix MLL | R15: 0.53 | S15: 0.3
A16: A | B16: Atmosphera | C16: 197703 | D16: Muebles deco | E16: Muebles deco | F16: Comoda doble 6 cajones Rayo | G16: Comoda doble 6 cajones Rayo | H16: 207900 | I16: 0.29 | J16: 86212 | K16: 699990 | L16: 499990 | M16: 411759 | N16: 294112 | O16: 0.3 | P16: 0.3 | Q16: Mix MLL | R16: 0.51 | S16: 0.28
A17: A | B17: Atmosphera | C17: 179098 | D17: Muebles deco | E17: Muebles deco | F17: Comoda 12 cajones Ajay | G17: Comoda 12 cajones Ajay | H17: 441000 | I17: 0.25 | J17: 147229 | K17: 1299990 | L17: 999990 | M17: 764700 | N17: 588229 | O17: 0.3 | P17: 0.3 | Q17: Mix MLL | R17: 0.48 | S17: 0.25
A18: A | B18: Atmosphera | C18: 123174 | D18: Muebles deco | E18: Muebles deco | F18: Lampara de pie tripode madera negra 145 cm Runo | G18: Lampara de pie tripode madera negra 145 cm Runo | H18: 27796 | I18: 0.32 | J18: 13375 | K18: 99990 | L18: 69990 | M18: 58818 | N18: 41171 | O18: 0.3 | P18: 0.3 | Q18: Mix MLL | R18: 0.53 | S18: 0.3
A19: A | B19: Atmosphera | C19: 190675 | D19: Muebles deco | E19: Muebles deco | F19: Lampara de pie arco bambu natural 173 cm Liby | G19: Lampara de pie arco bambu natural 173 cm Liby | H19: 65986 | I19: 0.34 | J19: 34008 | K19: 199990 | L19: 169990 | M19: 117641 | N19: 99994 | O19: 0.3 | P19: 0.3 | Q19: Mix MLL | R19: 0.54 | S19: 0.31
A20: A | B20: Atmosphera | C20: 182433 | D20: Muebles deco | E20: Muebles deco | F20: Lampra de pie arco metal 180 cm Rahe | G20: Lampra de pie arco metal 180 cm Rahe | H20: 48623 | I20: 0.36 | J20: 27841 | K20: 149990 | L20: 129990 | M20: 88229 | N20: 76465 | O20: 0.3 | P20: 0.3 | Q20: Mix MLL | R20: 0.55 | S20: 0.32
A21: A | B21: Atmosphera | C21: 181024L | D21: Cojines | E21: Cojines | F21: Cojin reciclado etnico 45X45 cm | G21: Cojin reciclado etnico 45X45 cm | H21: 9034 | I21: 0.39 | J21: 5666 | K21: 29990 | L21: 24990 | M21: 17641 | N21: 14700 | O21: 0.3 | P21: 0.3 | Q21: Mix MLL | R21: 0.57 | S21: 0.34
A22: A | B22: Atmosphera | C22: 185268 | D22: Cojines | E22: Cojines | F22: Cojin flecos y lazoi 45X45 cm | G22: Cojin flecos y lazoi 45X45 cm | H22: 9034 | I22: 0.39 | J22: 5666 | K22: 29990 | L22: 24990 | M22: 17641 | N22: 14700 | O22: 0.3 | P22: 0.3 | Q22: Mix MLL | R22: 0.57 | S22: 0.34
A23: A | B23: 5Five | C23: 111539A | D23: Bandejas | E23: Bandejas | F23: Bandeja Rectangular Angular 44X29 cm Bambú 5Five | G23: Bandeja Rectangular Angular 44X29 cm Bambú 5Five | H23: 4613 | I23: 0.4 | J23: 3028 | K23: 14990 | L23: 12990 | M23: 8818 | N23: 7641 | O23: 0.3 | P23: 0.3 | Q23: Mix MLL | R23: 0.58 | S23: 0.35
A24: A | B24: 5Five | C24: 161016 | D24: Espejos | E24: Espejos | F24: Joyero De Bambu Con Espejo 15X15X9 Cm 5Five | G24: Joyero De Bambu Con Espejo 15X15X9 Cm 5Five | H24: 6212 | I24: 0.38 | J24: 3782 | K24: 19990 | L24: 16990 | M24: 11759 | N24: 9994 | O24: 0.3 | P24: 0.3 | Q24: Descontinuado | R24: 0.56 | S24: 0.33
A25: A | B25: 5Five | C25: 160479 | D25: Muebles deco | E25: Muebles deco | F25: Banca Madera Mix Café 105 X 34 X 50 cm 5 Five | G25: Banca Madera Mix Café 105 X 34 X 50 cm 5 Five | H25: 33402 | I25: 0.37 | J25: 19533 | K25: 119990 | L25: 89990 | M25: 70582 | N25: 52935 | O25: 0.3 | P25: 0.3 | Q25: Mix MLL | R25: 0.56 | S25: 0.33
A26: A | B26: 5Five | C26: 134515 | D26: Cafeteras | E26: Cafeteras | F26: Cafetera Italiana acero 6 Tazas Negro 5Five | G26: Cafetera Italiana acero 6 Tazas Negro 5Five | H26: 6186 | I26: 0.34 | J26: 3220 | K26: 19990 | L26: 15990 | M26: 11759 | N26: 9406 | O26: 0.3 | P26: 0.3 | Q26: Descontinuado | R26: 0.54 | S26: 0.31
A27: A | B27: Atmosphera | C27: 172476 | D27: Alfombras | E27: Alfombras | F27: Alfombra Natura De Yute Beige 160X230 cm Atmosphera | G27: Alfombra Natura De Yute Beige 160X230 cm Atmosphera | H27: 62249 | I27: 0.33 | J27: 30098 | K27: 199990 | L27: 156990 | M27: 117641 | N27: 92347 | O27: 0.3 | P27: 0.3 | Q27: Mix MLL | R27: 0.53 | S27: 0.3
A28: A | B28: Atmosphera | C28: 194340 | D28: Alfombras | E28: Alfombras | F28: Alfombra Yute Redonda 160 cm Atmosphera | G28: Alfombra Yute Redonda 160 cm Atmosphera | H28: 32134 | I28: 0.33 | J28: 15507 | K28: 149990 | L28: 80990 | M28: 88229 | N28: 47641 | O28: 0.3 | P28: 0.3 | Q28: Mix MLL | R28: 0.53 | S28: 0.3
A29: A | B29: Atmosphera | C29: 168857D | D29: Alfombras | E29: Alfombras | F29: Alfombra Yute Natural 120X170 cm Atmosphera | G29: Alfombra Yute Natural 120X170 cm Atmosphera | H29: 28756 | I29: 0.33 | J29: 14179 | K29: 89990 | L29: 72990 | M29: 52935 | N29: 42935 | O29: 0.3 | P29: 0.3 | Q29: Mix MLL | R29: 0.53 | S29: 0.3
A30: A | B30: Atmosphera | C30: 168857J | D30: Alfombras | E30: Alfombras | F30: Alfombra Yute Borde Negro 120X170 cm Atmosphera | G30: Alfombra Yute Borde Negro 120X170 cm Atmosphera | H30: 28881 | I30: 0.33 | J30: 14054 | K30: 89990 | L30: 72990 | M30: 52935 | N30: 42935 | O30: 0.3 | P30: 0.3 | Q30: Mix MLL | R30: 0.53 | S30: 0.3
A31: A | B31: Atmosphera | C31: 181000 | D31: Alfombras | E31: Alfombras | F31: Alfombra Yute Redonda 120 cm Atmosphera | G31: Alfombra Yute Redonda 120 cm Atmosphera | H31: 16629 | I31: 0.34 | J31: 8659 | K31: 69990 | L31: 42990 | M31: 41171 | N31: 25288 | O31: 0.3 | P31: 0.3 | Q31: Mix MLL | R31: 0.54 | S31: 0.31
A32: A | B32: Atmosphera | C32: 146295J | D32: Alfombras | E32: Alfombras | F32: Alfombra Yute Redonda Con Borde Negro 120 cm Atmosphera | G32: Alfombra Yute Redonda Con Borde Negro 120 cm Atmosphera | H32: 16631 | I32: 0.34 | J32: 8657 | K32: 69990 | L32: 42990 | M32: 41171 | N32: 25288 | O32: 0.3 | P32: 0.3 | Q32: Mix MLL | R32: 0.54 | S32: 0.31
A33: A | B33: Atmosphera | C33: 157266 | D33: Cajas decorativas | E33: Cajas decorativas | F33: Costurero Oria 30 Cm De Largo Atmosphera | G33: Costurero Oria 30 Cm De Largo Atmosphera | H33: 8512 | I33: 0.34 | J33: 4423 | K33: 24990 | L33: 21990 | M33: 14700 | N33: 12935 | O33: 0.3 | P33: 0.3 | Q33: Mix MLL | R33: 0.54 | S33: 0.31
A34: A | B34: Atmosphera | C34: 178520 | D34: Cojines | E34: Cojines | F34: Cojín Macrame 30X50 cm Atmosphera | G34: Cojín Macrame 30X50 cm Atmosphera | H34: 8024 | I34: 0.35 | J34: 4323 | K34: 22990 | L34: 20990 | M34: 13524 | N34: 12347 | O34: 0.3 | P34: 0.3 | Q34: Mix MLL | R34: 0.55 | S34: 0.32
A35: A | B35: Atmosphera | C35: 172496 | D35: Cojines | E35: Cojines | F35: Cojin Algodón Y Polister Sand Cop 40X40 cm Atmosphera | G35: Cojin Algodón Y Polister Sand Cop 40X40 cm Atmosphera | H35: 6475 | I35: 0.15 | J35: 1166 | K35: 16990 | L35: 12990 | M35: 9994 | N35: 7641 | O35: 0.3 | P35: 0.3 | Q35: Mix MLL | R35: 0.41 | S35: 0.18
A36: A | B36: Atmosphera | C36: 172462N | D36: Cojines | E36: Cojines | F36: Cojin Inca Algodón Y Poliester 40X40 cm Terracota Atmosphera | G36: Cojin Inca Algodón Y Poliester 40X40 cm Terracota Atmosphera | H36: 4353 | I36: 0.43 | J36: 3288 | K36: 16990 | L36: 12990 | M36: 9994 | N36: 7641 | O36: 0.3 | P36: 0.3 | Q36: Mix MLL | R36: 0.6 | S36: 0.37
A37: A | B37: Atmosphera | C37: 179422B | D37: Espejos | E37: Espejos | F37: Espejo Redondo Alice 76 cm Con Borde Metal Dorado Atmosphera | G37: Espejo Redondo Alice 76 cm Con Borde Metal Dorado Atmosphera | H37: 21871 | I37: 0.34 | J37: 11064 | K37: 69990 | L37: 55990 | M37: 41171 | N37: 32935 | O37: 0.3 | P37: 0.3 | Q37: Descontinuado | R37: 0.54 | S37: 0.31
A38: A | B38: Atmosphera | C38: 200200B | D38: Espejos | E38: Espejos | F38: Espejo Redondo Alice 38 cm Borde Metal Dorado Atmosphera | G38: Espejo Redondo Alice 38 cm Borde Metal Dorado Atmosphera | H38: 6118 | I38: 0.35 | J38: 3288 | K38: 19990 | L38: 15990 | M38: 11759 | N38: 9406 | O38: 0.3 | P38: 0.3 | Q38: Descontinuado | R38: 0.54 | S38: 0.31
A39: A | B39: Atmosphera | C39: 116415C | D39: Luces Decorativas | E39: Luces Decorativas | F39: Guirnalda Led 10 Bolas Blanco 165 cm Atmosphera | G39: Guirnalda Led 10 Bolas Blanco 165 cm Atmosphera | H39: 2377 | I39: 0.42 | J39: 1735 | K39: 9990 | L39: 6990 | M39: 5876 | N39: 4112 | O39: 0.3 | P39: 0.3 | Q39: Descontinuado | R39: 0.6 | S39: 0.37
A40: A | B40: Atmosphera | C40: 179073 | D40: Mesas de centro | E40: Mesas de centro | F40: Mesa De Centro Solen 4 Cajones 110 X 60 X 47 cm Atmosphera | G40: Mesa De Centro Solen 4 Cajones 110 X 60 X 47 cm Atmosphera | H40: 92067 | I40: 0.32 | J40: 43809 | K40: 299990 | L40: 230990 | M40: 176465 | N40: 135876 | O40: 0.3 | P40: 0.3 | Q40: Descontinuado | R40: 0.53 | S40: 0.3
A41: A | B41: Atmosphera | C41: 157210 | D41: Mesas de centro | E41: Mesas de centro | F41: Mesa De Centro Damian 4 Cajones 110 X 60 X 45 cm Atmosphera | G41: Mesa De Centro Damian 4 Cajones 110 X 60 X 45 cm Atmosphera | H41: 95941 | I41: 0.32 | J41: 45818 | K41: 299990 | L41: 240990 | M41: 176465 | N41: 141759 | O41: 0.3 | P41: 0.3 | Q41: Descontinuado | R41: 0.53 | S41: 0.3
A42: A | B42: Atmosphera | C42: 102411 | D42: Mesas de centro | E42: Mesas de centro | F42: Mesa De Centro Edena 115 X 65 X 34 cm Atmosphera | G42: Mesa De Centro Edena 115 X 65 X 34 cm Atmosphera | H42: 74697 | I42: 0.32 | J42: 35886 | K42: 229990 | L42: 187990 | M42: 135288 | N42: 110582 | O42: 0.3 | P42: 0.3 | Q42: Mix MLL | R42: 0.53 | S42: 0.3
A43: A | B43: Atmosphera | C43: 179106 | D43: Muebles deco | E43: Muebles deco | F43: Arrimo Madera 2 Cajones Charme 110 X 40 X 85 cm Atmosphera | G43: Arrimo Madera 2 Cajones Charme 110 X 40 X 85 cm Atmosphera | H43: 97898 | I43: 0.32 | J43: 46802 | K43: 329990 | L43: 245990 | M43: 194112 | N43: 144700 | O43: 0.3 | P43: 0.3 | Q43: Mix MLL | R43: 0.53 | S43: 0.3
A44: A | B44: Atmosphera | C44: 179107 | D44: Muebles deco | E44: Muebles deco | F44: Rack Tv Junco Rayo Atmosphera | G44: Rack Tv Junco Rayo Atmosphera | H44: 125819 | I44: 0.32 | J44: 60057 | K44: 349990 | L44: 315990 | M44: 205876 | N44: 185876 | O44: 0.3 | P44: 0.3 | Q44: Mix MLL | R44: 0.53 | S44: 0.3
A45: A | B45: Atmosphera | C45: 157209 | D45: Muebles deco | E45: Muebles deco | F45: Arrimo Damian 110 X 40 X 85 cm Atmosphera | G45: Arrimo Damian 110 X 40 X 85 cm Atmosphera | H45: 79993 | I45: 0.32 | J45: 38236 | K45: 249990 | L45: 200990 | M45: 147053 | N45: 118229 | O45: 0.3 | P45: 0.3 | Q45: Descontinuado | R45: 0.53 | S45: 0.3
A46: A | B46: Atmosphera | C46: 157098 | D46: Muebles deco | E46: Muebles deco | F46: Escalera Deco Dream Bambu Atmosphera | G46: Escalera Deco Dream Bambu Atmosphera | H46: 10651 | I46: 0.35 | J46: 5814 | K46: 29990 | L46: 27990 | M46: 17641 | N46: 16465 | O46: 0.3 | P46: 0.3 | Q46: Mix MLL | R46: 0.55 | S46: 0.32
A47: A | B47: Atmosphera | C47: 140101 | D47: Muebles deco | E47: Muebles deco | F47: Taburete De Madera Woody Natural Atmosphera | G47: Taburete De Madera Woody Natural Atmosphera | H47: 10110 | I47: 0.34 | J47: 5178 | K47: 29990 | L47: 25990 | M47: 17641 | N47: 15288 | O47: 0.3 | P47: 0.3 | Q47: Mix MLL | R47: 0.54 | S47: 0.31
A48: A | B48: Atmosphera | C48: 138868 | D48: Organizadores zapato | E48: Organizadores zapato | F48: Zapatero de Acero 64x50x18 Cm Atmosphera Negro | G48: Zapatero de Acero 64x50x18 Cm Atmosphera Negro | H48: 3284 | I48: 0.38 | J48: 2004 | K48: 12990 | L48: 8990 | M48: 7641 | N48: 5288 | O48: 0.3 | P48: 0.3 | Q48: Mix MLL | R48: 0.57 | S48: 0.34
A49: A | B49: Berghoff | C49: 3950087 | D49: Tablas | E49: Tablas | F49: Tabla Bambú Leo Ranurada BERGHOFF | G49: Tabla Bambú Leo Ranurada BERGHOFF | H49: 4083 | I49: 0.37 | J49: 2382 | K49: 19990 | L49: 10990 | M49: 11759 | N49: 6465 | O49: 0.3 | P49: 0.3 | Q49: Descontinuado | R49: 0.56 | S49: 0.33
A50: A | B50: Berghoff | C50: 3950032 | D50: Utensilios de cocina | E50: Utensilios de cocina | F50: Mortero Blanco Con Tapa BERGHOFF | G50: Mortero Blanco Con Tapa BERGHOFF | H50: 7500 | I50: 0.36 | J50: 4259 | K50: 29990 | L50: 19990 | M50: 17641 | N50: 11759 | O50: 0.3 | P50: 0.3 | Q50: Descontinuado | R50: 0.55 | S50: 0.32
A51: A | B51: DAY | C51: 71874 | D51: Cajas decorativas | E51: Cajas decorativas | F51: Canasto Organizador Junco 34X24X17 cm DAY | G51: Canasto Organizador Junco 34X24X17 cm DAY | H51: 4532 | I51: 0.36 | J51: 2521 | K51: 17990 | L51: 11990 | M51: 10582 | N51: 7053 | O51: 0.3 | P51: 0.3 | Q51: Descontinuado | R51: 0.55 | S51: 0.32
... A81: A | B81: SecretDeGourmet | C81: 188455 | D81: Tablas | E81: Tablas | F81: Set Tabla + 3 Posillos Aperitivo Colores SecretDeGourmet | G81: Set Tabla + 3 Posillos Aperitivo Colores SecretDeGourmet | H81: 4531 | I81: 0.36 | J81: 2522 | K81: 14990 | L81: 11990 | M81: 8818 | N81: 7053 | O81: 0.3 | P81: 0.3 | Q81: Descontinuado | R81: 0.55 | S81: 0.32
A82: A | B82: Atmosphera | C82: 194306B | D82: Tablas | E82: Tablas | F82: Alfombra Living Rug Out+in Gris 120xX170 CM Atmosphera | G82: Alfombra Living Rug Out+in Gris 120xX170 CM Atmosphera | H82: 16579 | I82: 0.33 | J82: 8121 | K82: 59990 | L82: 41990 | M82: 35288 | N82: 24700 | O82: 0.3 | P82: 0.3 | Q82: Descontinuado | R82: 0.53 | S82: 0.3
A83: A | B83: Atmosphera | C83: 172462R | D83: Tablas | E83: Tablas | F83: Cojin Inca Algodon Y Poliester 40x40 Ocre Atmosphera | G83: Cojin Inca Algodon Y Poliester 40x40 Ocre Atmosphera | H83: 4353 | I83: 0.43 | J83: 3288 | K83: 16990 | L83: 12990 | M83: 9994 | N83: 7641 | O83: 0.3 | P83: 0.3 | Q83: Descontinuado | R83: 0.6 | S83: 0.37
A84: A | B84: 5Five | C84: 189717 | D84: Tablas | E84: Tablas | F84: Bandeja redonda kord 40 cm mimbre 5Five | G84: Bandeja redonda kord 40 cm mimbre 5Five | H84: 6507 | I84: 0.35 | J84: 3487 | K84: 19990 | L84: 16990 | M84: 11759 | N84: 9994 | O84: 0.3 | P84: 0.3 | Q84: Mix MLL | R84: 0.54 | S84: 0.31
A85: A | B85: Atmosphera | C85: 156173D | D85: Tablas | E85: Tablas | F85: Funda Cojin Etnik 40x40 cm Atmosphera | G85: Funda Cojin Etnik 40x40 cm Atmosphera | H85: 3513 | I85: 0.54 | J85: 4128 | K85: 16990 | L85: 12990 | M85: 9994 | N85: 7641 | O85: 0.3 | P85: 0.3 | Q85: Mix MLL | R85: 0.68 | S85: 0.45
A86: A | B86: Secret de Gourmet | C86: 188914 | D86: Tablas | E86: Tablas | F86: Soporte Madera Con 6 Vasos De Chupito Secret de Gourmet | G86: Soporte Madera Con 6 Vasos De Chupito Secret de Gourmet | H86: 9394 | I86: 0.33 | J86: 4718 | K86: 21990 | L86: 23990 | M86: 12935 | N86: 14112 | O86: 0.3 | P86: 0.3 | Q86: Descontinuado | R86: 0.53 | S86: 0.3
A87: A | B87: Secret de Gourmet | C87: 188890A | D87: Tablas | E87: Tablas | F87: Set 4 Posa Vasos Mármol 10 cm Blanco Secret de Gourmet | G87: Set 4 Posa Vasos Mármol 10 cm Blanco Secret de Gourmet | H87: 3287 | I87: 0.44 | J87: 2590 | K87: 14990 | L87: 9990 | M87: 8818 | N87: 5876 | O87: 0.3 | P87: 0.3 | Q87: Descontinuado | R87: 0.61 | S87: 0.38
A88: A | B88: Atmosphera | C88: 178603 | D88: Tablas | E88: Tablas | F88: Cojin Sequin 30x50 Cm Marfl Atmosphera | G88: Cojin Sequin 30x50 Cm Marfl Atmosphera | H88: 6711 | I88: 0.37 | J88: 3871 | K88: 22990 | L88: 17990 | M88: 13524 | N88: 10582 | O88: 0.3 | P88: 0.3 | Q88: Descontinuado | R88: 0.56 | S88: 0.33
A89: A | B89: 5Five | C89: 189646 | D89: Tablas | E89: Tablas | F89: Mueble Bar con soporte para 25 botellas Aliaj 5Five | G89: Mueble Bar con soporte para 25 botellas Aliaj 5Five | H89: 55853 | I89: 0.33 | J89: 27082 | K89: 149990 | L89: 140990 | M89: 88229 | N89: 82935 | O89: 0.3 | P89: 0.3 | Q89: Mix MLL | R89: 0.53 | S89: 0.3
A90: A | B90: Atmosphera | C90: 158229 | D90: Tablas | E90: Tablas | F90: Espejo Redondo Jane 76 Cm Con Borde Palillos Ratan Atmosphera | G90: Espejo Redondo Jane 76 Cm Con Borde Palillos Ratan Atmosphera | H90: 13154 | I90: 0.34 | J90: 6840 | K90: 49990 | L90: 33990 | M90: 29406 | N90: 19994 | O90: 0.3 | P90: 0.3 | Q90: Descontinuado | R90: 0.54 | S90: 0.31
A91: A | B91: Day | C91: 731176 | D91: Tablas | E91: Tablas | F91: Mesa 30X70Cm Metal Mdf Day | G91: Mesa 30X70Cm Metal Mdf Day | H91: 12852 | I91: 0.38 | J91: 7730 | K91: 49990 | L91: 34990 | M91: 29406 | N91: 20582 | O91: 0.3 | P91: 0.3 | Q91: Descontinuado | R91: 0.56 | S91: 0.33
A92: A | B92: Day | C92: 731192 | D92: Tablas | E92: Tablas | F92: Mesa 40X50Cm Metal Mdf Negro Day | G92: Mesa 40X50Cm Metal Mdf Negro Day | H92: 12559 | I92: 0.47 | J92: 10965 | K92: 49990 | L92: 39990 | M92: 29406 | N92: 23524 | O92: 0.3 | P92: 0.3 | Q92: Descontinuado | R92: 0.63 | S92: 0.4
A93: A | B93: 5Five | C93: 162085 | D93: Tablas | E93: Tablas | F93: Bandeja redonda de 35 cm Jacynte mimbre 5Five | G93: Bandeja redonda de 35 cm Jacynte mimbre 5Five | H93: 4376 | I93: 0.38 | J93: 2677 | K93: 14990 | L93: 11990 | M93: 8818 | N93: 7053 | O93: 0.3 | P93: 0.3 | Q93: Mix MLL | R93: 0.57 | S93: 0.34
A94: A | B94: Secret de Gourmet | C94: 160726 | D94: Tablas | E94: Tablas | F94: Set de 6 Posasvasos Madera Bambú Secret de Gourmet | G94: Set de 6 Posasvasos Madera Bambú Secret de Gourmet | H94: 3610 | I94: 0.39 | J94: 2266 | K94: 12990 | L94: 9990 | M94: 7641 | N94: 5876 | O94: 0.3 | P94: 0.3 | Q94: Descontinuado | R94: 0.57 | S94: 0.34
A95: A | B95: Day | C95: 72657 | D95: Tablas | E95: Tablas | F95: Perchero de Pared 5 Ganchos Negro Day | G95: Perchero de Pared 5 Ganchos Negro Day | H95: 3466 | I95: 0.41 | J95: 2410 | K95: 12990 | L95: 9990 | M95: 7641 | N95: 5876 | O95: 0.3 | P95: 0.3 | Q95: Descontinuado | R95: 0.59 | S95: 0.36
A96: A | B96: 5Five | C96: 185017 | D96: Tablas | E96: Tablas | F96: Escritorio Cierna 120x53x77 Cm 5Five | G96: Escritorio Cierna 120x53x77 Cm 5Five | H96: 89296 | I96: 0.32 | J96: 42463 | K96: 299990 | L96: 223990 | M96: 176465 | N96: 131759 | O96: 0.3 | P96: 0.3 | Q96: Descontinuado | R96: 0.53 | S96: 0.3
A97: A | B97: Atmosphera | C97: 156147 | D97: Tablas | E97: Tablas | F97: Alfombra Yute Calada Redonda 120 cm Atmosphera | G97: Alfombra Yute Calada Redonda 120 cm Atmosphera | H97: 16742 | I97: 0.34 | J97: 8546 | K97: 69990 | L97: 42990 | M97: 41171 | N97: 25288 | O97: 0.3 | P97: 0.3 | Q97: Mix MLL | R97: 0.54 | S97: 0.31
A98: A | B98: Atmosphera | C98: 157101 | D98: Tablas | E98: Tablas | F98: Set de 4 Canastos Yute Emmet Atmosphera | G98: Set de 4 Canastos Yute Emmet Atmosphera | H98: 15648 | I98: 0.33 | J98: 7876 | K98: 49990 | L98: 39990 | M98: 29406 | N98: 23524 | O98: 0.3 | P98: 0.3 | Q98: Mix MLL | R98: 0.53 | S98: 0.3
A99: A | B99: Atmosphera | C99: 162315A | D99: Tablas | E99: Tablas | F99: Espejo Joe Diametro 45 Cm Metal y MDF Atmosphera | G99: Espejo Joe Diametro 45 Cm Metal y MDF Atmosphera | H99: 6573 | I99: 0.34 | J99: 3421 | K99: 24990 | L99: 16990 | M99: 14700 | N99: 9994 | O99: 0.3 | P99: 0.3 | Q99: Descontinuado | R99: 0.54 | S99: 0.31
A100: A | B100: 5Five | C100: 189720 | D100: Tablas | E100: Tablas | F100: Bandeja cuadrada Kord 35cm beige mimbre 5Five | G100: Bandeja cuadrada Kord 35cm beige mimbre 5Five | H100: 5170 | I100: 0.37 | J100: 3059 | K100: 19990 | L100: 13990 | M100: 11759 | N100: 8229 | O100: 0.3 | P100: 0.3 | Q100: Descontinuado | R100: 0.56 | S100: 0.33
A101: A | B101: Day | C101: 49452 | D101: Tablas | E101: Tablas | F101: Lámpara Exterior 20x24cm Negra a Pilas Day | G101: Lámpara Exterior 20x24cm Negra a Pilas Day | H101: 5804 | I101: 0.38 | J101: 3602 | K101: 19990 | L101: 15990 | M101: 11759 | N101: 9406 | O101: 0.3 | P101: 0.3 | Q101: Descontinuado | R101: 0.57 | S101: 0.34
A102: A | B102: Day | C102: 72491 | D102: Tablas | E102: Tablas | F102: Canasto Yute Natural 38x34 cm Day | G102: Canasto Yute Natural 38x34 cm Day | H102: 6500 | I102: 0.35 | J102: 3494 | K102: 29990 | L102: 16990 | M102: 17641 | N102: 9994 | O102: 0.3 | P102: 0.3 | Q102: Descontinuado | R102: 0.54 | S102: 0.31
A103: A | B103: Atmosphera | C103: 141149 | D103: Tablas | E103: Tablas | F103: Espejo Redondo Jane 58 Cm Con Borde Palillos Ratan Atmosphera | G103: Espejo Redondo Jane 58 Cm Con Borde Palillos Ratan Atmosphera | H103: 9458 | I103: 0.36 | J103: 5242 | K103: 29990 | L103: 24990 | M103: 17641 | N103: 14700 | O103: 0.3 | P103: 0.3 | Q103: Descontinuado | R103: 0.55 | S103: 0.32
A104: A | B104: DAY | C104: 83318 | D104: Menaje Mesa | E104: Menaje Mesa | F104: SET ENSALADA ACERO INOXIDABLE NEGRO | G104: SET ENSALADA ACERO INOXIDABLE NEGRO | H104: 2710 | I104: 0.42 | J104: 1990 | K104: 12990 | L104: 7990 | M104: 7641 | N104: 4700 | O104: 0.3 | P104: 0.3 | Q104: Descontinuado | R104: 0.6 | S104: 0.37
A105: A | B105: Secret de Gourmet | C105: 108051 | D105: Menaje Mesa | E105: Menaje Mesa | F105: SOPORTE PARA TORTAS GIRATORIO VIDRIO | G105: SOPORTE PARA TORTAS GIRATORIO VIDRIO | H105: 4215 | I105: 0.4 | J105: 2838 | K105: 14990 | L105: 11990 | M105: 8818 | N105: 7053 | O105: 0.3 | P105: 0.3 | Q105: Descontinuado | R105: 0.58 | S105: 0.35
A106: A | B106: 5Five | C106: 188452 | D106: Menaje Mesa | E106: Menaje Mesa | F106: SOPORTE PARA POSTRES 2 NIVELES BAMBU 25 CM | G106: SOPORTE PARA POSTRES 2 NIVELES BAMBU 25 CM | H106: 5401 | I106: 0.39 | J106: 3417 | K106: 19990 | L106: 14990 | M106: 11759 | N106: 8818 | O106: 0.3 | P106: 0.3 | Q106: Descontinuado | R106: 0.57 | S106: 0.34
A107: A | B107: DAY | C107: 86386 | D107: Menaje Cocina | E107: Menaje Cocina | F107: SOPORTE CHOCLO 8PCS. NEGRO | G107: SOPORTE CHOCLO 8PCS. NEGRO | H107: 999 | I107: 0.43 | J107: 760 | K107: 4990 | L107: 2990 | M107: 2935 | N107: 1759 | O107: 0.3 | P107: 0.3 | Q107: Descontinuado | R107: 0.6 | S107: 0.37
A108: A | B108: DAY | C108: 77898 | D108: Menaje Cocina | E108: Menaje Cocina | F108: TABLA DE CORTAR BAMBU CON ANILLO DE SILICONA 28 X 20 CM | G108: TABLA DE CORTAR BAMBU CON ANILLO DE SILICONA 28 X 20 CM | H108: 1630 | I108: 0.44 | J108: 1305 | K108: 5990 | L108: 4990 | M108: 3524 | N108: 2935 | O108: 0.3 | P108: 0.3 | Q108: Descontinuado | R108: 0.61 | S108: 0.38
A109: A | B109: 5Five | C109: 179742 | D109: Menaje Cocina | E109: Menaje Cocina | F109: EXPRIMIDOR RALLADOR 4 EN 1 | G109: EXPRIMIDOR RALLADOR 4 EN 1 | H109: 2609 | I109: 0.44 | J109: 2091 | K109: 12990 | L109: 7990 | M109: 7641 | N109: 4700 | O109: 0.3 | P109: 0.3 | Q109: Descontinuado | R109: 0.61 | S109: 0.38
A110: A | B110: DAY | C110: 74919 | D110: Menaje Cocina | E110: Menaje Cocina | F110: SET DE TIJERAS NEGRAS 3 PIEZAS | G110: SET DE TIJERAS NEGRAS 3 PIEZAS | H110: 1335 | I110: 0.43 | J110: 1012 | K110: 9990 | L110: 3990 | M110: 5876 | N110: 2347 | O110: 0.3 | P110: 0.3 | Q110: Descontinuado | R110: 0.6 | S110: 0.37
A111: A | B111: 5Five | C111: 119666 | D111: Menaje Cocina | E111: Menaje Cocina | F111: ABRELATA SILVER PRECISION DE ACERO INOX | G111: ABRELATA SILVER PRECISION DE ACERO INOX | H111: 3948 | I111: 0.39 | J111: 2517 | K111: 14990 | L111: 10990 | M111: 8818 | N111: 6465 | O111: 0.3 | P111: 0.3 | Q111: Descontinuado | R111: 0.57 | S111: 0.34
... A136: A | B136: Secret de Gourmet | C136: 134993 | D136: Te y Café | E136: Te y Café | F136: SET 3 TAZAS CAFÉ VIDRIO Y METAL 110 CC | G136: SET 3 TAZAS CAFÉ VIDRIO Y METAL 110 CC | H136: 1662 | I136: 0.43 | J136: 1273 | K136: 7990 | L136: 4990 | M136: 4700 | N136: 2935 | O136: 0.3 | P136: 0.3 | Q136: Descontinuado | R136: 0.6 | S136: 0.37
A137: A | B137: Urban Products | C137: FW1008 | D137: Funcionales | E137: Funcionales | F137: LIMPIAPIES PVC NATURAL CON DISEÑO MAT 40 X 75 CM | G137: LIMPIAPIES PVC NATURAL CON DISEÑO MAT 40 X 75 CM | H137: 3555 | I137: 0.4 | J137: 2321 | K137: 14990 | L137: 9990 | M137: 8818 | N137: 5876 | O137: 0.3 | P137: 0.3 | Q137: Descontinuado | R137: 0.58 | S137: 0.35
A138: A | B138: 5Five | C138: 120040 | D138: Menaje Cocina | E138: Menaje Cocina | F138: BANDEJA ANTIDESLIZANTE GRIS 45 X 32 CM | G138: BANDEJA ANTIDESLIZANTE GRIS 45 X 32 CM | H138: 2370 | I138: 0.42 | J138: 1742 | K138: 9990 | L138: 6990 | M138: 5876 | N138: 4112 | O138: 0.3 | P138: 0.3 | Q138: Descontinuado | R138: 0.6 | S138: 0.37
A139: A | B139: 5Five | C139: 189702 | D139: Menaje Mesa | E139: Menaje Mesa | F139: PANERA CUADRADA METAL Y LONA 25X25X10 CM | G139: PANERA CUADRADA METAL Y LONA 25X25X10 CM | H139: 3983 | I139: 0.38 | J139: 2482 | K139: 19990 | L139: 10990 | M139: 11759 | N139: 6465 | O139: 0.3 | P139: 0.3 | Q139: Descontinuado | R139: 0.57 | S139: 0.34
A140: A | B140: Secret de Gourmet | C140: 188453 | D140: Bar y Cocktail | E140: Bar y Cocktail | F140: SET 6 POSAVASOS DE PIEDRA PIZARRA CON SOPORTE DE BAMBU 10 CM | G140: SET 6 POSAVASOS DE PIEDRA PIZARRA CON SOPORTE DE BAMBU 10 CM | H140: 2681 | I140: 0.43 | J140: 2019 | K140: 9990 | L140: 7990 | M140: 5876 | N140: 4700 | O140: 0.3 | P140: 0.3 | Q140: Descontinuado | R140: 0.6 | S140: 0.37
A141: A | B141: DANGRILL | C141: 86389 | D141: Parrilla | E141: Parrilla | F141: JERINGA MARINADORA | G141: JERINGA MARINADORA | H141: 2000 | I141: 0.43 | J141: 1524 | K141: 9990 | L141: 5990 | M141: 5876 | N141: 3524 | O141: 0.3 | P141: 0.3 | Q141: Descontinuado | R141: 0.6 | S141: 0.37
A142: A | B142: DAY | C142: 75571 | D142: Menaje Cocina | E142: Menaje Cocina | F142: MORTERO MARMOL NEGRO 13 CM | G142: MORTERO MARMOL NEGRO 13 CM | H142: 4541 | I142: 0.36 | J142: 2512 | K142: 19990 | L142: 11990 | M142: 11759 | N142: 7053 | O142: 0.3 | P142: 0.3 | Q142: Descontinuado | R142: 0.55 | S142: 0.32
A143: A | B143: DAY | C143: 73732 | D143: Muebles | E143: Muebles | F143: MESA METAL NEGRO D. 38 X 50 CM | G143: MESA METAL NEGRO D. 38 X 50 CM | H143: 8530 | I143: 0.34 | J143: 4405 | K143: 34990 | L143: 21990 | M143: 20582 | N143: 12935 | O143: 0.3 | P143: 0.3 | Q143: Descontinuado | R143: 0.54 | S143: 0.31
A144: A | B144: Atmosphera | C144: 158120 | D144: Decoración | E144: Decoración | F144: RELOJ ALEX D. 38 CM MIX 4 MODELOS SURTIDO | G144: RELOJ ALEX D. 38 CM MIX 4 MODELOS SURTIDO | H144: 4602 | I144: 0.4 | J144: 3039 | K144: 14990 | L144: 12990 | M144: 8818 | N144: 7641 | O144: 0.3 | P144: 0.3 | Q144: Descontinuado | R144: 0.58 | S144: 0.35
A145: A | B145: Grouw | C145: 21222 | D145: Jardin | E145: Jardin | F145: ASPERSOR DE IMPULSOS / ROCIADOR | G145: ASPERSOR DE IMPULSOS / ROCIADOR | H145: 2294 | I145: 0.44 | J145: 1818 | K145: 9990 | L145: 6990 | M145: 5876 | N145: 4112 | O145: 0.3 | P145: 0.3 | Q145: Descontinuado | R145: 0.61 | S145: 0.38
A146: A | B146: DANGRILL | C146: 86644 | D146: Parrilla | E146: Parrilla | F146: PRENSA DE HAMBURGUESA PLASTICO | G146: PRENSA DE HAMBURGUESA PLASTICO | H146: 2830 | I146: 0.4 | J146: 1870 | K146: 12990 | L146: 7990 | M146: 7641 | N146: 4700 | O146: 0.3 | P146: 0.3 | Q146: Descontinuado | R146: 0.58 | S146: 0.35
A147: A | B147: DAY | C147: 75298 | D147: Bar y Cocktail | E147: Bar y Cocktail | F147: COCTELERA VIDRIO 400CC | G147: COCTELERA VIDRIO 400CC | H147: 3345 | I147: 0.37 | J147: 1943 | K147: 12990 | L147: 8990 | M147: 7641 | N147: 5288 | O147: 0.3 | P147: 0.3 | Q147: Descontinuado | R147: 0.56 | S147: 0.33
A148: A | B148: 5Five | C148: 154748003 | D148: Menaje Cocina | E148: Menaje Cocina | F148: SECADOR DE VERDURAS SPINNER | G148: SECADOR DE VERDURAS SPINNER | H148: 6068 | I148: 0.35 | J148: 3338 | K148: 29990 | L148: 15990 | M148: 17641 | N148: 9406 | O148: 0.3 | P148: 0.3 | Q148: Descontinuado | R148: 0.55 | S148: 0.32
A149: A | B149: Grouw | C149: 97554 | D149: Jardin | E149: Jardin | F149: DESMALEZADOR ACERO INOXIDABLE Y MANGO INTIDESLIZANTE 33 X 3 X 4 CM | G149: DESMALEZADOR ACERO INOXIDABLE Y MANGO INTIDESLIZANTE 33 X 3 X 4 CM | H149: 1872 | I149: 0.47 | J149: 1652 | K149: 9990 | L149: 5990 | M149: 5876 | N149: 3524 | O149: 0.3 | P149: 0.3 | Q149: Descontinuado | R149: 0.63 | S149: 0.4
... A155: A | B155: Secret de Gourmet | C155: 160519 | D155: Te y Café | E155: Te y Café | F155: TETERA CON FILTRO PARA TE DE ACERO INOXIDABLE CON BOQUILLA 800 CC | G155: TETERA CON FILTRO PARA TE DE ACERO INOXIDABLE CON BOQUILLA 800 CC | H155: 4901 | I155: 0.36 | J155: 2740 | K155: 19990 | L155: 12990 | M155: 11759 | N155: 7641 | O155: 0.3 | P155: 0.3 | Q155: Descontinuado | R155: 0.55 | S155: 0.32
A156: A | B156: Atmosphera | C156: 155686C | D156: Decoración | E156: Decoración | F156: JARRON AZUL 35 CM VIDRIO RECICLADO | G156: JARRON AZUL 35 CM VIDRIO RECICLADO | H156: 8690 | I156: 0.36 | J156: 4834 | K156: 29990 | L156: 22990 | M156: 17641 | N156: 13524 | O156: 0.3 | P156: 0.3 | Q156: Descontinuado | R156: 0.55 | S156: 0.32
A157: A | B157: 5Five | C157: 150166 | D157: Menaje Cocina | E157: Menaje Cocina | F157: SET ALCUZA 4 PIEZAS | G157: SET ALCUZA 4 PIEZAS | H157: 3594 | I157: 0.39 | J157: 2282 | K157: 14990 | L157: 9990 | M157: 8818 | N157: 5876 | O157: 0.3 | P157: 0.3 | Q157: Descontinuado | R157: 0.57 | S157: 0.34
A158: A | B158: Atmosphera | C158: 155686F | D158: Decoración | E158: Decoración | F158: JARRON VERDE 35 CM VIDRIO RECICLADO | G158: JARRON VERDE 35 CM VIDRIO RECICLADO | H158: 8690 | I158: 0.36 | J158: 4834 | K158: 29990 | L158: 22990 | M158: 17641 | N158: 13524 | O158: 0.3 | P158: 0.3 | Q158: Descontinuado | R158: 0.55 | S158: 0.32
A159: A | B159: Berghoff | C159: 1100033 | D159: Menaje Cocina | E159: Menaje Cocina | F159: AFILADOR CUCHILLOS 3 EN 1 | G159: AFILADOR CUCHILLOS 3 EN 1 | H159: 7300 | I159: 0.35 | J159: 3871 | K159: 29990 | L159: 18990 | M159: 17641 | N159: 11171 | O159: 0.3 | P159: 0.3 | Q159: Descontinuado | R159: 0.54 | S159: 0.31
...

Sheet Productos y Categorizacion
A1: Marca | B1: SKU | C1: Producto | D1: Categoría macro | E1: Categoría padre | F1: Categoría hijo | G1: Categoría comercial | H1: In/out | I1: Pack | J1: Estado marca | K1: Proveedor
A2: 5 Surprise | B2: 32935 | C2: Bola 5 Sorpresas Serie My Mini Baby | D2: Kids | E2: Figuras y muñecos | F2: Figuras y muñecos | G2: Nuevo | H2: out | I2: No | J2: Out | K2: Ansaldo
A3: 5Five | B3: 120200A | C3: Mug De Café 350 Cc Gris - Acero Inoxidable | D3: Home | E3: Mundo Café | F3: Termos líquidos | G3: Nuevo | H3: out | I3: No | J3: In | K3: Urban
A4: 5Five | B4: 120200B | C4: Mug De Cafe Negro Acero Inoxidable 350 Cc | D4: Home | E4: Mundo Café | F4: Termos líquidos | G4: Nuevo | H4: out | I4: No | J4: In | K4: Urban
A5: 5Five | B5: 174713 | C5: Pulverizador Vidrio 450 Cc Color Ambar | D5: Home | E5: Deco | F5: Utensilios de aseo | G5: Nuevo | H5: out | I5: No | J5: In | K5: Urban
A6: 5Five | B6: 179742 | C6: Exprimidor rallado en 4 en 1 5Five | D6: Home | E6: Cristalería y Bar | F6: Bar | G6: Nuevo | H6: out | I6: No | J6: In | K6: Urban
A7: 5Five | B7: 120040 | C7: Bandeja Antideslizante Gris 45X32 Cm 5Five | D7: Kids | E7: Deco | F7: Bandejas | G7: Nuevo | H7: out | I7: No | J7: In | K7: Urban
A8: 5Five | B8: 189720 | C8: Bandeja cuadrada Kord 35cm beige mimbre | D8: Home | E8: Deco | F8: Bandejas | G8: Nuevo | H8: out | I8: No | J8: In | K8: Urban
A9: 5Five | B9: 169228 | C9: Bandeja De Metal Mayaj | D9: Home | E9: Deco | F9: Bandejas | G9: Nuevo | H9: out | I9: No | J9: In | K9: Urban
A10: 5Five | B10: 111539A | C10: Bandeja Rectangular Angular 44X29 cm Bambú | D10: Home | E10: Deco | F10: Bandejas | G10: Nuevo | H10: in | I10: No | J10: In | K10: Urban
A11: 5Five | B11: 162085 | C11: Bandeja redonda de 35 cm Jacynte mimbre | D11: Home | E11: Deco | F11: Bandejas | G11: Nuevo | H11: in | I11: No | J11: In | K11: Urban
A12: 5Five | B12: 189717 | C12: Bandeja redonda kord 40 cm mimbre | D12: Home | E12: Deco | F12: Bandejas | G12: Nuevo | H12: in | I12: No | J12: In | K12: Urban
A13: 5Five | B13: 161016 | C13: Joyero De Bambu Con Espejo 15X15X9 Cm | D13: Home | E13: Deco | F13: Joyeros | G13: Nuevo | H13: out | I13: No | J13: In | K13: Urban
A14: 5Five | B14: 189699 | C14: Set De 2 Tablas De Cortas Bambu 5Five | D14: Home | E14: Deco | F14: Tablas | G14: Nuevo | H14: out | I14: No | J14: In | K14: Urban
A15: 5Five | B15: 540724263 | C15: Set De 3 Tablas De Cortar De Bambu Secret de Gourmet | D15: Home | E15: Deco | F15: Tablas | G15: Nuevo | H15: out | I15: No | J15: In | K15: Urban
A16: 5Five | B16: 154350 | C16: Botella Vidrio Con Diseños Y Tapa Acero Inox 500 Ml | D16: Home | E16: Hidratación | F16: Botellas de Agua | G16: Nuevo | H16: out | I16: No | J16: In | K16: Urban
A17: 5Five | B17: 146604 | C17: Cuchillo Carnicero Acero Inox Y Mango Acacia 24 Cm | D17: Home | E17: Menaje de Cocina | F17: Cuchilleria | G17: Nuevo | H17: out | I17: No | J17: In | K17: Urban
A18: 5Five | B18: 146607 | C18: Cuchillo Chef Acero Inox Con Mango Acacia 35 Cm | D18: Home | E18: Menaje de Cocina | F18: Cuchilleria | G18: Nuevo | H18: out | I18: No | J18: In | K18: Urban
A19: 5Five | B19: 120307 | C19: Cuchillo Cocina Chef 33 Cm | D19: Home | E19: Menaje de Cocina | F19: Cuchilleria | G19: Nuevo | H19: out | I19: No | J19: In | K19: Urban
A20: 5Five | B20: 120306 | C20: Cuchillo Cocina Santoku 25 Cm | D20: Home | E20: Menaje de Cocina | F20: Cuchilleria | G20: Nuevo | H20: out | I20: No | J20: In | K20: Urban
A21: 5Five | B21: 151268 | C21: Set De Cuchillos Marmol | D21: Home | E21: Menaje de Cocina | F21: Cuchilleria | G21: Nuevo | H21: out | I21: No | J21: In | K21: Urban
A22: 5Five | B22: 151170 | C22: Taco De 11 Cuchillos Con Afilador Y Tijera Cocina | D22: Home | E22: Menaje de Cocina | F22: Cuchilleria | G22: Nuevo | H22: out | I22: No | J22: In | K22: Urban
... A35: 5Five | B35: 146589 | C35: Set De Utensilios De Cocina Nylon 4 Piezas | D35: Home | E35: Menaje de Cocina | F35: Utensilios de cocina | G35: Nuevo | H35: out | I35: No | J35: In | K35: Urban
A36: 5Five | B36: 100145A | C36: Soplete Cocina a Gas | D36: Home | E36: Menaje de Cocina | F36: Utensilios de cocina | G36: Nuevo | H36: out | I36: No | J36: In | K36: Urban
A37: 5Five | B37: 103700 | C37: Toma Olla De Silicona | D37: Home | E37: Menaje de Cocina | F37: Utensilios de cocina | G37: Nuevo | H37: out | I37: No | J37: In | K37: Urban
A38: 5Five | B38: 119695 | C38: Triturador De Papas Acero Inox 26 X 8 X 8 Cm | D38: Home | E38: Menaje de Cocina | F38: Utensilios de cocina | G38: Nuevo | H38: out | I38: No | J38: In | K38: Urban
A39: 5Five | B39: 124599 | C39: Mat Silicona Repostería 38 X 28 Cc | D39: Home | E39: Menaje de Cocina | F39: Utensilios repostería | G39: Nuevo | H39: out | I39: No | J39: In | K39: Urban
A40: 5Five | B40: 151190 | C40: Set 10 Cortadores/Moldes De Galletas | D40: Home | E40: Menaje de Cocina | F40: Utensilios repostería | G40: Nuevo | H40: out | I40: No | J40: In | K40: Urban
A41: 5Five | B41: 124576 | C41: Set 6 Moldes Silicona Para Respostería | D41: Home | E41: Menaje de Cocina | F41: Utensilios repostería | G41: Nuevo | H41: out | I41: No | J41: In | K41: Urban
A42: 5Five | B42: 160479 | C42: Banca Madera Mix Café 105 X 34 X 50 cm 5 Five | D42: Home | E42: Muebles deco | F42: Bancas | G42: Nuevo | H42: in | I42: No | J42: In | K42: Urban
A43: 5Five | B43: 160479A | C43: Banca Madera Mix Gris 105 X 50 X 34 | D43: Home | E43: Muebles deco | F43: Bancas | G43: Nuevo | H43: out | I43: No | J43: In | K43: Urban
A44: 5Five | B44: 189646 | C44: Mueble Bar con soporte para 25 botellas Aliaj 5Five | D44: Home | E44: Muebles deco | F44: Bares | G44: Nuevo | H44: in | I44: No | J44: In | K44: Urban
A45: 5Five | B45: 185017 | C45: Escritorio Cierna 120x53x77 Cm | D45: Home | E45: Muebles deco | F45: Escritorios | G45: Nuevo | H45: out | I45: No | J45: In | K45: Urban
A46: 5Five | B46: 181327 | C46: Escritorio Drawers 120 X 76 X 60 Cm | D46: Home | E46: Muebles deco | F46: Escritorios | G46: Nuevo | H46: out | I46: No | J46: In | K46: Urban
A47: 5Five | B47: 189634 | C47: Rack De Vino De Bambú Para 12 Botellas | D47: Home | E47: Muebles deco | F47: Repisas | G47: Nuevo | H47: out | I47: No | J47: In | K47: Urban
A48: 5Five | B48: 120075N | C48: Cafetera Prensa Francesa 800 cc Vidrio 5Five | D48: Home | E48: Mundo Café | F48: Cafeteras | G48: Nuevo | H48: in | I48: No | J48: In | K48: Urban
A49: 5Five | B49: 120075G | C49: Cafetera Prensa Francesa 800 cc Vidrio 5Five | D49: Home | E49: Mundo Café | F49: Cafeteras | G49: Nuevo | H49: in | I49: No | J49: In | K49: Urban
A50: 5Five | B50: 120075R | C50: Cafetera Prensa Francesa 800 cc Vidrio 5Five | D50: Home | E50: Mundo Café | F50: Cafeteras | G50: Nuevo | H50: out | I50: No | J50: In | K50: Urban
A51: 5Five | B51: 120075 | C51: Cafetera Presna Francesa 800 Cc Vidrio Y Polipropileno Colores | D51: Home | E51: Mundo Café | F51: Cafeteras | G51: Nuevo | H51: out | I51: No | J51: In | K51: Urban
A52: 5Five | B52: 188441 | C52: Soporte Y 6 Tazas De Cafe De Vidrio 100 Cc | D52: Home | E52: Mundo Café | F52: Tazas | G52: Nuevo | H52: out | I52: No | J52: In | K52: Urban
A53: 5Five | B53: 160572C | C53: Termo de Acero Inoxidable de 1,5L 5Five | D53: Home | E53: Mundo Café | F53: Termos líquidos | G53: Nuevo | H53: out | I53: No | J53: In | K53: Urban
A54: 5Five | B54: 136001 | C54: Termo Isotérmico De Acero Inox 500 Cc | D54: Home | E54: Mundo Café | F54: Termos líquidos | G54: Nuevo | H54: out | I54: No | J54: In | K54: Urban
A55: 5Five | B55: 138013J | C55: Dispensador De Jabón De Gres Color Silk Negro | D55: Home | E55: Organización | F55: Accesorios de Baño | G55: Nuevo | H55: out | I55: No | J55: In | K55: Urban
A56: 5Five | B56: 138013I | C56: Dispensador De Jabón Silk, Color Blanco | D56: Home | E56: Organización | F56: Accesorios de Baño | G56: Nuevo | H56: out | I56: No | J56: In | K56: Urban
A57: 5Five | B57: 174712A | C57: Dispensador De Jabón Transparente 450 Cc | D57: Home | E57: Organización | F57: Accesorios de Baño | G57: Nuevo | H57: out | I57: No | J57: In | K57: Urban
A58: 5Five | B58: 174550 | C58: Dispensador De Jabon Vidrio 400 Cc | D58: Home | E58: Organización | F58: Accesorios de Baño | G58: Nuevo | H58: out | I58: No | J58: In | K58: Urban
A59: 5Five | B59: 160873A | C59: Set De Baño De 3 Piezas Propileno 5Five | D59: Home | E59: Organización | F59: Accesorios de Baño | G59: Nuevo | H59: out | I59: No | J59: In | K59: Urban
A60: 5Five | B60: 160873B | C60: Set De Baño De 3 Piezas Propileno 5Five | D60: Home | E60: Organización | F60: Accesorios de Baño | G60: Nuevo | H60: out | I60: No | J60: In | K60: Urban
A61: 5Five | B61: 174528I | C61: Basurero Baño Metal Blanco Cierre Suave 3Lt | D61: Home | E61: Organización | F61: Basureros | G61: Nuevo | H61: out | I61: No | J61: In | K61: Urban
A62: 5Five | B62: 174528 | C62: Basurero baño metal blanco-cierre suave 3 lt | D62: Home | E62: Organización | F62: Basureros | G62: Nuevo | H62: out | I62: No | J62: In | K62: Urban
A63: 5Five | B63: 174528J | C63: Basurero deBaño Metal Negro con Cierre Suave 3L 5Five | D63: Home | E63: Organización | F63: Basureros | G63: Nuevo | H63: out | I63: No | J63: In | K63: Urban
A64: 5Five | B64: 189702 | C64: Panera Cuadrada 25X25X10 Cm 5Five | D64: Home | E64: Organización | F64: Contenedores | G64: Nuevo | H64: out | I64: No | J64: In | K64: Urban
A65: 5Five | B65: 189703 | C65: Panera Ovalada 30x18x11 cm 5Five | D65: Home | E65: Organización | F65: Contenedores | G65: Nuevo | H65: in | I65: No | J65: In | K65: Urban
A66: 5Five | B66: 120395 | C66: Set 4 Contenedores Plasticos Colores | D66: Home | E66: Organización | F66: Contenedores | G66: Nuevo | H66: out | I66: No | J66: In | K66: Urban
A67: 5Five | B67: 120392 | C67: Set 7 Contenedores Plasticos Colores | D67: Home | E67: Organización | F67: Contenedores | G67: Nuevo | H67: out | I67: No | J67: In | K67: Urban
A68: 5Five | B68: 120054 | C68: Set De 3 Contenedores De 300 Palillos De Dientes De Bambu | D68: Home | E68: Organización | F68: Contenedores | G68: Nuevo | H68: out | I68: No | J68: In | K68: Urban
A69: 5Five | B69: 146512 | C69: Set De 3 Contenedores De Vidrio Tapa Plastica 5Five | D69: Home | E69: Organización | F69: Contenedores | G69: Nuevo | H69: out | I69: No | J69: In | K69: Urban
A70: 5Five | B70: 179626 | C70: Set Especiero Metálico 5 Piezas 5Five | D70: Home | E70: Organización | F70: Especieros | G70: Nuevo | H70: out | I70: No | J70: In | K70: Urban
A71: 5Five | B71: 150164 | C71: Alcuza 2 Botellas Aceite Vinagre 160 Cc | D71: Home | E71: Vajilla | F71: Alcuzas | G71: Nuevo | H71: out | I71: No | J71: In | K71: Urban
A72: 5Five | B72: 150166 | C72: Set Alcuza 4 Piezas | D72: Home | E72: Vajilla | F72: Alcuzas | G72: Nuevo | H72: out | I72: No | J72: In | K72: Urban
A73: 5Five | B73: 202590 | C73: Set Alcuza 4 Piezas + Soporte | D73: Home | E73: Vajilla | F73: Alcuzas | G73: Nuevo | H73: out | I73: No | J73: In | K73: Urban
A74: 5Five | B74: 188452 | C74: Soporte Para Postres 2 Niveles Bambu 25 cm 5Five | D74: Home | E74: Vajilla | F74: Loza Granel | G74: Nuevo | H74: out | I74: No | J74: In | K74: Urban
A75: Ann Williams Group | B75: CT2165T | C75: Hazlo Tu Mismo Amuletos Para El Pelo | D75: Kids | E75: Jueguetes de Rol | F75: Maquillaje y Belleza | G75: Bronce | H75: out | I75: No | J75: Out | K75: Aboc
A76: Ann Williams Group | B76: CT1925T | C76: Hazlo Tu Mismo Crea Una Amiga Ciervo | D76: Kids | E76: Jueguetes de Rol | F76: Maquillaje y Belleza | G76: Bronce | H76: out | I76: No | J76: Out | K76: Aboc
A77: Ann Williams Group | B77: CT2156T | C77: Hazlo Tu Mismo Pulseras | D77: Kids | E77: Jueguetes de Rol | F77: Maquillaje y Belleza | G77: Bronce | H77: out | I77: No | J77: Out | K77: Aboc
A78: Ann Williams Group | B78: CT1853-6T | C78: Hazlo Tu Mismo Pulseras De Amuletos | D78: Kids | E78: Jueguetes de Rol | F78: Maquillaje y Belleza | G78: Bronce | H78: out | I78: No | J78: Out | K78: Aboc
A79: Ann Williams Group | B79: CT1761-6T | C79: Kit De Proyectos Yo Amo Los Unicornios | D79: Kids | E79: Juguetes de Motricidad | F79: Didacticos | G79: Bronce | H79: out | I79: No | J79: Out | K79: Aboc
A80: Ann Williams Group | B80: CT1929T | C80: Stickers De Pared Casa Encantada | D80: Kids | E80: Juguetes Didácticos | F80: Stickers | G80: Bronce | H80: out | I80: No | J80: Out | K80: Aboc
A81: Ansaldo Games | B81: 21508 | C81: Juego De Destreza Palabrea | D81: Kids | E81: Juegos de Mesa | F81: Juegos de mesa | G81: Nuevo | H81: out | I81: No | J81: Out | K81: Ansaldo
A82: Ansaldo Games | B82: 21526 | C82: Ojo De Lince Travel | D82: Kids | E82: Juegos de Mesa | F82: Juegos de rapidez | G82: Nuevo | H82: out | I82: No | J82: Out | K82: Ansaldo
A83: Atmosphera | B83: 157266 | C83: Costurero Oria 30 Cm De Largo | D83: Home | E83: Deco | F83: Cajas decorativas | G83: Nuevo | H83: in | I83: No | J83: In | K83: Urban
A84: Atmosphera | B84: 168413 | C84: Set 3 Canastos Yute Jackson Atmosphera | D84: Home | E84: Deco | F84: Canastos | G84: Nuevo | H84: out | I84: No | J84: In | K84: Urban
A85: Atmosphera | B85: 168414 | C85: Set 3 Canastos Yute Jackson Atmosphera | D85: Home | E85: Deco | F85: Canastos | G85: Nuevo | H85: out | I85: No | J85: In | K85: Urban
A86: Atmosphera | B86: 157102 | C86: Set 4 Canastos Emmet de Caña Artesanal (S a XL) Atmosphera | D86: Home | E86: Deco | F86: Canastos | G86: Nuevo | H86: out | I86: No | J86: In | K86: Urban
A87: Atmosphera | B87: 157101 | C87: Set de 4 Canastos Yute Emmet | D87: Home | E87: Deco | F87: Canastos | G87: Nuevo | H87: in | I87: No | J87: In | K87: Urban
A88: Atmosphera | B88: 162315A | C88: Espejo Joe Diametro 45 Cm Metal y MDF | D88: Home | E88: Deco | F88: Espejos | G88: Nuevo | H88: out | I88: No | J88: In | K88: Urban
A89: Atmosphera | B89: 200200B | C89: Espejo Redondo Alice 38 cm Borde Metal Dorado | D89: Home | E89: Deco | F89: Espejos | G89: Nuevo | H89: out | I89: No | J89: In | K89: Urban
A90: Atmosphera | B90: 179422B | C90: Espejo Redondo Alice 76 cm Con Borde Metal Dorado | D90: Home | E90: Deco | F90: Espejos | G90: Nuevo | H90: out | I90: No | J90: In | K90: Urban
A91: Atmosphera | B91: 179422A | C91: Espejo Redondo Alice 76 Cm Con Borde Metal Negro | D91: Home | E91: Deco | F91: Espejos | G91: Nuevo | H91: out | I91: No | J91: In | K91: Urban
A92: Atmosphera | B92: 141149 | C92: Espejo Redondo Jane 58 Cm Con Borde Palillos Ratan Atmosphera | D92: Home | E92: Deco | F92: Espejos | G92: Nuevo | H92: out | I92: No | J92: In | K92: Urban
A93: Atmosphera | B93: 158229 | C93: Espejo Redondo Jane 76 Cm Con Borde Palillos Ratan Atmosphera | D93: Home | E93: Deco | F93: Espejos | G93: Nuevo | H93: out | I93: No | J93: In | K93: Urban
A94: Atmosphera | B94: 137391 | C94: Espejo Redondo Olav 52 cm Marco de Madera Beige Atmosphera | D94: Home | E94: Deco | F94: Espejos | G94: Nuevo | H94: out | I94: No | J94: In | K94: Urban
A95: Atmosphera | B95: 197625A | C95: Espejo Selena 112 x 40 cm Marco Metal Negro Atmosphera | D95: Home | E95: Deco | F95: Espejos | G95: Nuevo | H95: out | I95: No | J95: In | K95: Urban
A96: Atmosphera | B96: 160102C | C96: Florero Redondo De Vidrio Reciclado Azul 22 Cm | D96: Home | E96: Deco | F96: Floreros | G96: Nuevo | H96: out | I96: No | J96: In | K96: Urban
A97: Atmosphera | B97: 160102F | C97: Florero Redondo De Vidrio Reciclado Verde 22 Cm | D97: Home | E97: Deco | F97: Floreros | G97: Nuevo | H97: out | I97: No | J97: In | K97: Urban
A98: Atmosphera | B98: 155614 | C98: Jarron Florero Deco Marmol 10X20 Cm | D98: Home | E98: Deco | F98: Floreros | G98: Nuevo | H98: out | I98: No | J98: In | K98: Urban
A99: Atmosphera | B99: 155613 | C99: Jarron Florero Deco Marmol 11X18Cm | D99: Home | E99: Deco | F99: Floreros | G99: Nuevo | H99: out | I99: No | J99: In | K99: Urban
A100: Atmosphera | B100: 155686A | C100: Botella Vidrio Reciclado 35Cm | D100: Home | E100: Deco | F100: Jarrones | G100: Nuevo | H100: out | I100: No | J100: In | K100: Urban
A101: Atmosphera | B101: 155688C | C101: Botella Vidrio Reciclado 73Cm Azul | D101: Home | E101: Deco | F101: Jarrones | G101: Nuevo | H101: out | I101: No | J101: In | K101: Urban
A102: Atmosphera | B102: 160102A | C102: Botella Vidrio Reciclado Redonda 23 Cm | D102: Home | E102: Deco | F102: Jarrones | G102: Nuevo | H102: out | I102: No | J102: In | K102: Urban
A103: Atmosphera | B103: 155686C | C103: Jarron Azul 35 Cm Vidrio Reciclado | D103: Home | E103: Deco | F103: Jarrones | G103: Nuevo | H103: out | I103: No | J103: In | K103: Urban
A104: Atmosphera | B104: 155686F | C104: Jarron Verde 35 Cm Vidrio Reciclado | D104: Home | E104: Deco | F104: Jarrones | G104: Nuevo | H104: out | I104: No | J104: In | K104: Urban
A105: Atmosphera | B105: 155687C | C105: Jarron Vidrio Reciclado 51 Cm Azul | D105: Home | E105: Deco | F105: Jarrones | G105: Nuevo | H105: out | I105: No | J105: In | K105: Urban
A106: Atmosphera | B106: 155687F | C106: Jarron Vidrio Reciclado 51 Cm Verde | D106: Home | E106: Deco | F106: Jarrones | G106: Nuevo | H106: out | I106: No | J106: In | K106: Urban
A107: Atmosphera | B107: 155687A | C107: Jarron Vidrio Reciclado Transparente 51 Cm Alto | D107: Home | E107: Deco | F107: Jarrones | G107: Nuevo | H107: out | I107: No | J107: In | K107: Urban
A108: Atmosphera | B108: 155688A | C108: Jarron Vidrio Reciclado Transparente, 73 Cm Alto | D108: Home | E108: Deco | F108: Jarrones | G108: Nuevo | H108: out | I108: No | J108: In | K108: Urban
A109: Atmosphera | B109: 155688F | C109: Jarron Vidrio Reciclado Verde 73 Cm Alto | D109: Home | E109: Deco | F109: Jarrones | G109: Nuevo | H109: out | I109: No | J109: In | K109: Urban
A110: Atmosphera | B110: 167884 | C110: Perchero Bambu Con 8 Ganchos 175 Cm | D110: Home | E110: Deco | F110: Percheros | G110: Nuevo | H110: in | I110: No | J110: In | K110: Urban
A111: Atmosphera | B111: 105490 | C111: Perchero Con 8 Ganchos De Metal Negro 171 Cm | D111: Home | E111: Deco | F111: Percheros | G111: Nuevo | H111: out | I111: No | J111: In | K111: Urban
A112: Atmosphera | B112: 202312 | C112: Perchero Con 8 Ganchos De Negro 175 Cm | D112: Home | E112: Deco | F112: Percheros | G112: Nuevo | H112: in | I112: No | J112: In | K112: Urban
...

Sheet Empresa
A1: Empresa | B1: Canal
A2: Cliente Bice | B2: Banco Bice
A3: Bravium Chile SPA | B3: Bravium
A4: COMERCIAL GIANNY GIOVANNY CAPONA PALACIOS | B4: Casa de la Carcasa
A5: Electrónica Casa Royal LTDA. | B5: Casa Royal
A6: Celmedia Fidelización SPA | B6: Celmedia
A7: Cliente Linio | B7: CMR
A8: AUTOBAHN S A | B8: Concesionarios autos
A9: Servicio Automotriz Automec Limitada | B9: Concesionarios autos
A10: Felicity 360 SpA | B10: Corporativo
A11: VUELVO AL SUR SPA | B11: Corporativo
A12: MW2 CHILE MARKETING SPA | B12: Corporativo
... A149: Sanchez y Cia. | B149: Ferretería Higuerillas

Sheet CanalxKam
A1: Canal | B1: Tipo Negocio | C1: KAM | D1: Estado Canal
A2: Abc | B2: Marketplace | C2: Trini | D2: In
A3: Andesgear | B3: Marketplace | C3: NA | D3: out
A4: Banco Bice | B4: Fidelización | C4: Clau | D4: In
A5: Banco Scotiabank | B5: Fidelización | C5: NA | D5: out
A6: BazarED | B6: Marketplace | C6: Nicole | D6: In
A7: Betterfly | B7: Fidelización | C7: NA | D7: out
A8: Bodega | B8: Distribución | C8: NA | D8: out
A9: Bravium | B9: Fidelización | C9: Nicole | D9: out
A10: Celmedia | B10: Fidelización | C10: Trini | D10: In
A11: Cencosud | B11: Garantía extendida | C11: NA | D11: out
A12: Cmr | B12: Fidelización | C12: Nacha | D12: In
... A125: Speedreams | B125: Corporativo | C125: Erich | D125: In

Sheet Stock
A1: CA1/Stock | B1: Sku | C1: Costo Neto | D1: 154,165
A2: [1-MA-M] Bolsa Courier Compostable Materiactiva | B2: 1-MA-M | C2: 22280 | D2: 69
A3: [10001374] Campanilla Bicicleta Nutcase Baby Shark | B3: 10001374 | C3: 6490 | D3: 1
A4: [1000190502] Collar Triángulo Azul Talla Xs Perro Mascan | B4: 1000190502 | C4: 0 | D4: 6
A5: [1000190507] Collar Triángulo Naranja Tallas XS Perro Mascan | B5: 1000190507 | C5: 0 | D5: 3
A6: [1000190521] Collar Triángulo Fucsia Talla Xs Perro Mascan | B6: 1000190521 | C6: 0 | D6: 3
A7: [1000190602] Collar Triángulo Azul Talla S Perro Mascan | B7: 1000190602 | C7: 0 | D7: 3
A8: [1000190607] Collar Triángulo Naranja Tallas S Perro Mascan | B8: 1000190607 | C8: 0 | D8: 3
A9: [1000190621] Collar Triángulo Fucsia Talla S Perro Mascan | B9: 1000190621 | C9: 0 | D9: 3
A10: [1000190702] Collar Triángulo Azul Talla M Perro Mascan | B10: 1000190702 | C10: 0 | D10: 2
A11: [1000190707] Collar Triángulo Naranja Tallas M Perro Mascan | B11: 1000190707 | C11: 0 | D11: 4
A12: [1000190721] Collar Triángulo Fucsia Talla M Perro Mascan | B12: 1000190721 | C12: 0 | D12: 3
A13: [1000190802] Collar Triángulo Azul Talla L Perro Mascan | B13: 1000190802 | C13: 0 | D13: 4
A14: [1000190807] Collar Triángulo Naranja Tallas L Perro Mascan | B14: 1000190807 | C14: 0 | D14: 4
... A116: [1481123937937] Ampolleta Auto Halógena Biolight 9007 65/55w White 12v | B116: 1481123937937 | C116: 0 | D116: 5
A117: [1483452520904] Sensor Anti Fatiga Driver State Monitor | B117: #N/A | C117: #N/A | D117: 10
A118: [1496183099853] Cámara Deportiva 4k Lhotse H1 Video Con Accesorios | B118: 1496183099853 | C118: 17422 | D118: 123
A119: [1507904554106] Android 2111 | B119: 1507904554106 | C119: 1200 | D119: 1
A120: [1513100019184] Estabilizador De Cámaras Universales Portátil | B120: 1513100019184 | C120: 6665 | D120: 3
A121: [1513614057219] Lámpara Solar Linterna Inflable Camping Pesca Outdoor | B121: 1513614057219 | C121: 3379 | D121: 266
A122: [1513615220412] TV Streaming Device Chromecast | B122: 1513615220412 | C122: 8987 | D122: 36
A123: [1513615272195] Android Tv Box Mxq Pro 4K | B123: 1513615272195 | C123: 13329 | D123: 6
A124: [1514379781861] Monkey Toy Interactivo Azul | B124: 1514379781861 | C124: 3505 | D124: 1
A125: [1523536647880] Hamaca Camping Pesca Outdoor Lhotse Verde Claro 270 Cm | B125: 1523536647880 | C125: 11468 | D125: 123
A126: [1535543463599] Parrilla Portátil Carbón Kettle Roja 17'' | B126: 1535543463599 | C126: 17356 | D126: 12
A127: [1535566560027] Reloj Smartwatch Lhotse P10 Blanco | B127: 1535566560027 | C127: 7128 | D127: 9
A128: [1537889368850] Audífonos Bluetooth Deportivos Lhotse Rm5 Manos Libres | B128: 1537889368850 | C128: 4355 | D128: 328
A129: [1538141129434] Pesa Digital Balanza Baño Bluetooth Negra Inteligente | B129: 1538141129434 | C129: 3649 | D129: 757
... A141: [1549546168927] Cargador SW55 | B141: 1549546168927 | C141: 1015 | D141: 26
A142: [1561394899592] Parrilla Smoker Grill Negra | B142: #N/A | C142: #N/A | D142: 2
A143: [1564147623145] Correa Smartwatch Lhotse SW88 20mm Morada | B143: 1564147623145 | C143: 1382 | D143: 24
A144: [1564150627423] Audífonos Lhotse Bluetooth Inalámbrico Rm12 Blanco | B144: 1564150627423 | C144: 3214 | D144: 6238
A145: [1564150661249] Audífonos Lhotse Bluetooth Inalámbrico Rm12 Negro | B145: 1564150661249 | C145: 3054 | D145: 9907
A146: [1565218463197] Repetidor de Wifi Booster | B146: 1565218463197 | C146: 4055 | D146: 2
A147: [1565277372026] Correa Smartwatch Lhotse SW88 20mm Negra | B147: 1565277372026 | C147: 734 | D147: 379
A148: [1566335721736] Audífonos Lhotse Bluetooth Inalámbrico Rm12 Celeste . | B148: 1566335721736 | C148: 2920 | D148: 3977
A149: [1566849947902] Mochila Antirrobo Lhotse Gris Oscuro MA147 | B149: 1566849947902 | C149: 9579 | D149: 258
A150: [1571055493973] Secador De Toallas Pedestal 6 Niveles | B150: 1571055493973 | C150: 21535 | D150: 324
A151: [1574177821495] Smartwatch RD9 Correa Metálica Negra | B151: 1574177821495 | C151: 26245 | D151: 1
A152: [1579117587919] Smartwatch RD7 Azul | B152: 1579117587919 | C152: 14143 | D152: 11
A153: [1579117612971] Smartwatch RD7 Cuero Negro | B153: 1579117612971 | C153: 14572 | D153: 2
A154: [1581963986702] Reloj Smartwatch Lhotse RD7 Plateado Negro | B154: 1581963986702 | C154: 16835 | D154: 1
... A165: [1595434263015] Correa RD9 Cafe Cuero | B165: 1595434263015 | C165: 1868 | D165: 1
A166: [1596549586882] Camara 4k H1 Azul | B166: #N/A | C166: #N/A | D166: 1
A167: [1597086499840] Audífonos Lhotse RM7 Pro Inalámbrico Blanco | B167: 1597086499840 | C167: 5529 | D167: 1464
A168: [1597098592591] Audífonos Lhotse RM7 Pro Inalámbrico Negro | B168: 1597098592591 | C168: 6248 | D168: 1287
A169: [1600117183428] Placa Cobre Para Celular Reduce Bacterias Cu+Safe | B169: 1600117183428 | C169: 8 | D169: 3555
A170: [1601323542043] Cargador Smartwatch RD7 | B170: 1601323542043 | C170: 315 | D170: 8
A171: [1602029190396] Smartwatch Stone M4 Negro GPS | B171: 1602029190396 | C171: 28513 | D171: 2
A172: [1602163055069] Esterilizador Luz Uv De Bolsillo Sk8 Uvpocket Blanco | B172: 1602163055069 | C172: 26000 | D172: 2
A173: [1602623210379] Reloj Análogo Lhotse Flame Watch Negro | B173: 1602623210379 | C173: 3760 | D173: 6
A174: [1605622069868] Smartwatch SW88 Dorado Correa Rosada Claro | B174: 1605622069868 | C174: 9869 | D174: 1
A175: [1605624656414] Smartwatch RD7 Plateado Cuero Café Claro | B175: 1605624656414 | C175: 14271 | D175: 2
A176: [1605624727428] Smartwatch RD7 Cuero Café Claro | B176: 1605624727428 | C176: 16835 | D176: 2
A177: [1605708086872] Smartwatch RD7 Dark Silver Azul | B177: 1605708086872 | C177: 14860 | D177: 2
A178: [1605820909877] Cargador Smartwatch SW88 | B178: 1605820909877 | C178: 3 | D178: 1
... A364: [1659999410637] Mochila para Notebook con Puerto USB 15" Negra Levo | B364: 1659999410637 | C364: 3561 | D364: 891
A365: [1660-SET] Set 6 Vasos Vidrio Super Sham Rock 311 Ml Libbey | B365: 1660-SET | C365: 5436 | D365: 47
A366: [1660825216719] SMARTWATCH PARIS D20L | B366: 1660825216719 | C366: 3917 | D366: 1
A367: [1660825229924] SMARTBAND PARIS M7 | B367: 1660825229924 | C367: 2788 | D367: 1
A368: [1660857800718] Especiero Condimentos de Madera 8 Frascos Vidrio Simplit | B368: 1660857800718 | C368: 5592 | D368: 222
A369: [1660857914743] Set 2 Vasos de Vidrio Estilo Japonés 320 ml Simplit | B369: 1660857914743 | C369: 1413 | D369: 364
A370: [1660857963520] Tabla de Corte Plegable 3 en 1 Simplit | B370: 1660857963520 | C370: 3321 | D370: 221
A371: [1660858025311] Bowl Cortador Rallador de Verduras Multifuncional Simplit | B371: 1660858025311 | C371: 2768 | D371: 298
A372: [1660858101318] Mantequillero de Cerámica Tapa Bamboo 300 ml Simplit | B372: 1660858101318 | C372: 3084 | D372: 534
A373: [1660858118518] Mantequillero Cerámica Tapa Bamboo + Cuchillo 600 ml Simplit | B373: 1660858118518 | C373: 3503 | D373: 641
A374: [1660858235219] Termo Jarra Insulado Acero Inox 1 Lt Gris Simplit | B374: 1660858235219 | C374: 8367 | D374: 127
A375: [1660858266475] Termo Jarra Insulado Acero Inox 1 Lt Blanco Simplit | B375: 1660858266475 | C375: 8359 | D375: 48
A376: [1660858341796] Secaplatos Escurridor 2 Niveles Acero Inox Negro Simplit | B376: 1660858341796 | C376: 5860 | D376: 1862
A377: [1660858356962] Secaplatos Escurridor 2 Niveles Acero Inox Blanco Simplit | B377: 1660858356962 | C377: 5674 | D377: 1930
... A390: [1660859424566] Carpa Funda Cubre Auto Impermeable Premium con Felpa Xroad | B390: 1660859424566 | C390: 4555 | D390: 164
A391: [1661-SET] Set 6 Vasos Super Sham Vidrio 355 Ml Libbey | B391: 1661-SET | C391: 5329 | D391: 5
A392: [1661872713289] Set Alcuza Cerámica 2 Piezas Redonda 500 ml Simplit | B392: 1661872713289 | C392: 4420 | D392: 259
A393: [1661872956577] Set 3 Fuentes de Cerámica para Horno Celeste Simplit | B393: 1661872956577 | C393: 11461 | D393: 142
A394: [1661873760641] Mochila Street Lhotse 20 Lt Negra | B394: 1661873760641 | C394: 8280 | D394: 27
A395: [1661873779510] Mochila Street Lhotse 20 Lt Verde | B395: 1661873779510 | C395: 8380 | D395: 2
A396: [1661873799978] Mochila Volcano Lhotse 19 Lt Negra | B396: 1661873799978 | C396: 9255 | D396: 130
A397: [1661873818029] Mochila Volcano Lhotse 19 Lt Verde | B397: 1661873818029 | C397: 9466 | D397: 111
A398: [1661877072053] Cámara Inspección de Tuberías Endoscopio Industrial H6 | B398: 1661877072053 | C398: 270567 | D398: 2
A399: [1661892847912] Parrilla Portátil a Carbón Kettle Roja 17'' | B399: 1661892847912 | C399: 17761 | D399: 13
A400: [1661892870974] Parrilla Portátil a Carbón Kettle Negra 17'' | B400: 1661892870974 | C400: 15694 | D400: 4
A401: [1661894945281] Set 12 Utensilios Cocina Silicona Negro Simplit | B401: 1661894945281 | C401: 6142 | D401: 10
A402: [1661894977439] Set 12 Utensilios Cocina Silicona Calipso Simplit | B402: 1661894977439 | C402: 6511 | D402: 4
A403: [1662389376894] Set 3 Contenedores Cerámica Hermético Blanco Simplit | B403: 1662389376894 | C403: 8515 | D403: -152
... A412: [186296] Termo Multiuso Acero 1 Lt Thermos | B412: 186296 | C412: 13329 | D412: 9
A413: [20-40015] Loción De Protección Solar Hidratante SPF 15 Sun Bum | B413: 20-40015 | C413: 8399 | D413: 17
A414: [20-45030] Protector Solar Facial En Barra PF 30 Sun Bum | B414: 20-45030 | C414: 7810 | D414: 7
A415: [20-45080] After Sun Cool Down Gel Sun Bum | B415: 20-45080 | C415: 7557 | D415: 18
A416: [20-45085] After Sun Cool Down Lotion Sun Bum | B416: 20-45085 | C416: 7316 | D416: 16
A417: [20-45090] Clear Zinc Pantalla Solar a Base de Mineral SPF 50 Sun Bum | B417: 20-45090 | C417: 7810 | D417: 19
A418: [20-45092] Protector Solar Facial SPF 50 Sun Bum | B418: 20-45092 | C418: 8023 | D418: 11
A419: [20-45095] Bálsamo Labial Lip Balm SPF 30 Banana Sun Bum | B419: 20-45095 | C419: 2582 | D419: 3
A420: [20-46022] Bálsamo Labial Lip Balm SPF 30 Pineapple Sun Bum | B420: 20-46022 | C420: 2358 | D420: 7
A421: [20-46023] Bálsamo Labial Lip Balm SPF 30 Watermelon Sun Bum | B421: 20-46023 | C421: 2307 | D421: 2
A422: [20-46024] Balsamo Labial Lip Balm SPF 30 Coco Sun Bum | B422: 20-46024 | C422: 2765 | D422: 9
A423: [20-46025] Bálsamo Sun Bum Labial Lip Balm SPF 30 Key Lime Sun Bum | B423: 20-46025 | C423: 2307 | D423: 6
A424: [20-46026] Bálsamo Labial Lip Balm SPF 30 Mango Sun Bum | B424: 20-46026 | C424: 2765 | D424: 2
... A430: [20-65032] Signature Face Stick Tinted SPF 50 Sun Bum | B430: 20-65032 | C430: 12600 | D430: 5
A431: [20000207087] Arnés Anti-pull M Paseo Seguridad Mascotas Perro Mascan | B431: 20000207087 | C431: 0 | D431: 6
A432: [20000208084] Arnés Anti-Pull L Paseo Seguridad Mascotas Perro Mascan | B432: 20000208084 | C432: 0 | D432: 1
...

Sheet Resumen Stock
H2: INFORMACION CLIENTE | J2: INFORMACION UNIONX | M2: INFORMACION CLIENTE
H3: UnionX | I3: Cliente | J3: UnionX | M3: Precios Ciente | O3: Costo Cliente
H4: Grupo | I4: Descripcion | J4: Costo | K4: Margen | L4: Utilidad UnionX | M4: P Etiqueta | N4: PVP | O4: Costo | P4: Costo Oferta | Q4: Sku MLL | R4: Stock CD | S4: OBS
H11: Audifonos RM12 | I11: =B11 -> Ultimate GPS 217 Pink | J11: =E11 -> 32051 | K11: =1-(J11/P11) -> -4.4541241 | L11: =P11-J11 -> -26174.529 | M11: 19990 | N11: 9990 | O11: =M11/1.19*0.7 -> 11758.824 | P11: =N11/1.19*0.7 -> 5876.4706 | Q11: =C11 -> 1639085755244 | R11: =VLOOKUP(Q11,$C$4:$D$1048576,2,0) -> 8
H12: Audifonos RM12 | I12: =B12 -> Ultimate GPS 217 Black | J12: =E12 -> 32149.3 | K12: =1-(J12/P12) -> -4.4708519 | L12: =P12-J12 -> -26272.829 | M12: 19990 | N12: 9990 | O12: =M12/1.19*0.7 -> 11758.824 | P12: =N12/1.19*0.7 -> 5876.4706 | Q12: =C12 -> 1639085745522 | R12: =VLOOKUP(Q12,$C$4:$D$1048576,2,0) -> 16
H13: Audifonos RM12 | I13: =B13 -> tupper tapa madera | J13: =E13 -> 10210 | K13: =1-(J13/P13) -> -0.73743744 | L13: =P13-J13 -> -4333.5294 | M13: 19990 | N13: 9990 | O13: =M13/1.19*0.7 -> 11758.824 | P13: =N13/1.19*0.7 -> 5876.4706 | Q13: =C13 -> 1644258979631 | R13: =VLOOKUP(Q13,$C$4:$D$1048576,2,0) -> 1
H14: Audifonos RM12 | I14: =B14 -> TRX Rosado | J14: =E14 -> 12642.5 | K14: =1-(J14/P14) -> -1.1513764 | L14: =P14-J14 -> -6766.0294 | M14: 19990 | N14: 9990 | O14: =M14/1.19*0.7 -> 11758.824 | P14: =N14/1.19*0.7 -> 5876.4706 | Q14: =C14 -> 1616006958885 | R14: =VLOOKUP(Q14,$C$4:$D$1048576,2,0) -> 1
H15: Audifonos RM7 | I15: =B15 -> TRX Amarillo | J15: =E15 -> 13108.9 | K15: =1-(J15/P15) -> -0.48666644 | L15: =P15-J15 -> -4291.2529 | M15: 29990 | N15: 14990 | O15: =M15/1.19*0.7 -> 17641.176 | P15: =N15/1.19*0.7 -> 8817.6471 | Q15: =C15 -> 1616006872824 | R15: =VLOOKUP(Q15,$C$4:$D$1048576,2,0) -> 1
H16: Audifonos RM7 | I16: =B16 -> TP9200 Sistema de cámara de inspección de tuberías | J16: =E16 -> 217380 | K16: =1-(J16/P16) -> -23.652835 | L16: =P16-J16 -> -208562.35 | M16: 29990 | N16: 14990 | O16: =M16/1.19*0.7 -> 17641.176 | P16: =N16/1.19*0.7 -> 8817.6471 | Q16: =C16 -> 1661877043628 | R16: =VLOOKUP(Q16,$C$4:$D$1048576,2,0) -> 3
H18: Audifonos RM5 | I18: =B18 -> TP05C 21TP0731PI | J18: =E18 -> 36459 | K18: =1-(J18/P18) -> -3.7713857 | L18: =P18-J18 -> -28817.824 | M18: 24990 | N18: 12990 | O18: =M18/1.19*0.7 -> 14700 | P18: =N18/1.19*0.7 -> 7641.1765 | Q18: =C18 -> 1628778362232 | R18: =VLOOKUP(Q18,$C$4:$D$1048576,2,0) -> 1
H21: Audifonos RM7 | I21: =B21 -> Termo Lhotse Patagón 1 Lt Verde | J21: =E21 -> 5244.7 | K21: =1-(J21/P21) -> 0.40520414 | L21: =P21-J21 -> 3572.9471 | M21: 29990 | N21: 14990 | O21: =M21/1.19*0.7 -> 17641.176 | P21: =N21/1.19*0.7 -> 8817.6471 | Q21: =C21 -> 1627418225537 | R21: =VLOOKUP(Q21,$C$4:$D$1048576,2,0) -> 259
H22: Audifonos RM7 | I22: =B22 -> Termo Lhotse Patagón 1 Lt Negro | J22: =E22 -> 5168.5 | K22: =1-(J22/P22) -> 0.4138459 | L22: =P22-J22 -> 3649.1471 | M22: 29990 | N22: 14990 | O22: =M22/1.19*0.7 -> 17641.176 | P22: =N22/1.19*0.7 -> 8817.6471 | Q22: =C22 -> 1627424867043 | R22: =VLOOKUP(Q22,$C$4:$D$1048576,2,0) -> 244
H27: Big Mug Tumbler | I27: =B27 -> Teclado GAMER COLORES | J27: =E27 -> 13765 | K27: =1-(J27/P27) -> -0.17061031 | L27: =P27-J27 -> -2006.1765 | M27: 24990 | N27: 19990 | O27: =M27/1.19*0.7 -> 14700 | P27: =N27/1.19*0.7 -> 11758.824 | Q27: =C27 -> 1650478050242 | R27: =VLOOKUP(Q27,$C$4:$D$1048576,2,0) -> 1
H28: Big Mug Tumbler | I28: =B28 -> Taza Insulated Cup Mug 350ml Verde | J28: =E28 -> 2753 | K28: =1-(J28/P28) -> 0.76587794 | L28: =P28-J28 -> 9005.8235 | M28: 24990 | N28: 19990 | O28: =M28/1.19*0.7 -> 14700 | P28: =N28/1.19*0.7 -> 11758.824 | Q28: =C28 -> LHCAMU-GR | R28: =VLOOKUP(Q28,$C$4:$D$1048576,2,0) -> 95
H29: Big Mug Tumbler | I29: =B29 -> Taza Insulated Cup Mug 350ml Negro | J29: =E29 -> 2753 | K29: =1-(J29/P29) -> 0.76587794 | L29: =P29-J29 -> 9005.8235 | M29: 24990 | N29: 19990 | O29: =M29/1.19*0.7 -> 14700 | P29: =N29/1.19*0.7 -> 11758.824 | Q29: =C29 -> LHCAMU-BK | R29: =VLOOKUP(Q29,$C$4:$D$1048576,2,0) -> 95
... H61: Camara Deportiva 4k Video con Accesorios | I61: =B61 -> Smartwatch Connect S03 Pink | J61: =E61 -> 27160 | K61: =1-(J61/P61) -> 0.076375275 | L61: =P61-J61 -> 2245.8824 | M61: 59990 | N61: 49990 | O61: =M61/1.19*0.7 -> 35288.235 | P61: =N61/1.19*0.7 -> 29405.882 | Q61: =C61 -> LHCONS03PK | R61: =VLOOKUP(Q61,$C$4:$D$1048576,2,0) -> 92
H74: Ver si se pueden reutilizar en otro reloj y cambiar nombre
H75: Ver si se pueden reutilizar en otro reloj y cambiar nombre
H76: Ver si se pueden reutilizar en otro reloj y cambiar nombre
H77: Ver si se pueden reutilizar en otro reloj y cambiar nombre
H78: Ver si se pueden reutilizar en otro reloj y cambiar nombre
H79: Ver si se pueden reutilizar en otro reloj y cambiar nombre
H80: Ver si se pueden reutilizar en otro reloj y cambiar nombre
H81: Ver si se pueden reutilizar en otro reloj y cambiar nombre
H82: Ducha Solar Camping Pesca 20 Litros Outdoor | I82: =B82 -> Parlante Tune Up Verde | J82: =E82 -> 4803 | K82: =1-(J82/P82) -> -0.36312187 | L82: =P82-J82 -> -1279.4706 | M82: 9990 | N82: 5990 | O82: =M82/1.19*0.7 -> 5876.4706 | P82: =N82/1.19*0.7 -> 3523.5294 | Q82: =C82 -> 67933835988925 | R82: =VLOOKUP(Q82,$C$4:$D$1048576,2,0) -> 1833
H93: Hamaca Camping Pesca Outdoor Verde Claro 270 Cm | I93: =B93 -> package machine 21TP0402PI | J93: =E93 -> 221431 | K93: =1-(J93/P93) -> -14.063333 | L93: =P93-J93 -> -206731 | M93: 36990 | N93: 24990 | O93: =M93/1.19*0.7 -> 21758.824 | P93: =N93/1.19*0.7 -> 14700 | Q93: =C93 -> 1621435991486 | R93: =VLOOKUP(Q93,$C$4:$D$1048576,2,0) -> 1
H95: Insulated Travel Mug 900ml | I95: =B95 -> MUESTRA Smartwatch MX1 | J95: =E95 -> 18527 | K95: =1-(J95/P95) -> -2.1527427 | L95: =P95-J95 -> -12650.529 | M95: 21990 | N95: 9990 | O95: =M95/1.19*0.7 -> 12935.294 | P95: =N95/1.19*0.7 -> 5876.4706 | Q95: =C95 -> 1653404633176 | R95: =VLOOKUP(Q95,$C$4:$D$1048576,2,0) -> 1
H96: Insulated Travel Mug 900ml | I96: =B96 -> MUESTRA Smartwatch GPS CR130 | J96: =E96 -> 34052 | K96: =1-(J96/P96) -> -4.7946346 | L96: =P96-J96 -> -28175.529 | M96: 21990 | N96: 9990 | O96: =M96/1.19*0.7 -> 12935.294 | P96: =N96/1.19*0.7 -> 5876.4706 | Q96: =C96 -> 67414793517640 | R96: =VLOOKUP(Q96,$C$4:$D$1048576,2,0) -> 1
H97: Insulated Travel Mug 900ml | I97: =B97 -> MUESTRA Proyector PL12 | J97: =E97 -> 120849 | K97: =1-(J97/P97) -> -19.564895 | L97: =P97-J97 -> -114972.53 | M97: 21990 | N97: 9990 | O97: =M97/1.19*0.7 -> 12935.294 | P97: =N97/1.19*0.7 -> 5876.4706 | Q97: =C97 -> 1653404646981 | R97: =VLOOKUP(Q97,$C$4:$D$1048576,2,0) -> 1
H98: Insulated Travel Mug 900ml | I98: =B98 -> Muestra Proyector Aao 3 | J98: =E98 -> 72002 | K98: =1-(J98/P98) -> -11.252593 | L98: =P98-J98 -> -66125.529 | M98: 21990 | N98: 9990 | O98: =M98/1.19*0.7 -> 12935.294 | P98: =N98/1.19*0.7 -> 5876.4706 | Q98: =C98 -> 66559859669124 | R98: =VLOOKUP(Q98,$C$4:$D$1048576,2,0) -> 1
H99: Insulated Travel Mug 900ml | I99: =B99 -> Muestra Proyector Aao 2 | J99: =E99 -> 26402 | K99: =1-(J99/P99) -> -3.4928328 | L99: =P99-J99 -> -20525.529 | M99: 21990 | N99: 9990 | O99: =M99/1.19*0.7 -> 12935.294 | P99: =N99/1.19*0.7 -> 5876.4706 | Q99: =C99 -> 66559856061451 | R99: =VLOOKUP(Q99,$C$4:$D$1048576,2,0) -> 1
H102: Lámpara Solar Linterna Inflable Camping Pesca Outdoor | I102: =B102 -> Muestra Drone 1080 sdcard | J102: =E102 -> 38595 | K102: =1-(J102/P102) -> -4.0509238 | L102: =P102-J102 -> -30953.824 | M102: 14990 | N102: 12990 | O102: =M102/1.19*0.7 -> 8817.6471 | P102: =N102/1.19*0.7 -> 7641.1765 | Q102: =C102 -> 1650477967885 | R102: =VLOOKUP(Q102,$C$4:$D$1048576,2,0) -> 1
H105: Mate Mug + Bombilla | I105: =B105 -> MUESTRA Audifonos 618-10 | J105: =E105 -> 6037 | K105: =1-(J105/P105) -> -0.027317317 | L105: =P105-J105 -> -160.52941 | M105: 16990 | N105: 9990 | O105: =M105/1.19*0.7 -> 9994.1176 | P105: =N105/1.19*0.7 -> 5876.4706 | Q105: =C105 -> 1656617655162 | R105: =VLOOKUP(Q105,$C$4:$D$1048576,2,0) -> 1
H106: Mate Mug + Bombilla | I106: =B106 -> MUESTRA Audifonos 618-1 | J106: =E106 -> 7379 | K106: =1-(J106/P106) -> -0.25568569 | L106: =P106-J106 -> -1502.5294 | M106: 16990 | N106: 9990 | O106: =M106/1.19*0.7 -> 9994.1176 | P106: =N106/1.19*0.7 -> 5876.4706 | Q106: =C106 -> 1656617557771 | R106: =VLOOKUP(Q106,$C$4:$D$1048576,2,0) -> 1
H107: Mate Mug + Bombilla | I107: =B107 -> MUESTRA Audifono T58 | J107: =E107 -> 4378 | K107: =1-(J107/P107) -> 0.254995 | L107: =P107-J107 -> 1498.4706 | M107: 16990 | N107: 9990 | O107: =M107/1.19*0.7 -> 9994.1176 | P107: =N107/1.19*0.7 -> 5876.4706 | Q107: =C107 -> 67414791217036 | R107: =VLOOKUP(Q107,$C$4:$D$1048576,2,0) -> 1
H108: Mate Mug + Bombilla | I108: =B108 -> MUESTRA Audifono T17 | J108: =E108 -> 15439 | K108: =1-(J108/P108) -> -1.6272573 | L108: =P108-J108 -> -9562.5294 | M108: 16990 | N108: 9990 | O108: =M108/1.19*0.7 -> 9994.1176 | P108: =N108/1.19*0.7 -> 5876.4706 | Q108: =C108 -> 1653404596846 | R108: =VLOOKUP(Q108,$C$4:$D$1048576,2,0) -> 1
... H375: Toldo lateral Auto camping | I375: =B375 -> VR BOX 2.0 Sin Control | J375: =E375 -> 2709.1 | K375: =1-(J375/P375) -> 0.97441263 | L375: =P375-J375 -> 103167.37 | M375: 199990 | N375: 179990 | O375: =M375/1.19*0.7 -> 117641.18 | P375: =N375/1.19*0.7 -> 105876.47 | Q375: =C375 -> 1479823191801 | R375: =VLOOKUP(Q375,$C$4:$D$1048576,2,0) -> 195

Sheet Base Stk BSale
A1: Sucursal | C1: Todas
A2: filtro de Atributos del Producto o Variante | C2: Sin Filtro
A3: filtro disp. venta menor igual a | C3: Sin Filtro
A5: Tipo de Producto | B5: Producto | C5: Variante | D5: Código Barras | E5: SKU | F5: Sucursal | G5: Stock | H5: Costo Neto Prom. Unitario | I5: Costo Neto Prom. Total | J5: Cantidad por Despachar | K5: Cantidad Disponible | L5: Por Recibir
A6: ABOC | B6: Ann Williams Group | C6: Hazlo Tu Mismo Amuletos Para El Pelo Ann Williams Group | D6: ="CT2165T" -> CT2165T | E6: ="CT2165T" -> CT2165T | F6: Bodega Carrascal | G6: 5 | H6: 9400 | I6: 47000 | J6: 0 | K6: 5 | L6: 0
A7: ABOC | B7: Ann Williams Group | C7: Hazlo Tu Mismo Crea Una Amiga Ciervo Ann Williams Group | D7: ="CT1925T" -> CT1925T | E7: ="CT1925T" -> CT1925T | F7: Bodega Carrascal | G7: 4 | H7: 10500 | I7: 42000 | J7: 0 | K7: 4 | L7: 0
A8: ABOC | B8: Ann Williams Group | C8: Hazlo Tu Mismo Pulseras Ann Williams Group | D8: ="CT2156T" -> CT2156T | E8: ="CT2156T" -> CT2156T | F8: Bodega Carrascal | G8: 7 | H8: 10079 | I8: 70553 | J8: 0 | K8: 7 | L8: 0
A9: ABOC | B9: Ann Williams Group | C9: Hazlo Tu Mismo Pulseras De Amuletos Ann Williams Group | D9: ="CT1853-6T" -> CT1853-6T | E9: ="CT1853-6T" -> CT1853-6T | F9: Bodega Carrascal | G9: 3 | H9: 9500 | I9: 28500 | J9: 0 | K9: 3 | L9: 0
A10: ABOC | B10: Ann Williams Group | C10: Kit De Proyectos Yo Amo Los Unicornios Ann Williams Group | D10: ="CT1761-6T" -> CT1761-6T | E10: ="CT1761-6T" -> CT1761-6T | F10: Bodega Carrascal | G10: 6 | H10: 10500 | I10: 63000 | J10: 0 | K10: 6 | L10: 0
A11: ABOC | B11: Ann Williams Group | C11: Stickers De Pared Casa Encantada Ann Williams Group | D11: ="CT1929T" -> CT1929T | E11: ="CT1929T" -> CT1929T | F11: Bodega Carrascal | G11: 6 | H11: 5950 | I11: 35700 | J11: 0 | K11: 6 | L11: 0
A12: MLL | B12: Armado Sillas | C12: Levo | D12: ="69748179686395" -> 69748179686395 | E12: ="69748179686395" -> 69748179686395 | F12: Bodega Carrascal | G12: 29 | H12: 1 | I12: 29 | J12: 0 | K12: 29 | L12: 0
A13: 4Trade | B13: Balvi | C13: Base Soporte Monitor Notebook Nordik Negro | D13: ="27534" -> 27534 | E13: ="27534" -> 27534 | F13: Bodega Carrascal | G13: 6 | H13: 15100 | I13: 90600 | J13: 0 | K13: 6 | L13: 0
A14: 4Trade | B14: Balvi | C14: Caja Organizador Capsulas Balvi | D14: ="8430306262505" -> 8430306262505 | E14: ="26250" -> 26250 | F14: Bodega Carrascal | G14: 9 | H14: 12580 | I14: 113220 | J14: 0 | K14: 9 | L14: 0
A15: 4Trade | B15: Balvi | C15: Caja Organizadora Rectangular Balvi | D15: ="8430306268828" -> 8430306268828 | E15: ="26882" -> 26882 | F15: Bodega Carrascal | G15: 3 | H15: 10100 | I15: 30300 | J15: 0 | K15: 3 | L15: 0
A16: 4Trade | B16: Balvi | C16: Caja Organizadora Ropa Balvi | D16: ="8430306268798" -> 8430306268798 | E16: ="26879" -> 26879 | F16: Bodega Carrascal | G16: 6 | H16: 10100 | I16: 60600 | J16: 0 | K16: 6 | L16: 0
A17: 4Trade | B17: Balvi | C17: Candelabro Metal Haus Balvi | D17: ="8430306265025" -> 8430306265025 | E17: ="26502" -> 26502 | F17: Bodega Carrascal | G17: 6 | H17: 5000 | I17: 30000 | J17: 0 | K17: 6 | L17: 0
A18: 4Trade | B18: Balvi | C18: Cojin Kitty Blanco Balvi | D18: ="27027" -> 27027 | E18: ="27027" -> 27027 | F18: Bodega Carrascal | G18: 6 | H18: 7600 | I18: 45600 | J18: 0 | K18: 6 | L18: 0
A19: 4Trade | B19: Balvi | C19: Cojin Kitty Gris Balvi | D19: ="26807" -> 26807 | E19: ="26807" -> 26807 | F19: Bodega Carrascal | G19: 11 | H19: 7600 | I19: 83600 | J19: 0 | K19: 11 | L19: 0
A20: 4Trade | B20: Balvi | C20: Cojin Kitty Negro Balvi | D20: ="26808" -> 26808 | E20: ="26808" -> 26808 | F20: Bodega Carrascal | G20: 9 | H20: 7600 | I20: 68400 | J20: 0 | K20: 9 | L20: 0
A21: 4Trade | B21: Balvi | C21: Cojin Kitty Rosado Balvi | D21: ="27213" -> 27213 | E21: ="27213" -> 27213 | F21: Bodega Carrascal | G21: 10 | H21: 7600 | I21: 76000 | J21: 0 | K21: 10 | L21: 0
A22: 4Trade | B22: Balvi | C22: Cojin Magic Dorado Balvi | D22: ="26916" -> 26916 | E22: ="26916" -> 26916 | F22: Bodega Carrascal | G22: 9 | H22: 2500 | I22: 22500 | J22: 0 | K22: 9 | L22: 0
A23: 4Trade | B23: Balvi | C23: Cojin Magic Plateado Balvi | D23: ="26915" -> 26915 | E23: ="26915" -> 26915 | F23: Bodega Carrascal | G23: 12 | H23: 2500 | I23: 30000 | J23: 0 | K23: 12 | L23: 0
A24: 4Trade | B24: Balvi | C24: Cojin Magic Rosado Balvi | D24: ="26917" -> 26917 | E24: ="26917" -> 26917 | F24: Bodega Carrascal | G24: 17 | H24: 2500 | I24: 42500 | J24: 0 | K24: 17 | L24: 0
A25: 4Trade | B25: Balvi | C25: Colgador Llaves Musik Balvi | D25: ="8430306274454" -> 8430306274454 | E25: ="27445" -> 27445 | F25: Bodega Carrascal | G25: 4 | H25: 5000 | I25: 20000 | J25: 0 | K25: 4 | L25: 0
A26: 4Trade | B26: Balvi | C26: Colgador Mountain Dorado Balvi | D26: ="27184" -> 27184 | E26: ="27184" -> 27184 | F26: Bodega Carrascal | G26: 6 | H26: 12600 | I26: 75600 | J26: 0 | K26: 6 | L26: 0
A27: 4Trade | B27: Balvi | C27: Colgador Mountain Plateado Balvi | D27: ="27185" -> 27185 | E27: ="27185" -> 27185 | F27: Bodega Carrascal | G27: 6 | H27: 12600 | I27: 75600 | J27: 0 | K27: 6 | L27: 0
A28: 4Trade | B28: Balvi | C28: Colgador Pared Musik Balvi | D28: ="27446" -> 27446 | E28: ="27446" -> 27446 | F28: Bodega Carrascal | G28: 7 | H28: 10100 | I28: 70700 | J28: 0 | K28: 7 | L28: 0
A29: 4Trade | B29: Balvi | C29: Colgador Pared The Bear Balvi | D29: ="26876" -> 26876 | E29: ="26876" -> 26876 | F29: Bodega Carrascal | G29: 11 | H29: 3000 | I29: 33000 | J29: 0 | K29: 11 | L29: 0
A30: 4Trade | B30: Balvi | C30: Colgador Pared The Cat Balvi | D30: ="26875" -> 26875 | E30: ="26875" -> 26875 | F30: Bodega Carrascal | G30: 9 | H30: 2458.3 | I30: 22125 | J30: 0 | K30: 9 | L30: 0
A31: 4Trade | B31: Balvi | C31: Espejo Cat Negro 48Cm Balvi | D31: ="27122" -> 27122 | E31: ="27122" -> 27122 | F31: Bodega Carrascal | G31: 6 | H31: 15100 | I31: 90600 | J31: 0 | K31: 6 | L31: 0
A32: 4Trade | B32: Balvi | C32: Estuche para Joyas Bureau Madera Balvi | D32: ="26404" -> 26404 | E32: ="26404" -> 26404 | F32: Bodega Carrascal | G32: 9 | H32: 15100 | I32: 135900 | J32: 0 | K32: 9 | L32: 0
A33: 4Trade | B33: Balvi | C33: Estuche para Joyas Haus Madera Balvi | D33: ="27239" -> 27239 | E33: ="27239" -> 27239 | F33: Bodega Carrascal | G33: 3 | H33: 20100 | I33: 60300 | J33: 0 | K33: 3 | L33: 0
A34: 4Trade | B34: Balvi | C34: Estuche para Joyas Precious Metal Balvi | D34: ="26773" -> 26773 | E34: ="26773" -> 26773 | F34: Bodega Carrascal | G34: 10 | H34: 5000 | I34: 50000 | J34: 0 | K34: 10 | L34: 0
A35: 4Trade | B35: Balvi | C35: Hielera Vidrio L`Hédoniste Balvi | D35: ="26065" -> 26065 | E35: ="26065" -> 26065 | F35: Bodega Carrascal | G35: 3 | H35: 7600 | I35: 22800 | J35: 0 | K35: 3 | L35: 0
A36: 4Trade | B36: Balvi | C36: Lámpara Mesa Bulb Balvi | D36: ="27246" -> 27246 | E36: ="27246" -> 27246 | F36: Bodega Carrascal | G36: 11 | H36: 4000 | I36: 44000 | J36: 0 | K36: 11 | L36: 0
A37: 4Trade | B37: Balvi | C37: Lámpara Mesa On Off Balvi | D37: ="26575" -> 26575 | E37: ="26575" -> 26575 | F37: Bodega Carrascal | G37: 12 | H37: 5000 | I37: 60000 | J37: 0 | K37: 12 | L37: 0
A38: 4Trade | B38: Balvi | C38: Lámpara Moon Balvi | D38: ="27353" -> 27353 | E38: ="27353" -> 27353 | F38: Bodega Carrascal | G38: 4 | H38: 10100 | I38: 40400 | J38: 0 | K38: 4 | L38: 0
A39: 4Trade | B39: Balvi | C39: Lámpara Sensor Lucciola | D39: ="8430306265964" -> 8430306265964 | E39: ="26596" -> 26596 | F39: Bodega Carrascal | G39: 7 | H39: 5000 | I39: 35000 | J39: 0 | K39: 7 | L39: 0
A40: 4Trade | B40: Balvi | C40: Lámpara Tic Tic Blanca Balvi | D40: ="27433" -> 27433 | E40: ="27433" -> 27433 | F40: Bodega Carrascal | G40: 8 | H40: 10100 | I40: 80800 | J40: 0 | K40: 8 | L40: 0
A41: 4Trade | B41: Balvi | C41: Lámpara Usb Clamp Verde Balvi | D41: ="27249" -> 27249 | E41: ="27249" -> 27249 | F41: Bodega Carrascal | G41: 7 | H41: 3000 | I41: 21000 | J41: 0 | K41: 7 | L41: 0
A42: 4Trade | B42: Balvi | C42: Lámpara Usb/3Aa 34Cm Balvi | D42: ="27245" -> 27245 | E42: ="27245" -> 27245 | F42: Bodega Carrascal | G42: 14 | H42: 7600 | I42: 106400 | J42: 0 | K42: 14 | L42: 1
A43: 4Trade | B43: Balvi | C43: Lámpara Usb/4Aa 43Cm | D43: ="8430306260709" -> 8430306260709 | E43: ="26070" -> 26070 | F43: Bodega Carrascal | G43: 5 | H43: 7600 | I43: 38000 | J43: 0 | K43: 5 | L43: 0
A44: 4Trade | B44: Balvi | C44: Mantequillero Vidrio Butter Balvi | D44: ="23669" -> 23669 | E44: ="23669" -> 23669 | F44: Bodega Carrascal | G44: 9 | H44: 4000 | I44: 36000 | J44: 0 | K44: 9 | L44: 0
A45: 4Trade | B45: Balvi | C45: Marco Foto Magic X8 Negro Balvi | D45: ="24767" -> 24767 | E45: ="24767" -> 24767 | F45: Bodega Carrascal | G45: 6 | H45: 4550 | I45: 27300 | J45: 0 | K45: 6 | L45: 0
A46: 4Trade | B46: Balvi | C46: Marco Foto Tratto 3D X4 Balvi | D46: ="8430306267609" -> 8430306267609 | E46: ="26760" -> 26760 | F46: Bodega Carrascal | G46: 6 | H46: 4000 | I46: 24000 | J46: 0 | K46: 6 | L46: 0
A47: 4Trade | B47: Balvi | C47: Marco Foto Tratto 3D X7 Balvi | D47: ="8430306267647" -> 8430306267647 | E47: ="26764" -> 26764 | F47: Bodega Carrascal | G47: 5 | H47: 6500 | I47: 32500 | J47: 0 | K47: 5 | L47: 0
A48: 4Trade | B48: Balvi | C48: Marco Foto Tratto 3D X9 Balvi | D48: ="8430306267661" -> 8430306267661 | E48: ="26766" -> 26766 | F48: Bodega Carrascal | G48: 5 | H48: 10100 | I48: 50500 | J48: 0 | K48: 5 | L48: 0
A49: 4Trade | B49: Balvi | C49: Marco Kube 10X10 1/Aa Balvi | D49: ="24824" -> 24824 | E49: ="24824" -> 24824 | F49: Bodega Carrascal | G49: 2 | H49: 5000 | I49: 10000 | J49: 0 | K49: 2 | L49: 0
A50: 4Trade | B50: Balvi | C50: Marco Messege Rec 10 Seg Balvi | D50: ="8430306258034" -> 8430306258034 | E50: ="25803" -> 25803 | F50: Bodega Carrascal | G50: 9 | H50: 2800 | I50: 25200 | J50: 0 | K50: 9 | L50: 1
A51: 4Trade | B51: Balvi | C51: Marco Mignon X2 Balvi | D51: ="8430306260556" -> 8430306260556 | E51: ="26055" -> 26055 | F51: Bodega Carrascal | G51: 2 | H51: 2500 | I51: 5000 | J51: 0 | K51: 2 | L51: 0
A52: 4Trade | B52: Balvi | C52: Marco Mignon X4 Balvi | D52: ="8430306260570" -> 8430306260570 | E52: ="26057" -> 26057 | F52: Bodega Carrascal | G52: 2 | H52: 4000 | I52: 8000 | J52: 0 | K52: 2 | L52: 0
A53: 4Trade | B53: Balvi | C53: Mesa de Centro Vidrio Cosmos Balvi | D53: ="27496" -> 27496 | E53: ="27496" -> 27496 | F53: Bodega Carrascal | G53: 6 | H53: 20100 | I53: 120600 | J53: 0 | K53: 6 | L53: 0
A54: 4Trade | B54: Balvi | C54: Mesa de Centro Vidrio Moon Balvi | D54: ="27495" -> 27495 | E54: ="27495" -> 27495 | F54: Bodega Carrascal | G54: 3 | H54: 20100 | I54: 60300 | J54: 0 | K54: 3 | L54: 0
A55: 4Trade | B55: Balvi | C55: Molinillo Pimienta Acrílico Balvi | D55: ="8430306275857" -> 8430306275857 | E55: ="27585" -> 27585 | F55: Bodega Carrascal | G55: 9 | H55: 4000 | I55: 36000 | J55: 0 | K55: 9 | L55: 0
A56: 4Trade | B56: Balvi | C56: Organizador De Zapatos 4 Niveles Balvi | D56: ="26022" -> 26022 | E56: ="26022" -> 26022 | F56: Bodega Carrascal | G56: 6 | H56: 3500 | I56: 21000 | J56: 0 | K56: 6 | L56: 0
A57: 4Trade | B57: Balvi | C57: Organizador De Zapatos Doble Balvi | D57: ="26021" -> 26021 | E57: ="26021" -> 26021 | F57: Bodega Carrascal | G57: 60 | H57: 1000 | I57: 60000 | J57: 0 | K57: 60 | L57: 0
A58: 4Trade | B58: Balvi | C58: ORGANIZADOR DE ZAPATOS DOBLE X2 | D58: ="26021A" -> 26021A | E58: ="26021A" -> 26021A | F58: Bodega Carrascal | G58: 2 | H58: 2000 | I58: 4000 | J58: 0 | K58: 2 | L58: 0
A59: 4Trade | B59: Balvi | C59: ORGANIZADOR DE ZAPATOS DOBLE X4 | D59: ="26021B" -> 26021B | E59: ="26021B" -> 26021B | F59: Bodega Carrascal | G59: 4 | H59: 3500 | I59: 14000 | J59: 0 | K59: 4 | L59: 0
A60: 4Trade | B60: Balvi | C60: Organizador Sofa Balvi | D60: ="8430306269948" -> 8430306269948 | E60: ="26994" -> 26994 | F60: Bodega Carrascal | G60: 6 | H60: 4161 | I60: 24966 | J60: 0 | K60: 6 | L60: 0
A61: 4Trade | B61: Balvi | C61: Pack x 2 Cojín Magic Plateado/Dorado Balvi | D61: ="2691516" -> 2691516 | E61: ="2691516" -> 2691516 | F61: Bodega Carrascal | G61: 6 | H61: 4000 | I61: 24000 | J61: 0 | K61: 6 | L61: 0
A62: 4Trade | B62: Balvi | C62: Pack x 2 Cojín Magic Plateado/Rosado Balvi | D62: ="2691517" -> 2691517 | E62: ="2691517" -> 2691517 | F62: Bodega Carrascal | G62: 7 | H62: 3329 | I62: 23303 | J62: 0 | K62: 7 | L62: 0
A63: 4Trade | B63: Balvi | C63: Papelera Basketball Polipropileno Balvi | D63: ="26409" -> 26409 | E63: ="26409" -> 26409 | F63: Bodega Carrascal | G63: 9 | H63: 6340 | I63: 57060 | J63: 0 | K63: 9 | L63: 0
A64: 4Trade | B64: Balvi | C64: Papelera Globe Lata Balvi | D64: ="25566" -> 25566 | E64: ="25566" -> 25566 | F64: Bodega Carrascal | G64: 8 | H64: 9260 | I64: 74080 | J64: 0 | K64: 8 | L64: 0
A65: 4Trade | B65: Balvi | C65: Papelera Letters Blanco Balvi | D65: ="26883" -> 26883 | E65: ="26883" -> 26883 | F65: Bodega Carrascal | G65: 5 | H65: 7600 | I65: 38000 | J65: 0 | K65: 5 | L65: 0
A66: 4Trade | B66: Balvi | C66: Papelera Letters Gris | D66: ="26885" -> 26885 | E66: ="26885" -> 26885 | F66: Bodega Carrascal | G66: 6 | H66: 7600 | I66: 45600 | J66: 0 | K66: 6 | L66: 0
A67: 4Trade | B67: Balvi | C67: Papelera Letters Negro Balvi | D67: ="26884" -> 26884 | E67: ="26884" -> 26884 | F67: Bodega Carrascal | G67: 6 | H67: 7600 | I67: 45600 | J67: 0 | K67: 6 | L67: 0
A68: 4Trade | B68: Balvi | C68: Papelera Sharpener Negro Balvi | D68: ="27409" -> 27409 | E68: ="27409" -> 27409 | F68: Bodega Carrascal | G68: 4 | H68: 10100 | I68: 40400 | J68: 0 | K68: 4 | L68: 0
A69: 4Trade | B69: Balvi | C69: Papelera Sharpener Rojo Balvi | D69: ="27261" -> 27261 | E69: ="27261" -> 27261 | F69: Bodega Carrascal | G69: 7 | H69: 10100 | I69: 70700 | J69: 0 | K69: 7 | L69: 0
A70: 4Trade | B70: Balvi | C70: Papelera Sharpener Rosado Balvi | D70: ="27413" -> 27413 | E70: ="27413" -> 27413 | F70: Bodega Carrascal | G70: 10 | H70: 10100 | I70: 101000 | J70: 0 | K70: 10 | L70: 0
A71: 4Trade | B71: Balvi | C71: Papelera Sharpener Turquesa Balvi | D71: ="27411" -> 27411 | E71: ="27411" -> 27411 | F71: Bodega Carrascal | G71: 15 | H71: 10100 | I71: 151500 | J71: 0 | K71: 15 | L71: 0
A72: 4Trade | B72: Balvi | C72: Perchero Birdie Metal Blanco Balvi | D72: ="26925" -> 26925 | E72: ="26925" -> 26925 | F72: Bodega Carrascal | G72: 5 | H72: 40300 | I72: 201500 | J72: 0 | K72: 5 | L72: 0
A73: 4Trade | B73: Balvi | C73: Perchero Alaska Metal Madera Balvi | D73: ="25163" -> 25163 | E73: ="25163" -> 25163 | F73: Bodega Carrascal | G73: 10 | H73: 40300 | I73: 403000 | J73: 0 | K73: 10 | L73: 0
A74: 4Trade | B74: Balvi | C74: Perchero Shiitake Acero Blanco Balvi | D74: ="26667" -> 26667 | E74: ="26667" -> 26667 | F74: Bodega Carrascal | G74: 5 | H74: 35300 | I74: 176500 | J74: 0 | K74: 5 | L74: 0
A75: 4Trade | B75: Balvi | C75: Perchero Shiitake Acero Negro Balvi | D75: ="26669" -> 26669 | E75: ="26669" -> 26669 | F75: Bodega Carrascal | G75: 2 | H75: 31770 | I75: 63540 | J75: 0 | K75: 2 | L75: 0
A76: 4Trade | B76: Balvi | C76: Perchero Shiitake Madera Blanco Balvi | D76: ="26668" -> 26668 | E76: ="26668" -> 26668 | F76: Bodega Carrascal | G76: 5 | H76: 40300 | I76: 201500 | J76: 0 | K76: 5 | L76: 0
A77: 4Trade | B77: Balvi | C77: Porta Foto Iman X3 Metal Madera Balvi | D77: ="8430306267364" -> 8430306267364 | E77: ="26736" -> 26736 | F77: Bodega Carrascal | G77: 9 | H77: 3000 | I77: 27000 | J77: 0 | K77: 9 | L77: 0
A78: 4Trade | B78: Balvi | C78: Puff La Vache Marron Polipiel Balvi | D78: ="26935" -> 26935 | E78: ="26935" -> 26935 | F78: Bodega Carrascal | G78: 2 | H78: 33583 | I78: 67166 | J78: 0 | K78: 2 | L78: 0
A79: 4Trade | B79: Balvi | C79: Puff La Vache Negra Polipiel | D79: ="27106" -> 27106 | E79: ="27106" -> 27106 | F79: Bodega Carrascal | G79: 6 | H79: 40300 | I79: 241800 | J79: 0 | K79: 6 | L79: 0
A80: 4Trade | B80: Balvi | C80: Puff La Vache Vaca Polipiel Balvi | D80: ="27174" -> 27174 | E80: ="27174" -> 27174 | F80: Bodega Carrascal | G80: 6 | H80: 40300 | I80: 241800 | J80: 0 | K80: 6 | L80: 0
A81: 4Trade | B81: Balvi | C81: Puff Le Carlin Café Balvi | D81: ="27489" -> 27489 | E81: ="27489" -> 27489 | F81: Bodega Carrascal | G81: 8 | H81: 50400 | I81: 403200 | J81: 0 | K81: 8 | L81: 0
A82: 4Trade | B82: Balvi | C82: Puff Le Minou Gris/Blanco | D82: ="27487" -> 27487 | E82: ="27487" -> 27487 | F82: Bodega Carrascal | G82: 2 | H82: 50400 | I82: 100800 | J82: 0 | K82: 2 | L82: 0
A83: 4Trade | B83: Balvi | C83: Puff Le Minou Negro/Blanco | D83: ="27488" -> 27488 | E83: ="27488" -> 27488 | F83: Bodega Carrascal | G83: 5 | H83: 50400 | I83: 252000 | J83: 0 | K83: 5 | L83: 0
A84: 4Trade | B84: Balvi | C84: Reloj Pared Milk Metal Balvi | D84: ="25835" -> 25835 | E84: ="25835" -> 25835 | F84: Bodega Carrascal | G84: 12 | H84: 3500 | I84: 42000 | J84: 0 | K84: 12 | L84: 0
A85: 4Trade | B85: Balvi | C85: Reloj Pared Oslo Metal Balvi | D85: ="26233" -> 26233 | E85: ="26233" -> 26233 | F85: Bodega Carrascal | G85: 7 | H85: 7600 | I85: 53200 | J85: 0 | K85: 7 | L85: 0
A86: 4Trade | B86: Balvi | C86: Revistero Cat Blanco Balvi | D86: ="8430306271255" -> 8430306271255 | E86: ="27125" -> 27125 | F86: Bodega Carrascal | G86: 4 | H86: 10100 | I86: 40400 | J86: 0 | K86: 4 | L86: 0
A87: 4Trade | B87: Balvi | C87: Revistero Haus Blanco Balvi | D87: ="27123" -> 27123 | E87: ="27123" -> 27123 | F87: Bodega Carrascal | G87: 5 | H87: 10100 | I87: 50500 | J87: 0 | K87: 5 | L87: 0
A88: 4Trade | B88: Balvi | C88: Revistero Haus Negro Balvi | D88: ="27124" -> 27124 | E88: ="27124" -> 27124 | F88: Bodega Carrascal | G88: 4 | H88: 10100 | I88: 40400 | J88: 0 | K88: 4 | L88: 0
A89: 4Trade | B89: Balvi | C89: Revistero News Blanco Balvi | D89: ="26968" -> 26968 | E89: ="26968" -> 26968 | F89: Bodega Carrascal | G89: 16 | H89: 12600 | I89: 201600 | J89: 0 | K89: 16 | L89: 0
A90: 4Trade | B90: Balvi | C90: Revistero News Negro Balvi | D90: ="26967" -> 26967 | E90: ="26967" -> 26967 | F90: Bodega Carrascal | G90: 6 | H90: 12600 | I90: 75600 | J90: 0 | K90: 6 | L90: 0
A91: 4Trade | B91: Balvi | C91: Soporte Nordik Mdf Pappers Blanco Balvi | D91: ="26969" -> 26969 | E91: ="26969" -> 26969 | F91: Bodega Carrascal | G91: 3 | H91: 15100 | I91: 45300 | J91: 0 | K91: 3 | L91: 0
A92: 4Trade | B92: Balvi | C92: Soporte Nordik Mdf Pattern Café Balvi | D92: ="26970" -> 26970 | E92: ="26970" -> 26970 | F92: Bodega Carrascal | G92: 6 | H92: 15100 | I92: 90600 | J92: 0 | K92: 6 | L92: 0
A93: 4Trade | B93: Balvi | C93: Soporte Nordik Mdf Pattern Negro Balvi | D93: ="27535" -> 27535 | E93: ="27535" -> 27535 | F93: Bodega Carrascal | G93: 5 | H93: 13084 | I93: 65420 | J93: 0 | K93: 5 | L93: 0
A94: 4Trade | B94: Balvi | C94: Tablero Madisson Magneticos X6 Balvi | D94: ="8430306257822" -> 8430306257822 | E94: ="25782" -> 25782 | F94: Bodega Carrascal | G94: 6 | H94: 4000 | I94: 24000 | J94: 0 | K94: 6 | L94: 0
A95: 4Trade | B95: Balvi | C95: Tablero Memories Balvi | D95: ="27016" -> 27016 | E95: ="27016" -> 27016 | F95: Bodega Carrascal | G95: 17 | H95: 10100 | I95: 171700 | J95: 0 | K95: 17 | L95: 0
A96: 4Trade | B96: Balvi | C96: Tablero Peg Balvi | D96: ="26966" -> 26966 | E96: ="26966" -> 26966 | F96: Bodega Carrascal | G96: 5 | H96: 15600 | I96: 78000 | J96: 0 | K96: 5 | L96: 0
A97: 4Trade | B97: Balvi | C97: Timer Y Reloj Digital Balvi | D97: ="8430306260181" -> 8430306260181 | E97: ="26018" -> 26018 | F97: Bodega Carrascal | G97: 14 | H97: 3500 | I97: 49000 | J97: 0 | K97: 14 | L97: 0
A98: Beauty Plus | B98: Beauty Jar | C98: SHAMPOO BRAVOCADO 250ML | D98: ="4751030830940" -> 4751030830940 | E98: ="4751030830940" -> 4751030830940 | F98: Bodega Carrascal | G98: 1 | H98: 5037 | I98: 5037 | J98: 0 | K98: 1 | L98: 0
A99: KW Chile | B99: Bergner | C99: ASADOR 36x23CM ALUMINIO FUNDIDO GRAVITY | D99: ="15916560879484" -> 15916560879484 | E99: ="BGMP-3306" -> BGMP-3306 | F99: Bodega Carrascal | G99: 8 | H99: 14264.8 | I99: 114118 | J99: 0 | K99: 8 | L99: 0
A100: KW Chile | B100: Bergner | C100: Sartén Aluminio Forjado 24cm Gravity Bergner | D100: ="BGMP-3302" -> BGMP-3302 | E100: ="BGMP-3302" -> BGMP-3302 | F100: Bodega Carrascal | G100: 1 | H100: 7850 | I100: 7850 | J100: 0 | K100: 1 | L100: 0
A101: KW Chile | B101: Bergner | C101: Sartén Infinity Copper 24cm Aluminio Forjado | D101: ="15888899205009" -> 15888899205009 | E101: ="BGIC-1002" -> BGIC-1002 | F101: Bodega Carrascal | G101: 1 | H101: 11034 | I101: 11034 | J101: 1 | K101: 0 | L101: 1
...

Sheet Propuestas Falabella regalable
C2: Marca | D2: Sku | E2: Grupo | F2: Descripcion | G2: Costo MLL | H2: Margen | I2: Utilidad UnionX | J2: P Etiqueta | K2: PVP | L2: Costo | M2: Costo Oferta
C3: Lhotse | D3: =VLOOKUP(F3,'Resumen Stock'!$B$4:$C$559,2,0) -> 1597086499840 | E3: Audifonos RM7 | F3: Audífonos Bluetooth RM7 Pro Blanco | G3: 5529.7 | H3: =1-(G3/M3) -> 0.37288259 | I3: =M3-G3 -> 3287.9471 | J3: 29990 | K3: 14990 | L3: =J3/1.19*0.7 -> 17641.176 | M3: =K3/1.19*0.7 -> 8817.6471
C4: Lhotse | D4: =VLOOKUP(F4,'Resumen Stock'!$B$4:$C$559,2,0) -> 1597098592591 | E4: Audifonos RM7 | F4: Audífonos Bluetooth RM7 Pro Negro | G4: 6248.4 | H4: =1-(G4/M4) -> 0.29137558 | I4: =M4-G4 -> 2569.2471 | J4: 29990 | K4: 14990 | L4: =J4/1.19*0.7 -> 17641.176 | M4: =K4/1.19*0.7 -> 8817.6471
C5: Lhotse | D5: =VLOOKUP(F5,'Resumen Stock'!$B$4:$C$559,2,0) -> 67898461965813 | E5: Parlante Bounce Mini | F5: Parlante Bounce Mini Black | G5: 4716.5 | H5: =1-(G5/M5) -> 0.55430517 | I5: =M5-G5 -> 5865.8529 | J5: 24990 | K5: 17990 | L5: =J5/1.19*0.7 -> 14700 | M5: =K5/1.19*0.7 -> 10582.353
C6: Lhotse | D6: =VLOOKUP(F6,'Resumen Stock'!$B$4:$C$559,2,0) -> 67898465380537 | E6: Parlante Bounce Mini | F6: Parlante Bounce Mini Blue | G6: 4710 | H6: =1-(G6/M6) -> 0.5549194 | I6: =M6-G6 -> 5872.3529 | J6: 24990 | K6: 17990 | L6: =J6/1.19*0.7 -> 14700 | M6: =K6/1.19*0.7 -> 10582.353
C7: Lhotse | D7: =VLOOKUP(F7,'Resumen Stock'!$B$4:$C$559,2,0) -> 67898466886403 | E7: Parlante Bounce Mini | F7: Parlante Bounce Mini Pink | G7: 4599 | H7: =1-(G7/M7) -> 0.56540856 | I7: =M7-G7 -> 5983.3529 | J7: 24990 | K7: 17990 | L7: =J7/1.19*0.7 -> 14700 | M7: =K7/1.19*0.7 -> 10582.353
C8: Lhotse | D8: =VLOOKUP(F8,'Resumen Stock'!$B$4:$C$559,2,0) -> 67898463643999 | E8: Parlante Bounce Mini | F8: Parlante Bounce Mini White | G8: 4490.1 | H8: =1-(G8/M8) -> 0.57569928 | I8: =M8-G8 -> 6092.2529 | J8: 24990 | K8: 17990 | L8: =J8/1.19*0.7 -> 14700 | M8: =K8/1.19*0.7 -> 10582.353
C9: Lhotse | D9: =VLOOKUP(F9,'Resumen Stock'!$B$4:$C$559,2,0) -> 67933835121467 | E9: Parlante TUNE | F9: Parlante TUNE UP AZUL | G9: 4817.4 | H9: =1-(G9/M9) -> 0.45366378 | I9: =M9-G9 -> 4000.2471 | J9: 21990 | K9: 14990 | L9: =J9/1.19*0.7 -> 12935.294 | M9: =K9/1.19*0.7 -> 8817.6471
C10: Lhotse | D10: =VLOOKUP(F10,'Resumen Stock'!$B$4:$C$559,2,0) -> 67933831843970 | E10: Parlante TUNE | F10: Parlante TUNE UP NEGRO | G10: 4870.8 | H10: =1-(G10/M10) -> 0.44760774 | I10: =M10-G10 -> 3946.8471 | J10: 21990 | K10: 14990 | L10: =J10/1.19*0.7 -> 12935.294 | M10: =K10/1.19*0.7 -> 8817.6471
C11: Lhotse | D11: =VLOOKUP(F11,'Resumen Stock'!$B$4:$C$559,2,0) -> 67933833934278 | E11: Parlante TUNE | F11: Parlante TUNE UP ROJO | G11: 4876.8 | H11: =1-(G11/M11) -> 0.44692728 | I11: =M11-G11 -> 3940.8471 | J11: 21990 | K11: 14990 | L11: =J11/1.19*0.7 -> 12935.294 | M11: =K11/1.19*0.7 -> 8817.6471
C12: Lhotse | D12: =VLOOKUP(F12,'Resumen Stock'!$B$4:$C$559,2,0) -> 67933835988925 | E12: Parlante TUNE | F12: Parlante TUNE UP VERDE | G12: 4803 | H12: =1-(G12/M12) -> 0.45529686 | I12: =M12-G12 -> 4014.6471 | J12: 21990 | K12: 14990 | L12: =J12/1.19*0.7 -> 12935.294 | M12: =K12/1.19*0.7 -> 8817.6471
C15: Marca | D15: Sku | E15: Grupo | F15: Descripcion | G15: Costo MLL | H15: Margen | I15: Utilidad UnionX | J15: P Etiqueta | K15: PVP | L15: Costo | M15: Costo Oferta | N15: Q unidades | O15: Utilidad UnionX
C16: Lhotse | E16: Combo RM7 + Tune | F16: Combo RM7 + Tune | G16: =G10+G4 -> 11119.2 | H16: =1-(G16/M16) -> 0.29964283 | I16: =M16-G16 -> 4757.2706 | J16: =J10+J4 -> 51980 | K16: 26990 | L16: =J16/1.19*0.7 -> 30576.471 | M16: =K16/1.19*0.7 -> 15876.471 | N16: 5000 | O16: =N16*I16 -> 23786353
C17: Lhotse | E17: Combo RM7 + Bounce | F17: Combo RM7 + Bounce | G17: =G5+G4 -> 10964.9 | H17: =1-(G17/M17) -> 0.30936162 | I17: =M17-G17 -> 4911.5706 | J17: =J5+J4 -> 54980 | K17: 26990 | L17: =J17/1.19*0.7 -> 32341.176 | M17: =K17/1.19*0.7 -> 15876.471 | N17: 5000 | O17: =N17*I17 -> 24557853
N25: 299990 | O25: 299990 | P25: 299990 | Q25: 299990 | R25: 299990 | W25: 129990 | X25: 149990 | Y25: 149990
N26: enero | O26: febrero | P26: marzo | Q26: abril | R26: mayo | S26: junio | T26: julio | U26: agosto | V26: septiembre | W26: octubre | X26: noviembre | Y26: diciembre
L27: Proyector | M27: Viejo | N27: x | O27: x | P27: x | Q27: x | R27: x | S27: x | T27: x | U27: x | V27: x | W27: x | X27: x | Y27: x
N28: x | O28: x | P28: x | Q28: x | R28: 99990
N30: 299990 | O30: 299990 | P30: 299990 | Q30: 299990 | R30: 199990 | W30: 129990 | X30: 149990 | Y30: 149990
M31: Nuevo | N31: x | O31: x | P31: x | Q31: x | R31: x | S31: x | T31: x | U31: x | V31: x | W31: x | X31: x | Y31: x
N32: x | O32: x | P32: x | Q32: x | R32: x
